Workbook

Sheet Instruction
A3: Instructions
B4: 1. Make a copy of the template
B5: 2. Overwrite the column A-C 'Investment Perf His' tab using your portfolio performance history(ideally >5 years)
B6: 3. Update 'Calculation results' tab following the instruction in the orange text box
B7: 4. Copy and paste table C5 to R25 into board paper.

Sheet Calculation results
S3: Accumulated return | V3: Annualised return | Y3: Volatility | Z3: Benchmark retunrs | AC3: Benchmark vol | AD3: Morningstar Category | AH3: Tracking error
E4: Fund vs BM. 5 year net returns. Fail if alpha<0 | F4: Fund vs peers. 5 year rank in Morningstar peer group. Fail if in 4th quartile | G4: Fund vs BM. 2 year net returns. Fail if alpha<0 | H4: Fund vs peers. 3 year rank in Morningstar peer group. Fail if in 4th quartile | I4: Annualised 2 year tracking error. Fail if >2x peer median TE | J4: Annualised 2 year volatility. Fail if >1.5x BM volatility | K4: Fail if <80% liquid in 21 business days | L4: Fail if not Approved/Investment Grade (Zenith, Lonsec), 3.5 (SQM) or Neutral (Morningstar) or higher | M4: Team (resourcing, skills, stability) | N4: Process (robust, disciplined, governance) | O4: Business (conflicts, support, stability) | P4: Product (viability, fees, capacity, concentration) | S4: 5 years | T4: 3 years | U4: 2 years | V4: 5 years | W4: 3 years | X4: 2 years | Y4: 2 years | Z4: 5 years | AA4: 3 years | AB4: 2 years | AC4: 2 years | AD4: 5 yr 4th Quartile Cut-off Return: | AE4: 3 yr 4th Quartile Cut-off Return: | AF4: 2 yr 4th Quartile Cut-off Return: | AG4: 2 yr Median tracking error: | AH4: 2 years Tracking error
D5: Overall Score (out of 100) | E5: 5yr Returns vs BM | F5: 5yr Rank vs Peers | G5: 3yr Returns vs BM | H5: 3yr Rank vs Peers | I5: Tracking Error | J5: Volatility | K5: Liquidity (Underlying) | L5: Ratings | M5: Team | N5: Process | O5: Business | P5: Product | R5: {=MAX(_xlfn._xlws.FILTER('Invert return series (5 years)'!B:B,'Invert return series (5 years)'!A:A='Calculation results'!C7))} -> 46022 | S5: =EDATE(R5,-60) -> 44196 | T5: =EDATE(R5,-36) -> 44926 | U5: =EDATE(R5,-24) -> 45291
E6: 0 | F6: 0 | G6: 0.2 | H6: 0.2 | I6: 0.05 | J6: 0.05 | K6: 0.1 | L6: 0.1 | M6: 0.1 | N6: 0.1 | O6: 0.05 | P6: 0.05 | Q6: Benchmark | R6: Morningstar Peer Group
C7: Aurora 0% Growth | D7: =SUMIF(E7:P7,CHAR(149),E$6:P$6) -> 0.9 | E7: =IF(V7>Z7,CHAR(149),"-") -> • | F7: =IF(V7>AD7,CHAR(149),"-") -> • | G7: =IF(W7>AA7,CHAR(149),"-") -> • | H7: =IF(W7>AE7,CHAR(149),"-") -> • | I7: =IF(AH7>2*AG7,"-",CHAR(149)) -> • | J7: =IF(Y7>1.5*AC7,"-",CHAR(149)) -> • | K7: • | L7: - | M7: • | N7: • | O7: • | P7: • | Q7: Morningstar AUS Con Tgt Alloc NR AUD | R7: Australia Fund Multisector Conservative | S7: {=PRODUCT(_xlfn._xlws.FILTER(1+'Invert return series (5 years)'!C$2:C$10000,('Invert return series (5 years)'!A$2:A$10000='Calculation results'!C7)*('Invert return series (5 years)'!B$2:B$10000>'Calculation results'!$S$5)*('Invert return series (5 years)'!B$2:B$10000<=$R$5)))} -> 1.1793661 | T7: {=PRODUCT(_xlfn._xlws.FILTER(1+'Invert return series (5 years)'!C$2:C$10000,('Invert return series (5 years)'!A$2:A$10000='Calculation results'!C7)*('Invert return series (5 years)'!B$2:B$10000>'Calculation results'!$T$5)*('Invert return series (5 years)'!B$2:B$10000<=$R$5)))} -> 1.1793661 | U7: {=PRODUCT(_xlfn._xlws.FILTER('Invert return series (5 years)'!C$2:C$10000+1,('Invert return series (5 years)'!A$2:A$10000='Calculation results'!C7)*('Invert return series (5 years)'!B$2:B$10000>'Calculation results'!$U$5)*('Invert return series (5 years)'!B$2:B$10000<=$R$5)))} -> 1.104915 | V7: =(PRODUCT(S7)^(0.2)-1) -> 0.033545802 | W7: =PRODUCT(T7)^(0.333333333)-1 -> 0.056532544 | X7: =(PRODUCT(U7)^(0.5)-1) -> 0.051149375 | Y7: {=STDEV(_xlfn._xlws.FILTER('Invert return series (5 years)'!C$2:C$1000+1,('Invert return series (5 years)'!A$2:A$1000='Calculation results'!C7)*('Invert return series (5 years)'!B$2:B$1000>'Calculation results'!$U$5)*('Invert return series (5 years)'!B$2:B$1000<=$R$5)))*SQRT(12)} -> 0.019056829 | Z7: {=_xlfn._xlws.FILTER('BM Data'!$B$7:$B$1000,'BM Data'!$A$7:$A$1000=Q7)/100} -> 0.01405189 | AA7: {=_xlfn._xlws.FILTER('BM Data'!$D$7:$D$1000,'BM Data'!$A$7:$A$1000=$Q7)/100} -> 0.04702102 | AB7: {=_xlfn._xlws.FILTER('BM Data'!$F$7:$F$1000,'BM Data'!$A$7:$A$1000=$Q7)/100} -> 0.04247839 | AC7: {=_xlfn._xlws.FILTER('BM Data'!G$7:G$1000,'BM Data'!$A$7:$A$1000=$Q7)/100} -> 0.02447929 | AD7: =VLOOKUP($R7,'Morningstar Category Data'!$A:$E,5,FALSE)/100 -> 0.02067251 | AE7: =VLOOKUP($R7,'Morningstar Category Data'!$A:$E,4,FALSE)/100 -> 0.05191326 | AF7: =VLOOKUP($R7,'Morningstar Category Data'!$A:$E,3,FALSE)/100 -> 0.04974302 | AG7: =VLOOKUP($R7,'Morningstar Category Data'!$I:$J,2,FALSE)/100 -> 0.01228132 | AH7: {=STDEV( _xlfn._xlws.FILTER( 'Invert return series (5 years)'!C$2:C$1000, ('Invert return series (5 years)'!A$2:A$1000='Calculation results'!C7) *('Invert return series (5 years)'!B$2:B$1000>'Calculation results'!$U$5)*('Invert return series (5 years)'!B$2:B$1000<=$R$5) ) - TRANSPOSE( _xlfn._xlws.FILTER( INDEX('BM Data'!$K$8:$BE$500, MATCH(Q7, 'BM Data'!$A$8:$A$500, 0), ), INDEX('BM Data'!$K$8:$BE$500, MATCH(Q7, 'BM Data'!$A$8:$A$500, 0), ) <> "" ))/100 )*SQRT(12)} -> 0.0090903348
C8: Aurora 100% Growth Portfolio | D8: =SUMIF(E8:P8,CHAR(149),E$6:P$6) -> 0.9 | E8: =IF(V8>Z8,CHAR(149),"-") -> - | F8: =IF(V8>AD8,CHAR(149),"-") -> • | G8: =IF(W8>AA8,CHAR(149),"-") -> • | H8: =IF(W8>AE8,CHAR(149),"-") -> • | I8: =IF(AH8>2*AG8,"-",CHAR(149)) -> • | J8: =IF(Y8>1.5*AC8,"-",CHAR(149)) -> • | K8: • | L8: - | M8: • | N8: • | O8: • | P8: • | Q8: Morningstar AUS Agg Tgt Alloc NR AUD | R8: Australia Fund Multisector Aggressive | S8: {=PRODUCT(_xlfn._xlws.FILTER(1+'Invert return series (5 years)'!C$2:C$10000,('Invert return series (5 years)'!A$2:A$10000='Calculation results'!C8)*('Invert return series (5 years)'!B$2:B$10000>'Calculation results'!$S$5)*('Invert return series (5 years)'!B$2:B$10000<=$R$5)))} -> 1.5828326 | T8: {=PRODUCT(_xlfn._xlws.FILTER(1+'Invert return series (5 years)'!C$2:C$10000,('Invert return series (5 years)'!A$2:A$10000='Calculation results'!C8)*('Invert return series (5 years)'!B$2:B$10000>'Calculation results'!$T$5)*('Invert return series (5 years)'!B$2:B$10000<=$R$5)))} -> 1.5828326 | U8: {=PRODUCT(_xlfn._xlws.FILTER('Invert return series (5 years)'!C$2:C$10000+1,('Invert return series (5 years)'!A$2:A$10000='Calculation results'!C8)*('Invert return series (5 years)'!B$2:B$10000>'Calculation results'!$U$5)*('Invert return series (5 years)'!B$2:B$10000<=$R$5)))} -> 1.369041 | V8: =(PRODUCT(S8)^(0.2)-1) -> 0.096192938 | W8: =PRODUCT(T8)^(0.33333)-1 -> 0.16540712 | X8: =(PRODUCT(U8)^(0.5)-1) -> 0.17006027 | Y8: {=STDEV(_xlfn._xlws.FILTER('Invert return series (5 years)'!C$2:C$1000+1,('Invert return series (5 years)'!A$2:A$1000='Calculation results'!C8)*('Invert return series (5 years)'!B$2:B$1000>'Calculation results'!$U$5)*('Invert return series (5 years)'!B$2:B$1000<=$R$5)))*SQRT(12)} -> 0.072349173 | Z8: {=_xlfn._xlws.FILTER('BM Data'!$B$7:$B$1000,'BM Data'!$A$7:$A$1000=Q8)/100} -> 0.10446274 | AA8: {=_xlfn._xlws.FILTER('BM Data'!$D$7:$D$1000,'BM Data'!$A$7:$A$1000=$Q8)/100} -> 0.14801448 | AB8: {=_xlfn._xlws.FILTER('BM Data'!$F$7:$F$1000,'BM Data'!$A$7:$A$1000=$Q8)/100} -> 0.14472671 | AC8: {=_xlfn._xlws.FILTER('BM Data'!G$7:G$1000,'BM Data'!$A$7:$A$1000=$Q8)/100} -> 0.0688133 | AD8: =VLOOKUP($R8,'Morningstar Category Data'!$A:$E,5,FALSE)/100 -> 0.08647114 | AE8: =VLOOKUP($R8,'Morningstar Category Data'!$A:$E,4,FALSE)/100 -> 0.12524835 | AF8: =VLOOKUP($R8,'Morningstar Category Data'!$A:$E,3,FALSE)/100 -> 0.12081514 | AG8: =VLOOKUP($R8,'Morningstar Category Data'!$I:$J,2,FALSE)/100 -> 0.0159729 | AH8: {=STDEV( _xlfn._xlws.FILTER( 'Invert return series (5 years)'!C$2:C$1000, ('Invert return series (5 years)'!A$2:A$1000='Calculation results'!C8) *('Invert return series (5 years)'!B$2:B$1000>'Calculation results'!$U$5)*('Invert return series (5 years)'!B$2:B$1000<=$R$5) ) - TRANSPOSE( _xlfn._xlws.FILTER( INDEX('BM Data'!$K$8:$BE$500, MATCH(Q8, 'BM Data'!$A$8:$A$500, 0), ), INDEX('BM Data'!$K$8:$BE$500, MATCH(Q8, 'BM Data'!$A$8:$A$500, 0), ) <> "" ))/100 )*SQRT(12)} -> 0.022565865
D10: Green > 60%
D11: Amber 50-59% | K11: • | L11: Pass
D12: Red < 50% | K12: – | L12: Fail
C13: Please note:
C14: Managed Portfolio scoring weights are defined in Investment Options Charter and Operational Guidelines October 2021.
C16: * Where portfolio's have an absolute return target tracking error score cannot be calculated. In these cases the Volatiliy weight doubles and increases from 5% to 10%
C17: ^ For portfolio's that do not have 5 yr track record the performance weighting of 2/3 years doubles from 10% to 20%.

Sheet Investment Perf His
A1: Portfolio Name | B1: Date | C1: Paste series below
A2: Aurora 0% Growth | B2: 44957 | C2: 0.02288292
A3: Aurora 0% Growth | B3: 44985 | C3: -0.00757107
A4: Aurora 0% Growth | B4: 45016 | C4: 0.01473816
A5: Aurora 0% Growth | B5: 45046 | C5: 0.00401853
A6: Aurora 0% Growth | B6: 45077 | C6: -0.00638449
A7: Aurora 0% Growth | B7: 45107 | C7: -0.00957917
A8: Aurora 0% Growth | B8: 45138 | C8: 0.00607261
A9: Aurora 0% Growth | B9: 45169 | C9: 0.00695855
A10: Aurora 0% Growth | B10: 45199 | C10: -0.00606397
A11: Aurora 0% Growth | B11: 45230 | C11: -0.00674147
A12: Aurora 0% Growth | B12: 45260 | C12: 0.02266398
A13: Aurora 0% Growth | B13: 45291 | C13: 0.02533541
... A73: Aurora 100% Growth Portfolio | B73: 46022 | C73: -0.00248887

Sheet Invert return series (5 years)
A1: Portfolio Name | B1: Date | C1: Paste series below | D1: Corrected order (most recent month at top)
A2: {=_xlfn.SORTBY('Investment Perf His'!A2:C8852,'Investment Perf His'!A2:A8852,1,'Investment Perf His'!B2:B8852,1)} -> Aurora 0% Growth | B2: 44957 | C2: 0.02288292
A3: Aurora 0% Growth | B3: 44985 | C3: -0.00757107
A4: Aurora 0% Growth | B4: 45016 | C4: 0.01473816
A5: Aurora 0% Growth | B5: 45046 | C5: 0.00401853
A6: Aurora 0% Growth | B6: 45077 | C6: -0.00638449
A7: Aurora 0% Growth | B7: 45107 | C7: -0.00957917
A8: Aurora 0% Growth | B8: 45138 | C8: 0.00607261
A9: Aurora 0% Growth | B9: 45169 | C9: 0.00695855
A10: Aurora 0% Growth | B10: 45199 | C10: -0.00606397
A11: Aurora 0% Growth | B11: 45230 | C11: -0.00674147
A12: Aurora 0% Growth | B12: 45260 | C12: 0.02266398 | H12: =_xlfn.STDEV.S(C14:C37)*SQRT(12) -> 0.019056829
A13: Aurora 0% Growth | B13: 45291 | C13: 0.02533541
A14: Aurora 0% Growth | B14: 45322 | C14: 0.00305986
A15: Aurora 0% Growth | B15: 45351 | C15: -0.00025378
A16: Aurora 0% Growth | B16: 45382 | C16: 0.01093866
A17: Aurora 0% Growth | B17: 45412 | C17: -0.00920594
A18: Aurora 0% Growth | B18: 45443 | C18: 0.00553179
A19: Aurora 0% Growth | B19: 45473 | C19: 0.00628667
A20: Aurora 0% Growth | B20: 45504 | C20: 0.01481509
A21: Aurora 0% Growth | B21: 45535 | C21: 0.0087324
A22: Aurora 0% Growth | B22: 45565 | C22: 0.00661086
A23: Aurora 0% Growth | B23: 45596 | C23: -0.00775096
A24: Aurora 0% Growth | B24: 45626 | C24: 0.00995131
... A73: Aurora 100% Growth Portfolio | B73: 46022 | C73: -0.00248887
A74: 0 | B74: 0 | C74: 0
A75: 0 | B75: 0 | C75: 0
A76: 0 | B76: 0 | C76: 0
A77: 0 | B77: 0 | C77: 0
A78: 0 | B78: 0 | C78: 0
A79: 0 | B79: 0 | C79: 0
A80: 0 | B80: 0 | C80: 0
A81: 0 | B81: 0 | C81: 0
A82: 0 | B82: 0 | C82: 0
A83: 0 | B83: 0 | C83: 0
A84: 0 | B84: 0 | C84: 0
A85: 0 | B85: 0 | C85: 0
... A8852: 0 | B8852: 0 | C8852: 0

Sheet Invert return series (3 years)
A1: Paste series below | B1: Corrected order (most recent month at top)
A2: -0.011368317 | B2: =A37 -> -0.019161857
A3: -0.00083905231 | B3: =A36 -> -0.009174655
A4: 0.011113253 | B4: =A35 -> -0.030244762
A5: -0.0037259254 | B5: =A34 -> 0.032136723
A6: 0.018776878 | B6: =A33 -> -0.016170345
A7: -0.0050125762 | B7: =A32 -> -0.032049431
A8: 0.0083382064 | B8: =A31 -> 0.020472374
A9: 0.0076003792 | B9: =A30 -> 0.023159597
A10: 0.01734194 | B10: =A29 -> -0.019686065
A11: 0.0087494403 | B11: =A28 -> 0.028205909
A12: 0.010123351 | B12: =A27 -> -0.0080229702
A13: -0.016858346 | B13: =A26 -> 0.015557598
A14: 0.015097839 | B14: =A25 -> 0.0087650403
A15: 0.0091940259 | B15: =A24 -> -0.0039882307
A16: 0.0072424781 | B16: =A23 -> 0.0049977342
A17: 0.027364197 | B17: =A22 -> 0.0085679419
A18: 0.032476107 | B18: =A21 -> 0.00099608678
A19: -0.01231937 | B19: =A20 -> -0.01773787
A20: -0.01773787 | B20: =A19 -> -0.01231937
A21: 0.00099608678 | B21: =A18 -> 0.032476107
A22: 0.0085679419 | B22: =A17 -> 0.027364197
A23: 0.0049977342 | B23: =A16 -> 0.0072424781
A24: -0.0039882307 | B24: =A15 -> 0.0091940259
A25: 0.0087650403 | B25: =A14 -> 0.015097839
A26: 0.015557598 | B26: =A13 -> -0.016858346
A27: -0.0080229702 | B27: =A12 -> 0.010123351
A28: 0.028205909 | B28: =A11 -> 0.0087494403
A29: -0.019686065 | B29: =A10 -> 0.01734194
A30: 0.023159597 | B30: =A9 -> 0.0076003792
A31: 0.020472374 | B31: =A8 -> 0.0083382064
A32: -0.032049431 | B32: =A7 -> -0.0050125762
A33: -0.016170345 | B33: =A6 -> 0.018776878
A34: 0.032136723 | B34: =A5 -> -0.0037259254
A35: -0.030244762 | B35: =A4 -> 0.011113253
A36: -0.009174655 | B36: =A3 -> -0.00083905231
A37: -0.019161857 | B37: =A2 -> -0.011368317

Sheet Invert return series (2 years)
A1: Paste series below | B1: Corrected order (most recent month at top)
A2: 0.03070665 | B2: =A25 -> 0.001265213
A3: -0.057978741 | B3: =A24 -> -0.0011540287
A4: 0.049354245 | B4: =A23 -> 0.036626656
A5: 0.005765681 | B5: =A22 -> 0.025042679
A6: -0.026776591 | B6: =A21 -> 0.041179419
A7: 0.018036866 | B7: =A20 -> 0.041752524
A8: 0.02051514 | B8: =A19 -> 0.015407347
A9: 0.017416475 | B9: =A18 -> -0.0088147818
A10: 0.034338148 | B10: =A17 -> 0.046012452
A11: 0.00093871301 | B11: =A16 -> 0.035364225
A12: -0.01603754 | B12: =A15 -> -0.0063277413
A13: -0.10878218 | B13: =A14 -> 0.0204754
A14: 0.0204754 | B14: =A13 -> -0.10878218
A15: -0.0063277413 | B15: =A12 -> -0.01603754
A16: 0.035364225 | B16: =A11 -> 0.00093871301
A17: 0.046012452 | B17: =A10 -> 0.034338148
A18: -0.0088147818 | B18: =A9 -> 0.017416475
A19: 0.015407347 | B19: =A8 -> 0.02051514
A20: 0.041752524 | B20: =A7 -> 0.018036866
A21: 0.041179419 | B21: =A6 -> -0.026776591
A22: 0.025042679 | B22: =A5 -> 0.005765681
A23: 0.036626656 | B23: =A4 -> 0.049354245
A24: -0.0011540287 | B24: =A3 -> -0.057978741
A25: 0.001265213 | B25: =A2 -> 0.03070665

Sheet Manual Calc (5 years)
B1: Return Series | D1: Investment Option | F1: Investment option monthly returns> | G1: Month 1 | I1: Month 2 | K1: Month 3 | M1: Month 4 | O1: Month 5 | Q1: Month 6 | S1: Month 7 | U1: Month 8 | W1: Month 9 | Y1: Month 10 | AA1: Month 11 | AC1: Month 12 | AE1: Month 13 | AG1: Month 14 | AI1: Month 15 | AK1: Month 16 | AM1: Month 17 | AO1: Month 18 | AQ1: Month 19 | AS1: Month 20 | AU1: Month 21 | AW1: Month 22 | AY1: Month 23 | BA1: Month 24
A2: Month 60 | B2: ='Invert return series (5 years)'!$D2 -> 0 | C2: =(1+B2) -> 1 | D2: 5 yr annualised return: | E2: {=(PRODUCT(1+$B$2:$B$61)^(0.2)-1)*100} -> 0 | G2: =$B25*100 -> 0 | I2: =$B24*100 -> 0 | K2: =$B23*100 -> 0 | M2: =$B22*100 -> 0 | O2: =$B21*100 -> 0 | Q2: =$B20*100 -> 0 | S2: =$B19*100 -> 0 | U2: =$B18*100 -> 0 | W2: =$B17*100 -> 0 | Y2: =$B16*100 -> 0 | AA2: =$B15*100 -> 0 | AC2: =$B14*100 -> 0 | AE2: =$B13*100 -> 0 | AG2: =$B12*100 -> 0 | AI2: =$B11*100 -> 0 | AK2: =$B10*100 -> 0 | AM2: =$B9*100 -> 0 | AO2: =$B8*100 -> 0 | AQ2: =$B7*100 -> 0 | AS2: =$B6*100 -> 0 | AU2: =$B5*100 -> 0 | AW2: =$B4*100 -> 0 | AY2: =$B3*100 -> 0 | BA2: =$B2*100 -> 0
A3: Month 59 | B3: ='Invert return series (5 years)'!$D3 -> 0 | C3: =(1+B3) -> 1 | D3: 3 yr annualised return: | E3: {=(PRODUCT(1+$B$2:$B$37)^(0.333333333)-1)*100} -> 0 | F3: Benchmark monthly returns> | G3: =INDEX('BM Data'!$K$7:$BE$260,MATCH('Manual Calc (5 years)'!$F7,'BM Data'!$A$7:$A$260,0),MATCH('Manual Calc (5 years)'!G$1,'BM Data'!$K$1:$BE$1,0)) -> 0.97442 | I3: =INDEX('BM Data'!$K$7:$BE$260,MATCH('Manual Calc (5 years)'!$F7,'BM Data'!$A$7:$A$260,0),MATCH('Manual Calc (5 years)'!I$1,'BM Data'!$K$1:$BE$1,0)) -> 1.46685 | K3: =INDEX('BM Data'!$K$7:$BE$260,MATCH('Manual Calc (5 years)'!$F7,'BM Data'!$A$7:$A$260,0),MATCH('Manual Calc (5 years)'!K$1,'BM Data'!$K$1:$BE$1,0)) -> 2.01317 | M3: =INDEX('BM Data'!$K$7:$BE$260,MATCH('Manual Calc (5 years)'!$F7,'BM Data'!$A$7:$A$260,0),MATCH('Manual Calc (5 years)'!M$1,'BM Data'!$K$1:$BE$1,0)) -> -2.38612 | O3: =INDEX('BM Data'!$K$7:$BE$260,MATCH('Manual Calc (5 years)'!$F7,'BM Data'!$A$7:$A$260,0),MATCH('Manual Calc (5 years)'!O$1,'BM Data'!$K$1:$BE$1,0)) -> 1.09816 | Q3: =INDEX('BM Data'!$K$7:$BE$260,MATCH('Manual Calc (5 years)'!$F7,'BM Data'!$A$7:$A$260,0),MATCH('Manual Calc (5 years)'!Q$1,'BM Data'!$K$1:$BE$1,0)) -> 0.99444 | S3: =INDEX('BM Data'!$K$7:$BE$260,MATCH('Manual Calc (5 years)'!$F7,'BM Data'!$A$7:$A$260,0),MATCH('Manual Calc (5 years)'!S$1,'BM Data'!$K$1:$BE$1,0)) -> 2.71493 | U3: =INDEX('BM Data'!$K$7:$BE$260,MATCH('Manual Calc (5 years)'!$F7,'BM Data'!$A$7:$A$260,0),MATCH('Manual Calc (5 years)'!U$1,'BM Data'!$K$1:$BE$1,0)) -> 0.66696 | W3: =INDEX('BM Data'!$K$7:$BE$260,MATCH('Manual Calc (5 years)'!$F7,'BM Data'!$A$7:$A$260,0),MATCH('Manual Calc (5 years)'!W$1,'BM Data'!$K$1:$BE$1,0)) -> 1.18405 | Y3: =INDEX('BM Data'!$K$7:$BE$260,MATCH('Manual Calc (5 years)'!$F7,'BM Data'!$A$7:$A$260,0),MATCH('Manual Calc (5 years)'!Y$1,'BM Data'!$K$1:$BE$1,0)) -> -0.67899 | AA3: =INDEX('BM Data'!$K$7:$BE$260,MATCH('Manual Calc (5 years)'!$F7,'BM Data'!$A$7:$A$260,0),MATCH('Manual Calc (5 years)'!AA$1,'BM Data'!$K$1:$BE$1,0)) -> 2.41574 | AC3: =INDEX('BM Data'!$K$7:$BE$260,MATCH('Manual Calc (5 years)'!$F7,'BM Data'!$A$7:$A$260,0),MATCH('Manual Calc (5 years)'!AC$1,'BM Data'!$K$1:$BE$1,0)) -> -0.67086 | AE3: =INDEX('BM Data'!$K$7:$BE$260,MATCH('Manual Calc (5 years)'!$F7,'BM Data'!$A$7:$A$260,0),MATCH('Manual Calc (5 years)'!AE$1,'BM Data'!$K$1:$BE$1,0)) -> 1.87484 | AG3: =INDEX('BM Data'!$K$7:$BE$260,MATCH('Manual Calc (5 years)'!$F7,'BM Data'!$A$7:$A$260,0),MATCH('Manual Calc (5 years)'!AG$1,'BM Data'!$K$1:$BE$1,0)) -> -0.37671 | AI3: =INDEX('BM Data'!$K$7:$BE$260,MATCH('Manual Calc (5 years)'!$F7,'BM Data'!$A$7:$A$260,0),MATCH('Manual Calc (5 years)'!AI$1,'BM Data'!$K$1:$BE$1,0)) -> -1.78595 | AK3: =INDEX('BM Data'!$K$7:$BE$260,MATCH('Manual Calc (5 years)'!$F7,'BM Data'!$A$7:$A$260,0),MATCH('Manual Calc (5 years)'!AK$1,'BM Data'!$K$1:$BE$1,0)) -> 1.08211 | AM3: =INDEX('BM Data'!$K$7:$BE$260,MATCH('Manual Calc (5 years)'!$F7,'BM Data'!$A$7:$A$260,0),MATCH('Manual Calc (5 years)'!AM$1,'BM Data'!$K$1:$BE$1,0)) -> 2.20645 | AO3: =INDEX('BM Data'!$K$7:$BE$260,MATCH('Manual Calc (5 years)'!$F7,'BM Data'!$A$7:$A$260,0),MATCH('Manual Calc (5 years)'!AO$1,'BM Data'!$K$1:$BE$1,0)) -> 1.40935 | AQ3: =INDEX('BM Data'!$K$7:$BE$260,MATCH('Manual Calc (5 years)'!$F7,'BM Data'!$A$7:$A$260,0),MATCH('Manual Calc (5 years)'!AQ$1,'BM Data'!$K$1:$BE$1,0)) -> 1.21245 | AS3: =INDEX('BM Data'!$K$7:$BE$260,MATCH('Manual Calc (5 years)'!$F7,'BM Data'!$A$7:$A$260,0),MATCH('Manual Calc (5 years)'!AS$1,'BM Data'!$K$1:$BE$1,0)) -> 1.42229 | AU3: =INDEX('BM Data'!$K$7:$BE$260,MATCH('Manual Calc (5 years)'!$F7,'BM Data'!$A$7:$A$260,0),MATCH('Manual Calc (5 years)'!AU$1,'BM Data'!$K$1:$BE$1,0)) -> 0.66659 | AW3: =INDEX('BM Data'!$K$7:$BE$260,MATCH('Manual Calc (5 years)'!$F7,'BM Data'!$A$7:$A$260,0),MATCH('Manual Calc (5 years)'!AW$1,'BM Data'!$K$1:$BE$1,0)) -> 1.18844 | AY3: =INDEX('BM Data'!$K$7:$BE$260,MATCH('Manual Calc (5 years)'!$F7,'BM Data'!$A$7:$A$260,0),MATCH('Manual Calc (5 years)'!AY$1,'BM Data'!$K$1:$BE$1,0)) -> -0.60468 | BA3: =INDEX('BM Data'!$K$7:$BE$260,MATCH('Manual Calc (5 years)'!$F7,'BM Data'!$A$7:$A$260,0),MATCH('Manual Calc (5 years)'!BA$1,'BM Data'!$K$1:$BE$1,0)) -> 0.05682
A4: Month 58 | B4: ='Invert return series (5 years)'!$D4 -> 0 | C4: =(1+B4) -> 1 | D4: 2 yr annualised vol: | E4: =(STDEV($B$2:$B$25)*SQRT(12))*100 -> 0 | F4: Monthly Excess> | G4: =G2-G3 -> -0.97442 | I4: =I2-I3 -> -1.46685 | K4: =K2-K3 -> -2.01317 | M4: =M2-M3 -> 2.38612 | O4: =O2-O3 -> -1.09816 | Q4: =Q2-Q3 -> -0.99444 | S4: =S2-S3 -> -2.71493 | U4: =U2-U3 -> -0.66696 | W4: =W2-W3 -> -1.18405 | Y4: =Y2-Y3 -> 0.67899 | AA4: =AA2-AA3 -> -2.41574 | AC4: =AC2-AC3 -> 0.67086 | AE4: =AE2-AE3 -> -1.87484 | AG4: =AG2-AG3 -> 0.37671 | AI4: =AI2-AI3 -> 1.78595 | AK4: =AK2-AK3 -> -1.08211 | AM4: =AM2-AM3 -> -2.20645 | AO4: =AO2-AO3 -> -1.40935 | AQ4: =AQ2-AQ3 -> -1.21245 | AS4: =AS2-AS3 -> -1.42229 | AU4: =AU2-AU3 -> -0.66659 | AW4: =AW2-AW3 -> -1.18844 | AY4: =AY2-AY3 -> 0.60468 | BA4: =BA2-BA3 -> -0.05682
A5: Month 57 | B5: ='Invert return series (5 years)'!$D5 -> 0 | C5: =(1+B5) -> 1 | F5: Tracking error | G5: =STDEV(G4,I4,K4,M4,O4,Q4,S4,U4,W4,Y4,AA4,AC4,AE4,AG4,AI4,AK4,AM4,AO4,AQ4,AS4,AU4,AW4,AY4,BA4)*SQRT(12) -> 4.4455966
A6: Month 56 | B6: ='Invert return series (5 years)'!$D6 -> 0 | C6: =(1+B6) -> 1
A7: Month 55 | B7: ='Invert return series (5 years)'!$D7 -> 0 | C7: =(1+B7) -> 1 | D7: Benchmark: | F7: Morningstar AUS Balance Tgt Alloc NR AUD
A8: Month 54 | B8: ='Invert return series (5 years)'!$D8 -> 0 | C8: =(1+B8) -> 1 | D8: 5 yr annualised return: | E8: =VLOOKUP($F$7,'BM Data'!$A:$G,2,FALSE) -> 5.607414
A9: Month 53 | B9: ='Invert return series (5 years)'!$D9 -> 0 | C9: =(1+B9) -> 1 | D9: 3 yr annualised return: | E9: =VLOOKUP($F$7,'BM Data'!$A:$G,4,FALSE) -> 9.72249
A10: Month 52 | B10: ='Invert return series (5 years)'!$D10 -> 0 | C10: =(1+B10) -> 1 | D10: 2 yr annualised vol: | E10: =VLOOKUP($F$7,'BM Data'!$A:$G,7,FALSE) -> 4.445597
A11: Month 51 | B11: ='Invert return series (5 years)'!$D11 -> 0 | C11: =(1+B11) -> 1
A12: Month 50 | B12: ='Invert return series (5 years)'!$D12 -> 0 | C12: =(1+B12) -> 1
A13: Month 49 | B13: ='Invert return series (5 years)'!$D13 -> 0 | C13: =(1+B13) -> 1 | D13: Morningstar Category: | F13: Australia Fund Multisector Balanced
A14: Month 48 | B14: ='Invert return series (5 years)'!$D14 -> 0 | C14: =(1+B14) -> 1 | D14: 5 yr 4th Quartile Cut-off Return: | E14: =VLOOKUP($F$13,'Morningstar Category Data'!$A:$E,5,FALSE) -> 5.229288
A15: Month 47 | B15: ='Invert return series (5 years)'!$D15 -> 0 | C15: =(1+B15) -> 1 | D15: 3 yr 4th Quartile Cut-off Return: | E15: =VLOOKUP($F$13,'Morningstar Category Data'!$A:$E,4,FALSE) -> 8.046388
A16: Month 46 | B16: ='Invert return series (5 years)'!$D16 -> 0 | C16: =(1+B16) -> 1 | D16: 2 yr Median tracking error: | E16: =VLOOKUP($F$13,'Morningstar Category Data'!$I:$J,2,FALSE) -> 1.139196
A17: Month 45 | B17: ='Invert return series (5 years)'!$D17 -> 0 | C17: =(1+B17) -> 1
A18: Month 44 | B18: ='Invert return series (5 years)'!$D18 -> 0 | C18: =(1+B18) -> 1
A19: Month 43 | B19: ='Invert return series (5 years)'!$D19 -> 0 | C19: =(1+B19) -> 1
A20: Month 42 | B20: ='Invert return series (5 years)'!$D20 -> 0 | C20: =(1+B20) -> 1
A21: Month 41 | B21: ='Invert return series (5 years)'!$D21 -> 0 | C21: =(1+B21) -> 1
A22: Month 40 | B22: ='Invert return series (5 years)'!$D22 -> 0 | C22: =(1+B22) -> 1
A23: Month 39 | B23: ='Invert return series (5 years)'!$D23 -> 0 | C23: =(1+B23) -> 1
A24: Month 38 | B24: ='Invert return series (5 years)'!$D24 -> 0 | C24: =(1+B24) -> 1
A25: Month 37 | B25: ='Invert return series (5 years)'!$D25 -> 0 | C25: =(1+B25) -> 1
A26: Month 36 | B26: ='Invert return series (5 years)'!$D26 -> 0 | C26: =(1+B26) -> 1
A27: Month 35 | B27: ='Invert return series (5 years)'!$D27 -> 0 | C27: =(1+B27) -> 1
A28: Month 34 | B28: ='Invert return series (5 years)'!$D28 -> 0 | C28: =(1+B28) -> 1
... A61: Month 1 | B61: ='Invert return series (5 years)'!$D61 -> 0 | C61: =(1+B61) -> 1
A64: Scoring Summary
A65: Fund vs BM. 5 year net returns. Fail if alpha<0 | B65: Fund vs peers. 5 year rank in Morningstar peer group. Fail if in 4th quartile | C65: Fund vs BM. 3 year net returns. Fail if alpha<0 | D65: Fund vs peers. 3 year rank in Morningstar peer group. Fail if in 4th quartile | E65: Annualised 2 year tracking error. Fail if >2x peer median TE | F65: Annualised 2 year volatility. Fail if >1.5x BM volatility | G65: Fail if <80% liquid in 21 business days | H65: Fail if not Approved/Investment Grade (Zenith, Lonsec), 3.5 (SQM) or Neutral (Morningstar) or higher | I65: Team (resourcing, skills, stability) | J65: Process (robust, disciplined, governance) | K65: Business (conflicts, support, stability) | L65: Product (viability, fees, capacity, concentration) | M65: Score | N65: Final Rating
A66: =IF(E2>E8,10,"-") -> - | B66: =IF(E2>E14,10,"-") -> - | C66: =IF(E3>E9,10,"-") -> - | D66: =IF(E3>E15,10,"-") -> - | E66: =IF(G5>(2*E16),"-",5) -> - | F66: =IF(E4>(1.5*E10),"-",5) -> 5 | G66: 10 | I66: 10 | J66: 10 | K66: 5 | L66: 5 | M66: =SUM(A66:L66) -> 45 | N66: =IF(M66<50,"Red",IF(M66>60,"Green","Amber")) -> Red

Sheet Manual Calc (3 years)
B1: Return Series | D1: Investment Option | F1: Investment option monthly returns> | G1: Month 1 | I1: Month 2 | K1: Month 3 | M1: Month 4 | O1: Month 5 | Q1: Month 6 | S1: Month 7 | U1: Month 8 | W1: Month 9 | Y1: Month 10 | AA1: Month 11 | AC1: Month 12 | AE1: Month 13 | AG1: Month 14 | AI1: Month 15 | AK1: Month 16 | AM1: Month 17 | AO1: Month 18 | AQ1: Month 19 | AS1: Month 20 | AU1: Month 21 | AW1: Month 22 | AY1: Month 23 | BA1: Month 24
A2: Month 36 | B2: ='Invert return series (3 years)'!$B2 -> -0.019161857 | D2: 3 yr annualised return: | E2: {=(PRODUCT(1+$B$2:$B$37)^(0.333333333)-1)*100} -> 3.5512209 | G2: =$B25*100 -> 1.5097839 | I2: =$B24*100 -> 0.91940259 | K2: =$B23*100 -> 0.72424781 | M2: =$B22*100 -> 2.7364197 | O2: =$B21*100 -> 3.2476107 | Q2: =$B20*100 -> -1.231937 | S2: =$B19*100 -> -1.773787 | U2: =$B18*100 -> 0.099608678 | W2: =$B17*100 -> 0.85679419 | Y2: =$B16*100 -> 0.49977342 | AA2: =$B15*100 -> -0.39882307 | AC2: =$B14*100 -> 0.87650403 | AE2: =$B13*100 -> 1.5557598 | AG2: =$B12*100 -> -0.80229702 | AI2: =$B11*100 -> 2.8205909 | AK2: =$B10*100 -> -1.9686065 | AM2: =$B9*100 -> 2.3159597 | AO2: =$B8*100 -> 2.0472374 | AQ2: =$B7*100 -> -3.2049431 | AS2: =$B6*100 -> -1.6170345 | AU2: =$B5*100 -> 3.2136723 | AW2: =$B4*100 -> -3.0244762 | AY2: =$B3*100 -> -0.9174655 | BA2: =$B2*100 -> -1.9161857
A3: Month 35 | B3: ='Invert return series (3 years)'!$B3 -> -0.009174655 | D3: 2 yr annualised vol: | E3: =(STDEV($B$2:$B$25)*SQRT(12))*100 -> 6.768104 | F3: Benchmark monthly returns> | G3: =INDEX('BM Data'!$K$7:$BE$260,MATCH('Manual Calc (3 years)'!$F7,'BM Data'!$A$7:$A$260,0),MATCH('Manual Calc (3 years)'!G$1,'BM Data'!$K$1:$BE$1,0)) -> 0.59675 | I3: =INDEX('BM Data'!$K$7:$BE$260,MATCH('Manual Calc (3 years)'!$F7,'BM Data'!$A$7:$A$260,0),MATCH('Manual Calc (3 years)'!I$1,'BM Data'!$K$1:$BE$1,0)) -> 0.67652 | K3: =INDEX('BM Data'!$K$7:$BE$260,MATCH('Manual Calc (3 years)'!$F7,'BM Data'!$A$7:$A$260,0),MATCH('Manual Calc (3 years)'!K$1,'BM Data'!$K$1:$BE$1,0)) -> 1.58729 | M3: =INDEX('BM Data'!$K$7:$BE$260,MATCH('Manual Calc (3 years)'!$F7,'BM Data'!$A$7:$A$260,0),MATCH('Manual Calc (3 years)'!M$1,'BM Data'!$K$1:$BE$1,0)) -> -2.0119 | O3: =INDEX('BM Data'!$K$7:$BE$260,MATCH('Manual Calc (3 years)'!$F7,'BM Data'!$A$7:$A$260,0),MATCH('Manual Calc (3 years)'!O$1,'BM Data'!$K$1:$BE$1,0)) -> 0.81376 | Q3: =INDEX('BM Data'!$K$7:$BE$260,MATCH('Manual Calc (3 years)'!$F7,'BM Data'!$A$7:$A$260,0),MATCH('Manual Calc (3 years)'!Q$1,'BM Data'!$K$1:$BE$1,0)) -> 0.80348 | S3: =INDEX('BM Data'!$K$7:$BE$260,MATCH('Manual Calc (3 years)'!$F7,'BM Data'!$A$7:$A$260,0),MATCH('Manual Calc (3 years)'!S$1,'BM Data'!$K$1:$BE$1,0)) -> 2.22882 | U3: =INDEX('BM Data'!$K$7:$BE$260,MATCH('Manual Calc (3 years)'!$F7,'BM Data'!$A$7:$A$260,0),MATCH('Manual Calc (3 years)'!U$1,'BM Data'!$K$1:$BE$1,0)) -> 0.82534 | W3: =INDEX('BM Data'!$K$7:$BE$260,MATCH('Manual Calc (3 years)'!$F7,'BM Data'!$A$7:$A$260,0),MATCH('Manual Calc (3 years)'!W$1,'BM Data'!$K$1:$BE$1,0)) -> 0.94076 | Y3: =INDEX('BM Data'!$K$7:$BE$260,MATCH('Manual Calc (3 years)'!$F7,'BM Data'!$A$7:$A$260,0),MATCH('Manual Calc (3 years)'!Y$1,'BM Data'!$K$1:$BE$1,0)) -> -0.94336 | AA3: =INDEX('BM Data'!$K$7:$BE$260,MATCH('Manual Calc (3 years)'!$F7,'BM Data'!$A$7:$A$260,0),MATCH('Manual Calc (3 years)'!AA$1,'BM Data'!$K$1:$BE$1,0)) -> 1.77574 | AC3: =INDEX('BM Data'!$K$7:$BE$260,MATCH('Manual Calc (3 years)'!$F7,'BM Data'!$A$7:$A$260,0),MATCH('Manual Calc (3 years)'!AC$1,'BM Data'!$K$1:$BE$1,0)) -> -0.45227 | AE3: =INDEX('BM Data'!$K$7:$BE$260,MATCH('Manual Calc (3 years)'!$F7,'BM Data'!$A$7:$A$260,0),MATCH('Manual Calc (3 years)'!AE$1,'BM Data'!$K$1:$BE$1,0)) -> 1.28107 | AG3: =INDEX('BM Data'!$K$7:$BE$260,MATCH('Manual Calc (3 years)'!$F7,'BM Data'!$A$7:$A$260,0),MATCH('Manual Calc (3 years)'!AG$1,'BM Data'!$K$1:$BE$1,0)) -> 0.10692 | AI3: =INDEX('BM Data'!$K$7:$BE$260,MATCH('Manual Calc (3 years)'!$F7,'BM Data'!$A$7:$A$260,0),MATCH('Manual Calc (3 years)'!AI$1,'BM Data'!$K$1:$BE$1,0)) -> -1.00802 | AK3: =INDEX('BM Data'!$K$7:$BE$260,MATCH('Manual Calc (3 years)'!$F7,'BM Data'!$A$7:$A$260,0),MATCH('Manual Calc (3 years)'!AK$1,'BM Data'!$K$1:$BE$1,0)) -> 1.18781 | AM3: =INDEX('BM Data'!$K$7:$BE$260,MATCH('Manual Calc (3 years)'!$F7,'BM Data'!$A$7:$A$260,0),MATCH('Manual Calc (3 years)'!AM$1,'BM Data'!$K$1:$BE$1,0)) -> 1.2941 | AO3: =INDEX('BM Data'!$K$7:$BE$260,MATCH('Manual Calc (3 years)'!$F7,'BM Data'!$A$7:$A$260,0),MATCH('Manual Calc (3 years)'!AO$1,'BM Data'!$K$1:$BE$1,0)) -> 1.07077 | AQ3: =INDEX('BM Data'!$K$7:$BE$260,MATCH('Manual Calc (3 years)'!$F7,'BM Data'!$A$7:$A$260,0),MATCH('Manual Calc (3 years)'!AQ$1,'BM Data'!$K$1:$BE$1,0)) -> 0.71495 | AS3: =INDEX('BM Data'!$K$7:$BE$260,MATCH('Manual Calc (3 years)'!$F7,'BM Data'!$A$7:$A$260,0),MATCH('Manual Calc (3 years)'!AS$1,'BM Data'!$K$1:$BE$1,0)) -> 1.06078 | AU3: =INDEX('BM Data'!$K$7:$BE$260,MATCH('Manual Calc (3 years)'!$F7,'BM Data'!$A$7:$A$260,0),MATCH('Manual Calc (3 years)'!AU$1,'BM Data'!$K$1:$BE$1,0)) -> 0.46655 | AW3: =INDEX('BM Data'!$K$7:$BE$260,MATCH('Manual Calc (3 years)'!$F7,'BM Data'!$A$7:$A$260,0),MATCH('Manual Calc (3 years)'!AW$1,'BM Data'!$K$1:$BE$1,0)) -> 0.85046 | AY3: =INDEX('BM Data'!$K$7:$BE$260,MATCH('Manual Calc (3 years)'!$F7,'BM Data'!$A$7:$A$260,0),MATCH('Manual Calc (3 years)'!AY$1,'BM Data'!$K$1:$BE$1,0)) -> -0.52841 | BA3: =INDEX('BM Data'!$K$7:$BE$260,MATCH('Manual Calc (3 years)'!$F7,'BM Data'!$A$7:$A$260,0),MATCH('Manual Calc (3 years)'!BA$1,'BM Data'!$K$1:$BE$1,0)) -> -0.0883
A4: Month 34 | B4: ='Invert return series (3 years)'!$B4 -> -0.030244762 | F4: Monthly Excess> | G4: =G2-G3 -> 0.91303386 | I4: =I2-I3 -> 0.24288259 | K4: =K2-K3 -> -0.86304219 | M4: =M2-M3 -> 4.7483197 | O4: =O2-O3 -> 2.4338507 | Q4: =Q2-Q3 -> -2.035417 | S4: =S2-S3 -> -4.002607 | U4: =U2-U3 -> -0.72573132 | W4: =W2-W3 -> -0.083965811 | Y4: =Y2-Y3 -> 1.4431334 | AA4: =AA2-AA3 -> -2.1745631 | AC4: =AC2-AC3 -> 1.328774 | AE4: =AE2-AE3 -> 0.27468984 | AG4: =AG2-AG3 -> -0.90921702 | AI4: =AI2-AI3 -> 3.8286109 | AK4: =AK2-AK3 -> -3.1564165 | AM4: =AM2-AM3 -> 1.0218597 | AO4: =AO2-AO3 -> 0.97646737 | AQ4: =AQ2-AQ3 -> -3.9198931 | AS4: =AS2-AS3 -> -2.6778145 | AU4: =AU2-AU3 -> 2.7471223 | AW4: =AW2-AW3 -> -3.8749362 | AY4: =AY2-AY3 -> -0.3890555 | BA4: =BA2-BA3 -> -1.8278857
A5: Month 33 | B5: ='Invert return series (3 years)'!$B5 -> 0.032136723 | F5: Tracking error | G5: =STDEV(G4,I4,K4,M4,O4,Q4,S4,U4,W4,Y4,AA4,AC4,AE4,AG4,AI4,AK4,AM4,AO4,AQ4,AS4,AU4,AW4,AY4,BA4)*SQRT(12) -> 8.3499603
A6: Month 32 | B6: ='Invert return series (3 years)'!$B6 -> -0.016170345
A7: Month 31 | B7: ='Invert return series (3 years)'!$B7 -> -0.032049431 | D7: Benchmark: | F7: Morningstar AUS Mod Tgt Alloc NR AUD
A8: Month 30 | B8: ='Invert return series (3 years)'!$B8 -> 0.020472374 | D8: 3 yr annualised return: | E8: =VLOOKUP($F$7,'BM Data'!$A:$G,4,FALSE) -> 7.201367
A9: Month 29 | B9: ='Invert return series (3 years)'!$B9 -> 0.023159597 | D9: 2 yr annualised vol: | E9: =VLOOKUP($F$7,'BM Data'!$A:$G,7,FALSE) -> 3.381862
A10: Month 28 | B10: ='Invert return series (3 years)'!$B10 -> -0.019686065
A11: Month 27 | B11: ='Invert return series (3 years)'!$B11 -> 0.028205909
A12: Month 26 | B12: ='Invert return series (3 years)'!$B12 -> -0.0080229702
A13: Month 25 | B13: ='Invert return series (3 years)'!$B13 -> 0.015557598 | D13: Morningstar Category: | F13: Australia Fund Alternative - Other
A14: Month 24 | B14: ='Invert return series (3 years)'!$B14 -> 0.0087650403 | D14: 3 yr 4th Quartile Cut-off Return: | E14: =VLOOKUP($F$13,'Morningstar Category Data'!$A:$E,4,FALSE) -> 3.437971
A15: Month 23 | B15: ='Invert return series (3 years)'!$B15 -> -0.0039882307 | D15: 2 yr Median tracking error: | E15: =VLOOKUP($F$13,'Morningstar Category Data'!$I:$J,2,FALSE) -> 11.011605
A16: Month 22 | B16: ='Invert return series (3 years)'!$B16 -> 0.0049977342
A17: Month 21 | B17: ='Invert return series (3 years)'!$B17 -> 0.0085679419
A18: Month 20 | B18: ='Invert return series (3 years)'!$B18 -> 0.00099608678
A19: Month 19 | B19: ='Invert return series (3 years)'!$B19 -> -0.01773787
A20: Month 18 | B20: ='Invert return series (3 years)'!$B20 -> -0.01231937
A21: Month 17 | B21: ='Invert return series (3 years)'!$B21 -> 0.032476107
A22: Month 16 | B22: ='Invert return series (3 years)'!$B22 -> 0.027364197
A23: Month 15 | B23: ='Invert return series (3 years)'!$B23 -> 0.0072424781
A24: Month 14 | B24: ='Invert return series (3 years)'!$B24 -> 0.0091940259
A25: Month 13 | B25: ='Invert return series (3 years)'!$B25 -> 0.015097839
A26: Month 12 | B26: ='Invert return series (3 years)'!$B26 -> -0.016858346
A27: Month 11 | B27: ='Invert return series (3 years)'!$B27 -> 0.010123351
... A37: Month 1 | B37: ='Invert return series (3 years)'!$B37 -> -0.011368317
A40: Scoring Summary
A41: Fund vs BM. 3 year net returns. Fail if alpha<0 | B41: Fund vs peers. 3 year rank in Morningstar peer group. Fail if in 4th quartile | C41: Annualised 2 year tracking error. Fail if >2x peer median TE | D41: Annualised 2 year volatility. Fail if >1.5x BM volatility | E41: Fail if <80% liquid in 21 business days | F41: Fail if not Approved/Investment Grade (Zenith, Lonsec), 3.5 (SQM) or Neutral (Morningstar) or higher | G41: Team (resourcing, skills, stability) | H41: Process (robust, disciplined, governance) | I41: Business (conflicts, support, stability) | J41: Product (viability, fees, capacity, concentration) | K41: Score | L41: Final Rating
A42: =IF(E2>E8,20,"-") -> - | B42: =IF(E2>E14,20,"-") -> 20 | C42: =IF(G5>(2*E15),"-",5) -> 5 | D42: =IF(E3>(1.5*E9),"-",5) -> - | E42: 10 | G42: 10 | H42: 10 | I42: 5 | J42: 5 | K42: =SUM(A42:J42) -> 65 | L42: =IF(K42<50,"Red",IF(K42>60,"Green","Amber")) -> Green

Sheet Manual Calc (2 years)
B1: Return Series | D1: Investment Option | F1: Investment option monthly returns> | G1: Month 1 | I1: Month 2 | K1: Month 3 | M1: Month 4 | O1: Month 5 | Q1: Month 6 | S1: Month 7 | U1: Month 8 | W1: Month 9 | Y1: Month 10 | AA1: Month 11 | AC1: Month 12 | AE1: Month 13 | AG1: Month 14 | AI1: Month 15 | AK1: Month 16 | AM1: Month 17 | AO1: Month 18 | AQ1: Month 19 | AS1: Month 20 | AU1: Month 21 | AW1: Month 22 | AY1: Month 23 | BA1: Month 24
A2: Month 24 | B2: ='Invert return series (2 years)'!$B2 -> 0.001265213 | D2: 2 yr annualised return: | E2: {=(PRODUCT(1+$B$2:$B$25)^(0.5)-1)*100} -> 10.422398 | G2: =$B25*100 -> 3.070665 | I2: =$B24*100 -> -5.7978741 | K2: =$B23*100 -> 4.9354245 | M2: =$B22*100 -> 0.5765681 | O2: =$B21*100 -> -2.6776591 | Q2: =$B20*100 -> 1.8036866 | S2: =$B19*100 -> 2.051514 | U2: =$B18*100 -> 1.7416475 | W2: =$B17*100 -> 3.4338148 | Y2: =$B16*100 -> 0.093871301 | AA2: =$B15*100 -> -1.603754 | AC2: =$B14*100 -> -10.878218 | AE2: =$B13*100 -> 2.04754 | AG2: =$B12*100 -> -0.63277413 | AI2: =$B11*100 -> 3.5364225 | AK2: =$B10*100 -> 4.6012452 | AM2: =$B9*100 -> -0.88147818 | AO2: =$B8*100 -> 1.5407347 | AQ2: =$B7*100 -> 4.1752524 | AS2: =$B6*100 -> 4.1179419 | AU2: =$B5*100 -> 2.5042679 | AW2: =$B4*100 -> 3.6626656 | AY2: =$B3*100 -> -0.11540287 | BA2: =$B2*100 -> 0.1265213
A3: Month 23 | B3: ='Invert return series (2 years)'!$B3 -> -0.0011540287 | D3: 2 yr annualised vol: | E3: =(STDEV($B$2:$B$25)*SQRT(12))*100 -> 12.395555 | F3: Benchmark monthly returns> | G3: =INDEX('BM Data'!$K$7:$BE$260,MATCH('Manual Calc (2 years)'!$F7,'BM Data'!$A$7:$A$260,0),MATCH('Manual Calc (2 years)'!G$1,'BM Data'!$K$1:$BE$1,0)) -> 0.01506 | I3: =INDEX('BM Data'!$K$7:$BE$260,MATCH('Manual Calc (2 years)'!$F7,'BM Data'!$A$7:$A$260,0),MATCH('Manual Calc (2 years)'!I$1,'BM Data'!$K$1:$BE$1,0)) -> 0.79921 | K3: =INDEX('BM Data'!$K$7:$BE$260,MATCH('Manual Calc (2 years)'!$F7,'BM Data'!$A$7:$A$260,0),MATCH('Manual Calc (2 years)'!K$1,'BM Data'!$K$1:$BE$1,0)) -> 1.4799 | M3: =INDEX('BM Data'!$K$7:$BE$260,MATCH('Manual Calc (2 years)'!$F7,'BM Data'!$A$7:$A$260,0),MATCH('Manual Calc (2 years)'!M$1,'BM Data'!$K$1:$BE$1,0)) -> -0.7255 | O3: =INDEX('BM Data'!$K$7:$BE$260,MATCH('Manual Calc (2 years)'!$F7,'BM Data'!$A$7:$A$260,0),MATCH('Manual Calc (2 years)'!O$1,'BM Data'!$K$1:$BE$1,0)) -> 1.11126 | Q3: =INDEX('BM Data'!$K$7:$BE$260,MATCH('Manual Calc (2 years)'!$F7,'BM Data'!$A$7:$A$260,0),MATCH('Manual Calc (2 years)'!Q$1,'BM Data'!$K$1:$BE$1,0)) -> 0.56979 | S3: =INDEX('BM Data'!$K$7:$BE$260,MATCH('Manual Calc (2 years)'!$F7,'BM Data'!$A$7:$A$260,0),MATCH('Manual Calc (2 years)'!S$1,'BM Data'!$K$1:$BE$1,0)) -> 1.73315 | U3: =INDEX('BM Data'!$K$7:$BE$260,MATCH('Manual Calc (2 years)'!$F7,'BM Data'!$A$7:$A$260,0),MATCH('Manual Calc (2 years)'!U$1,'BM Data'!$K$1:$BE$1,0)) -> 1.64181 | W3: =INDEX('BM Data'!$K$7:$BE$260,MATCH('Manual Calc (2 years)'!$F7,'BM Data'!$A$7:$A$260,0),MATCH('Manual Calc (2 years)'!W$1,'BM Data'!$K$1:$BE$1,0)) -> 1.69939 | Y3: =INDEX('BM Data'!$K$7:$BE$260,MATCH('Manual Calc (2 years)'!$F7,'BM Data'!$A$7:$A$260,0),MATCH('Manual Calc (2 years)'!Y$1,'BM Data'!$K$1:$BE$1,0)) -> -0.15724 | AA3: =INDEX('BM Data'!$K$7:$BE$260,MATCH('Manual Calc (2 years)'!$F7,'BM Data'!$A$7:$A$260,0),MATCH('Manual Calc (2 years)'!AA$1,'BM Data'!$K$1:$BE$1,0)) -> 1.28995 | AC3: =INDEX('BM Data'!$K$7:$BE$260,MATCH('Manual Calc (2 years)'!$F7,'BM Data'!$A$7:$A$260,0),MATCH('Manual Calc (2 years)'!AC$1,'BM Data'!$K$1:$BE$1,0)) -> -0.25624 | AE3: =INDEX('BM Data'!$K$7:$BE$260,MATCH('Manual Calc (2 years)'!$F7,'BM Data'!$A$7:$A$260,0),MATCH('Manual Calc (2 years)'!AE$1,'BM Data'!$K$1:$BE$1,0)) -> 1.33452 | AG3: =INDEX('BM Data'!$K$7:$BE$260,MATCH('Manual Calc (2 years)'!$F7,'BM Data'!$A$7:$A$260,0),MATCH('Manual Calc (2 years)'!AG$1,'BM Data'!$K$1:$BE$1,0)) -> 0.76972 | AI3: =INDEX('BM Data'!$K$7:$BE$260,MATCH('Manual Calc (2 years)'!$F7,'BM Data'!$A$7:$A$260,0),MATCH('Manual Calc (2 years)'!AI$1,'BM Data'!$K$1:$BE$1,0)) -> -0.96199 | AK3: =INDEX('BM Data'!$K$7:$BE$260,MATCH('Manual Calc (2 years)'!$F7,'BM Data'!$A$7:$A$260,0),MATCH('Manual Calc (2 years)'!AK$1,'BM Data'!$K$1:$BE$1,0)) -> -0.03016 | AM3: =INDEX('BM Data'!$K$7:$BE$260,MATCH('Manual Calc (2 years)'!$F7,'BM Data'!$A$7:$A$260,0),MATCH('Manual Calc (2 years)'!AM$1,'BM Data'!$K$1:$BE$1,0)) -> 1.64521 | AO3: =INDEX('BM Data'!$K$7:$BE$260,MATCH('Manual Calc (2 years)'!$F7,'BM Data'!$A$7:$A$260,0),MATCH('Manual Calc (2 years)'!AO$1,'BM Data'!$K$1:$BE$1,0)) -> 1.68905 | AQ3: =INDEX('BM Data'!$K$7:$BE$260,MATCH('Manual Calc (2 years)'!$F7,'BM Data'!$A$7:$A$260,0),MATCH('Manual Calc (2 years)'!AQ$1,'BM Data'!$K$1:$BE$1,0)) -> 0.84725 | AS3: =INDEX('BM Data'!$K$7:$BE$260,MATCH('Manual Calc (2 years)'!$F7,'BM Data'!$A$7:$A$260,0),MATCH('Manual Calc (2 years)'!AS$1,'BM Data'!$K$1:$BE$1,0)) -> 1.0837 | AU3: =INDEX('BM Data'!$K$7:$BE$260,MATCH('Manual Calc (2 years)'!$F7,'BM Data'!$A$7:$A$260,0),MATCH('Manual Calc (2 years)'!AU$1,'BM Data'!$K$1:$BE$1,0)) -> 0.58797 | AW3: =INDEX('BM Data'!$K$7:$BE$260,MATCH('Manual Calc (2 years)'!$F7,'BM Data'!$A$7:$A$260,0),MATCH('Manual Calc (2 years)'!AW$1,'BM Data'!$K$1:$BE$1,0)) -> 1.03466 | AY3: =INDEX('BM Data'!$K$7:$BE$260,MATCH('Manual Calc (2 years)'!$F7,'BM Data'!$A$7:$A$260,0),MATCH('Manual Calc (2 years)'!AY$1,'BM Data'!$K$1:$BE$1,0)) -> 0.44207 | BA3: =INDEX('BM Data'!$K$7:$BE$260,MATCH('Manual Calc (2 years)'!$F7,'BM Data'!$A$7:$A$260,0),MATCH('Manual Calc (2 years)'!BA$1,'BM Data'!$K$1:$BE$1,0)) -> 0.74981
A4: Month 22 | B4: ='Invert return series (2 years)'!$B4 -> 0.036626656 | F4: Monthly Excess> | G4: =G2-G3 -> 3.055605 | I4: =I2-I3 -> -6.5970841 | K4: =K2-K3 -> 3.4555245 | M4: =M2-M3 -> 1.3020681 | O4: =O2-O3 -> -3.7889191 | Q4: =Q2-Q3 -> 1.2338966 | S4: =S2-S3 -> 0.31836402 | U4: =U2-U3 -> 0.09983752 | W4: =W2-W3 -> 1.7344248 | Y4: =Y2-Y3 -> 0.2511113 | AA4: =AA2-AA3 -> -2.893704 | AC4: =AC2-AC3 -> -10.621978 | AE4: =AE2-AE3 -> 0.71302001 | AG4: =AG2-AG3 -> -1.4024941 | AI4: =AI2-AI3 -> 4.4984125 | AK4: =AK2-AK3 -> 4.6314052 | AM4: =AM2-AM3 -> -2.5266882 | AO4: =AO2-AO3 -> -0.14831533 | AQ4: =AQ2-AQ3 -> 3.3280024 | AS4: =AS2-AS3 -> 3.0342419 | AU4: =AU2-AU3 -> 1.9162979 | AW4: =AW2-AW3 -> 2.6280056 | AY4: =AY2-AY3 -> -0.55747287 | BA4: =BA2-BA3 -> -0.6232887
A5: Month 21 | B5: ='Invert return series (2 years)'!$B5 -> 0.025042679 | F5: Tracking error | G5: =STDEV(G4,I4,K4,M4,O4,Q4,S4,U4,W4,Y4,AA4,AC4,AE4,AG4,AI4,AK4,AM4,AO4,AQ4,AS4,AU4,AW4,AY4,BA4)*SQRT(12) -> 12.268674
A6: Month 20 | B6: ='Invert return series (2 years)'!$B6 -> 0.041179419
A7: Month 19 | B7: ='Invert return series (2 years)'!$B7 -> 0.041752524 | D7: Benchmark: | F7: Bloomberg Global High Yield TR Hdg AUD
A8: Month 18 | B8: ='Invert return series (2 years)'!$B8 -> 0.015407347 | D8: 2 yr annualised return: | E8: =VLOOKUP($F$7,'BM Data'!$A:$G,6,FALSE) -> 9.555733
A9: Month 17 | B9: ='Invert return series (2 years)'!$B9 -> -0.0088147818 | D9: 2 yr annualised vol: | E9: =VLOOKUP($F$7,'BM Data'!$A:$G,7,FALSE) -> 2.711053
A10: Month 16 | B10: ='Invert return series (2 years)'!$B10 -> 0.046012452
A11: Month 15 | B11: ='Invert return series (2 years)'!$B11 -> 0.035364225
A12: Month 14 | B12: ='Invert return series (2 years)'!$B12 -> -0.0063277413
A13: Month 13 | B13: ='Invert return series (2 years)'!$B13 -> 0.0204754 | D13: Morningstar Category: | F13: Australia Fund Alternative - Macro Trading
A14: Month 12 | B14: ='Invert return series (2 years)'!$B14 -> -0.10878218 | D14: 2 yr 4th Quartile Cut-off Return: | E14: =VLOOKUP($F$13,'Morningstar Category Data'!$A:$E,3,FALSE) -> -1.255531
A15: Month 11 | B15: ='Invert return series (2 years)'!$B15 -> -0.01603754 | D15: 2 yr Median tracking error: | E15: =VLOOKUP($F$13,'Morningstar Category Data'!$I:$J,2,FALSE) -> 11.186195
A16: Month 10 | B16: ='Invert return series (2 years)'!$B16 -> 0.00093871301
A17: Month 9 | B17: ='Invert return series (2 years)'!$B17 -> 0.034338148
A18: Month 8 | B18: ='Invert return series (2 years)'!$B18 -> 0.017416475
A19: Month 7 | B19: ='Invert return series (2 years)'!$B19 -> 0.02051514
A20: Month 6 | B20: ='Invert return series (2 years)'!$B20 -> 0.018036866
A21: Month 5 | B21: ='Invert return series (2 years)'!$B21 -> -0.026776591
A22: Month 4 | B22: ='Invert return series (2 years)'!$B22 -> 0.005765681
A23: Month 3 | B23: ='Invert return series (2 years)'!$B23 -> 0.049354245
A24: Month 2 | B24: ='Invert return series (2 years)'!$B24 -> -0.057978741
A25: Month 1 | B25: ='Invert return series (2 years)'!$B25 -> 0.03070665
A28: Scoring Summary
A29: Fund vs BM. 2 year net returns. Fail if alpha<0 | B29: Fund vs peers. 2 year rank in Morningstar peer group. Fail if in 4th quartile | C29: Annualised 2 year tracking error. Fail if >2x peer median TE | D29: Annualised 2 year volatility. Fail if >1.5x BM volatility | E29: Fail if <80% liquid in 21 business days | F29: Fail if not Approved/Investment Grade (Zenith, Lonsec), 3.5 (SQM) or Neutral (Morningstar) or higher | G29: Team (resourcing, skills, stability) | H29: Process (robust, disciplined, governance) | I29: Business (conflicts, support, stability) | J29: Product (viability, fees, capacity, concentration) | K29: Score | L29: Final Rating
A30: =IF(E2>E8,20,"-") -> 20 | B30: =IF(E2>E14,20,"-") -> 20 | C30: =IF(G5>(2*E15),"-",5) -> 5 | D30: =IF(E3>(1.5*E9),"-",5) -> - | E30: 10 | G30: 10 | H30: 10 | I30: 5 | J30: 5 | K30: =SUM(A30:J30) -> 85 | L30: =IF(K30<50,"Red",IF(K30>60,"Green","Amber")) -> Green

Sheet Morningstar Category Data
A1: 4th Quartile Category Returns | I1: Median Category TE
A2: Morningstar Categories (31 Dec 2025) | B2: 1 Year | C2: 2 Years | D2: 3 Years | E2: 5 Years | I2: Morningstar Categories (31 Dec 2025) | J2: 2 Years
A3: Australia Fund Alternative - Macro Trading | B3: -4.826621 | C3: -1.255531 | D3: 1.364369 | E3: 1.054108 | I3: Australia Fund Alternative - Macro Trading | J3: 11.186195 | L3: 11.186195
A4: Australia Fund Alternative - Multistrategy | B4: 4.871406 | C4: 5.651317 | D4: 6.294975 | E4: 5.129028 | I4: Australia Fund Alternative - Multistrategy | J4: 10.509394 | L4: 10.509394
A5: Australia Fund Alternative - Other | B5: 2.028752 | C5: 4.263378 | D5: 3.437971 | E5: 1.836301 | I5: Australia Fund Alternative - Other | J5: 11.011605 | L5: 11.011605
A6: Australia Fund Alternative - Systematic Trend | B6: 2.065401 | C6: 3.141138 | D6: 1.892295 | E6: 4.067185 | I6: Australia Fund Alternative - Systematic Trend | J6: 13.333063 | L6: 13.333063
A7: Australia Fund Australian Cash | B7: 3.976694 | C7: 4.197108 | D7: 4.081719 | E7: 2.703786 | I7: Australia Fund Australian Cash | J7: 0.067356 | L7: 0.067356
A8: Australia Fund Australian Short Term Fixed Interest | B8: 4.227854 | C8: 4.49918 | D8: 4.357877 | E8: 2.862583 | I8: Australia Fund Australian Short Term Fixed Interest | J8: 0.276417 | L8: 0.276417
A9: Australia Fund Bonds - Australia | B9: 2.917516 | C9: 2.774295 | D9: 3.500913 | E9: -0.748842 | I9: Australia Fund Bonds - Australia | J9: 0.390321 | L9: 0.390321
A10: Australia Fund Bonds - Emerging Market Debt | B10: 12.250659 | C10: 8.558974 | D10: 8.702037 | E10: -0.338676 | I10: Australia Fund Bonds - Emerging Market Debt | J10: 6.235418 | L10: 6.235418
A11: Australia Fund Bonds - Global | B11: 4.09684 | C11: 2.5749 | D11: 3.333599 | E11: -1.333749 | I11: Australia Fund Bonds - Global | J11: 0.943908 | L11: 0.943908
A12: Australia Fund Bonds - Global / Australia | B12: 4.051782 | C12: 2.999734 | D12: 3.743944 | E12: -0.634365 | I12: Australia Fund Bonds - Global / Australia | J12: 0.98566 | L12: 0.98566
A13: Australia Fund Bonds - Inflation-linked | B13: 1.78533 | C13: 0.447276 | D13: 3.165272 | E13: -0.231252 | I13: Australia Fund Bonds - Inflation-linked | J13: 2.129815 | L13: 2.129815
A14: Australia Fund Commodities & Precious Metals | B14: 51.784353 | C14: 42.32934 | D14: 31.299259 | E14: 16.218238 | I14: Australia Fund Commodities & Precious Metals | J14: 23.877368 | L14: 23.877368
A15: Australia Fund Diversified Credit | B15: 5.021038 | C15: 5.106361 | D15: 5.407998 | E15: 2.297666 | I15: Australia Fund Diversified Credit | J15: 3.665483 | L15: 3.665483
A16: Australia Fund Australia Equity Income | B16: 5.375341 | C16: 5.989496 | D16: 6.834276 | E16: 7.560119 | I16: Australia Fund Australia Equity Income | J16: 4.444865 | K16: New Peer Group | L16: 4.444865
A17: Australia Fund Equity Asia Pacific w/o Japan | B17: 13.001158 | C17: 18.607074 | D17: 11.10338 | E17: 5.000682 | I17: Australia Fund Equity Asia Pacific w/o Japan | J17: 6.35787 | L17: 6.35787
A18: Australia Fund Equity Australia Large Blend | B18: 6.235883 | C18: 8.189298 | D18: 8.562284 | E18: 8.025206 | I18: Australia Fund Equity Australia Large Blend | J18: 2.849924 | L18: 2.849924
A19: Australia Fund Equity Australia Large Geared | B19: 1.254876 | C19: 9.477726 | D19: 11.361641 | E19: 10.441292 | I19: Australia Fund Equity Australia Large Geared | J19: 12.366682 | L19: 12.366682
A20: Australia Fund Equity Australia Large Growth | B20: -9.671288 | C20: 2.30309 | D20: 8.088135 | E20: 3.803866 | I20: Australia Fund Equity Australia Large Growth | J20: 6.374814 | L20: 6.374814
A21: Australia Fund Equity Australia Large Value | B21: 4.263558 | C21: 6.489516 | D21: 6.254033 | E21: 8.167696 | I21: Australia Fund Equity Australia Large Value | J21: 3.727303 | L21: 3.727303
A22: Australia Fund Equity Australia Long Short | B22: 7.433136 | C22: 5.901951 | D22: 6.230103 | E22: 6.295768 | I22: Australia Fund Equity Australia Long Short | J22: 8.585015 | L22: 8.585015
A23: Australia Fund Equity Australia Mid/Small Blend | B23: 12.025828 | C23: 11.224768 | D23: 10.167329 | E23: 5.362855 | I23: Australia Fund Equity Australia Mid/Small Blend | J23: 7.957892 | L23: 7.957892
A24: Australia Fund Equity Australia Mid/Small Growth | B24: -1.01519 | C24: 8.868575 | D24: 10.024472 | E24: 2.916581 | I24: Australia Fund Equity Australia Mid/Small Growth | J24: 8.755063 | L24: 8.755063
A25: Australia Fund Equity Australia Mid/Small Value | B25: 8.266127 | C25: 10.841429 | D25: 11.320505 | E25: 9.014166 | I25: Australia Fund Equity Australia Mid/Small Value | J25: 9.44535 | L25: 9.44535
A26: Australia Fund Equity Australia Other | B26: 7.193372 | C26: 8.131666 | D26: 8.523926 | E26: 7.075629 | I26: Australia Fund Equity Australia Other | J26: 11.648779 | L26: 11.648779
A27: Australia Fund Equity Australia Real Estate | B27: 8.936854 | C27: 12.386949 | D27: 13.409132 | E27: 7.938494 | I27: Australia Fund Equity Australia Real Estate | J27: 1.35508 | L27: 1.35508
A28: Australia Fund Equity Emerging Markets | B28: 18.703339 | C28: 14.41817 | D28: 14.07947 | E28: 4.361566 | I28: Australia Fund Equity Emerging Markets | J28: 4.858408 | L28: 4.858408
... A62: Australia Fund Unconstrained Fixed Income | B62: 4.165955 | C62: 5.046363 | D62: 5.471164 | E62: 2.14285 | I62: Australia Fund Unconstrained Fixed Income | J62: 3.188445 | L62: 3.188445
A63: Australia Fund Reserve Backed | I63: Australia Fund Reserve Backed
A64: Australia Fund Unlisted and Direct Property | B64: 1.647436 | C64: -4.90543 | D64: -5.824458 | E64: -1.290515 | I64: Australia Fund Unlisted and Direct Property | J64: 16.691281 | L64: 16.691281
A65: Australia Fund Alternative - Private Debt | B65: 7.704317 | C65: 8.235877 | D65: 8.513764 | E65: 7.151331 | I65: Australia Fund Alternative - Private Debt | J65: 2.752517 | L65: 2.752517
A66: Australia Fund Non Investment Grade Debt | B66: 4.939721 | C66: 6.406669 | D66: 7.094707 | E66: 3.252213 | I66: Australia Fund Non Investment Grade Debt | J66: 2.05497 | L66: 2.05497
A67: Australia Fund Alternative - Private Equity | B67: -8.539211 | C67: -3.128872 | D67: -5.621465 | E67: 2.45875 | I67: Australia Fund Alternative - Private Equity | J67: 8.029192 | L67: 8.029192
A68: Australia Fund Equity Alternative - Private Debt | B68: 4.939721 | C68: 6.406669 | D68: 7.094707 | E68: 3.252213 | I68: Australia Fund Equity Alternative - Private Debt | J68: 2.752517 | L68: 2.752517
A69: Australia Invst Bd Equity Australia Large Blend | B69: 4.718023 | C69: 5.456103 | D69: 6.441186 | E69: 5.82846 | I69: Australia Invst Bd Equity Australia Large Blend | J69: 5.554619 | L69: 5.554619

Sheet BM Data
B1: 5 year Return | D1: 3 year Return | F1: 2 year Return | G1: 2 year Vol | I1: 1 year Return | K1: Month 1 | M1: Month 2 | O1: Month 3 | Q1: Month 4 | S1: Month 5 | U1: Month 6 | W1: Month 7 | Y1: Month 8 | AA1: Month 9 | AC1: Month 10 | AE1: Month 11 | AG1: Month 12 | AI1: Month 13 | AK1: Month 14 | AM1: Month 15 | AO1: Month 16 | AQ1: Month 17 | AS1: Month 18 | AU1: Month 19 | AW1: Month 20 | AY1: Month 21 | BA1: Month 22 | BC1: Month 23 | BE1: Month 24
A4: Group/Investment | B4: Return (Annualized) | D4: Return (Annualized) | F4: Return (Annualized) | G4: Std Dev (Annualized) | I4: Return (Cumulative) | K4: Return (Cumulative) | M4: Return (Cumulative) | O4: Return (Cumulative) | Q4: Return (Cumulative) | S4: Return (Cumulative) | U4: Return (Cumulative) | W4: Return (Cumulative) | Y4: Return (Cumulative) | AA4: Return (Cumulative) | AC4: Return (Cumulative) | AE4: Return (Cumulative) | AG4: Return (Cumulative) | AI4: Return (Cumulative) | AK4: Return (Cumulative) | AM4: Return (Cumulative) | AO4: Return (Cumulative) | AQ4: Return (Cumulative) | AS4: Return (Cumulative) | AU4: Return (Cumulative) | AW4: Return (Cumulative) | AY4: Return (Cumulative) | BA4: Return (Cumulative) | BC4: Return (Cumulative) | BE4: Return (Cumulative)
A6: Unclassified
A7: 35FTSE EPRANAREIT Dev H + 45FTSE Dev Core Infra 5050 H + 20S&PASX 200 AREIT | B7: 6.966644 | D7: 9.6068 | F7: 10.814072 | G7: 9.61355 | I7: 10.742233 | K7: -1.914453 | M7: 1.278615 | O7: 4.962044 | Q7: -4.219876 | S7: 3.713545 | U7: -0.682853 | W7: 6.161281 | Y7: 3.29047 | AA7: 3.196299 | AC7: -2.13471 | AE7: 3.237188 | AG7: -5.717517 | AI7: 2.112899 | AK7: 0.518019 | AM7: -1.284542 | AO7: 1.195402 | AQ7: 2.566931 | AS7: 0.64192 | AU7: 1.295565 | AW7: 2.812308 | AY7: 0.501973 | BA7: -0.251214 | BC7: 1.331767 | BE7: -1.100711
A8: 50 BB AusBond Bank 0+ 50 BB AusBond Composite | B8: 1.16169 | D8: 3.940045 | F8: 3.646627 | G8: 1.592446 | I8: 3.5767 | K8: 0.288004 | M8: 0.022105 | O8: 0.74441 | Q8: -0.816054 | S8: 0.383935 | U8: 0.561548 | W8: 0.926253 | Y8: 0.792808 | AA8: 0.333304 | AC8: -0.753587 | AE8: 0.748033 | AG8: 0.441824 | AI8: 0.28491 | AK8: 0.633189 | AM8: 0.260554 | AO8: 1.026124 | AQ8: 0.253154 | AS8: 0.533194 | AU8: 0.132832 | AW8: 0.327579 | AY8: 0.196004 | BA8: 0.328736 | BC8: -0.29155 | BE8: -0.158893
A9: 50 Bloomberg AusBond Composite 0+Y TR and 50 BBg Barclay Aggregate TR Hdg | B9: -0.498486 | D9: 3.853058 | F9: 3.189625 | G9: 2.998521 | I9: 3.796815 | K9: -0.053206 | M9: -0.552553 | O9: 0.965773 | Q9: -1.843563 | S9: 0.583692 | U9: 0.778861 | W9: 1.680482 | Y9: 1.096544 | AA9: 0.689468 | AC9: -1.694264 | AE9: 1.148437 | AG9: -0.174943 | AI9: 0.28548 | AK9: 1.062176 | AM9: -0.132002 | AO9: 1.322385 | AQ9: -0.098152 | AS9: 0.826962 | AU9: -0.093712 | AW9: 0.414508 | AY9: 0.389428 | BA9: 0.554046 | BC9: -0.351382 | BE9: -0.430282
A10: 50 JPM EMBI (hedged) + 50 JPM EMBI
A11: 50 MSCI %0 AUD CASH | B11: 9.157971 | D11: 12.91167 | F11: 12.703663 | G11: 4.795691 | I11: 8.307305 | K11: 2.447925 | M11: 3.13743 | O11: 1.697593 | Q11: -1.449072 | S11: 1.195702 | U11: 0.985697 | W11: 2.22677 | Y11: -0.434777 | AA11: -0.053418 | AC11: 2.147561 | AE11: 2.771587 | AG11: 1.476201 | AI11: 1.55691 | AK11: -0.01163 | AM11: -2.158774 | AO11: -0.749031 | AQ11: 2.8431 | AS11: 1.387173 | AU11: 1.724963 | AW11: 0.619657 | AY11: 1.145515 | BA11: 1.813449 | BC11: 0.233538 | BE11: -0.296879
A12: 50 MSCI EM NR AUD 50 MSCI WORLD SMALL CAP | B12: 9.047306 | D12: 16.341698 | F12: 18.459175 | G12: 8.318843 | I12: 17.657622 | K12: -0.602944 | M12: 5.628516 | O12: 2.988586 | Q12: -1.899362 | S12: 0.137126 | U12: 0.57629 | W12: 5.929591 | Y12: -2.744275 | AA12: 1.982295 | AC12: 2.136657 | AE12: 1.987407 | AG12: 2.005957 | AI12: 1.869402 | AK12: -1.113002 | AM12: -1.772412 | AO12: -1.629881 | AQ12: 4.431803 | AS12: 3.474521 | AU12: 3.389284 | AW12: 1.539759 | AY12: 3.265198 | BA12: 3.438757 | BC12: -0.516413 | BE12: 0.270661
A13: 50% ASX 300 TR + 50% MSCI World ex Aus unhedged | B13: 12.810354 | D13: 16.75878 | F13: 16.285759 | G13: 7.94662 | I13: 11.709678 | K13: 2.81047 | M13: 3.453791 | O13: 3.141474 | Q13: -3.092421 | S13: 1.433481 | U13: 1.262201 | W13: 4.105314 | Y13: -0.400038 | AA13: 1.301654 | AC13: 1.312166 | AE13: 4.431346 | AG13: -0.24891 | AI13: 3.601047 | AK13: -2.073141 | AM13: -4.005146 | AO13: 0.878825 | AQ13: 4.768455 | AS13: 1.936442 | AU13: 2.775533 | AW13: 2.042428 | AY13: 0.669685 | BA13: 1.868903 | BC13: -1.235299 | BE13: 0.231502
A14: 50% ASX Midcap 50% Small Ord | B14: 8.606015 | D14: 13.159128 | F14: 15.925845 | G14: 10.61524 | I14: 21.663912 | K14: -0.637157 | M14: 3.532378 | O14: 4.114997 | Q14: -2.593691 | S14: 0.235112 | U14: -1.390603 | W14: 3.827937 | Y14: -0.023771 | AA14: 4.062023 | AC14: -0.808597 | AE14: 3.51137 | AG14: -3.418339 | AI14: 5.074138 | AK14: -3.721536 | AM14: -3.562271 | AO14: 2.596834 | AQ14: 5.851573 | AS14: 0.812176 | AU14: 3.565044 | AW14: 6.969734 | AY14: 1.910656 | BA14: 1.393785 | BC14: -0.587237 | BE14: 0.091768
A15: 50% AusBond Bank, 50% AusBond Composite | B15: 1.16169 | D15: 3.940045 | F15: 3.646627 | G15: 1.592446 | I15: 3.5767 | K15: 0.288004 | M15: 0.022105 | O15: 0.74441 | Q15: -0.816054 | S15: 0.383935 | U15: 0.561548 | W15: 0.926253 | Y15: 0.792808 | AA15: 0.333304 | AC15: -0.753587 | AE15: 0.748033 | AG15: 0.441824 | AI15: 0.28491 | AK15: 0.633189 | AM15: 0.260554 | AO15: 1.026124 | AQ15: 0.253154 | AS15: 0.533194 | AU15: 0.132832 | AW15: 0.327579 | AY15: 0.196004 | BA15: 0.328736 | BC15: -0.29155 | BE15: -0.158893
A16: 50% AusBond Comp 0-3yr, 50% AusBond Bank | B16: 2.281767 | D16: 3.947622 | F16: 4.038378 | G16: 0.49201 | I16: 3.793179 | K16: 0.369488 | M16: 0.248483 | O16: 0.408033 | Q16: 0.062184 | S16: 0.379225 | U16: 0.320222 | W16: 0.591341 | Y16: 0.495377 | AA16: 0.36848 | AC16: 0.085815 | AE16: 0.414194 | AG16: 0.460743 | AI16: 0.397923 | AK16: 0.373544 | AM16: 0.379788 | AO16: 0.598634 | AQ16: 0.339978 | AS16: 0.36071 | AU16: 0.217824 | AW16: 0.328058 | AY16: 0.188674 | BA16: 0.275633 | BC16: 0.121385 | BE16: 0.147584
A17: 50% Ausbond Comp, 50% Global Agg hdg | B17: -0.498486 | D17: 3.853058 | F17: 3.189625 | G17: 2.998521 | I17: 3.796815 | K17: -0.053206 | M17: -0.552553 | O17: 0.965773 | Q17: -1.843563 | S17: 0.583692 | U17: 0.778861 | W17: 1.680482 | Y17: 1.096544 | AA17: 0.689468 | AC17: -1.694264 | AE17: 1.148437 | AG17: -0.174943 | AI17: 0.28548 | AK17: 1.062176 | AM17: -0.132002 | AO17: 1.322385 | AQ17: -0.098152 | AS17: 0.826962 | AU17: -0.093712 | AW17: 0.414508 | AY17: 0.389428 | BA17: 0.554046 | BC17: -0.351382 | BE17: -0.430282
A18: 50% FTSE EPRANAREIT Developed (H) + 50% FTSE Dvlp Core Infra 5050 (H) | B18: 5.611656 | D18: 7.496292 | F18: 8.975552 | G18: 9.50603 | I18: 10.113163 | K18: -2.807677 | M18: 0.232806 | O18: 3.736174 | Q18: -3.573862 | S18: 3.946863 | U18: -0.816522 | W18: 5.937561 | Y18: 4.044487 | AA18: 2.344168 | AC18: -2.233006 | AE18: 3.292283 | AG18: -5.765688 | AI18: 1.48827 | AK18: 2.155673 | AM18: -0.668099 | AO18: -0.158752 | AQ18: 1.979022 | AS18: 0.315691 | AU18: 0.681036 | AW18: 2.492718 | AY18: 1.322726 | BA18: -0.500563 | BC18: 2.520102 | BE18: -1.846626
A19: 50% MSCI ACWI Info Tech + 50% MSCI ACWI Financials | B19: 17.82624 | D19: 29.605142 | F19: 28.232324 | G19: 10.841328 | I19: 25.485112 | K19: 2.738112 | M19: 5.223656 | O19: 3.510727 | Q19: -3.765873 | S19: 5.623825 | U19: 4.475002 | W19: 1.32439 | Y19: 1.596342 | AA19: 1.382658 | AC19: 0.604794 | AE19: 5.727108 | AG19: -0.663618 | AI19: 2.380216 | AK19: -0.275808 | AM19: -5.688702 | AO19: 0.284828 | AQ19: 7.702486 | AS19: 5.954264 | AU19: 3.064059 | AW19: 1.402069 | AY19: 4.427542 | BA19: 3.428558 | BC19: -1.327759 | BE19: 2.24167
A20: 50% MSCI World Small Cap (unhedged) 50% MSCI EM NR AUD | B20: 9.047306 | D20: 16.341698 | F20: 18.459175 | G20: 8.318843 | I20: 17.657622 | K20: -0.602944 | M20: 5.628516 | O20: 2.988586 | Q20: -1.899362 | S20: 0.137126 | U20: 0.57629 | W20: 5.929591 | Y20: -2.744275 | AA20: 1.982295 | AC20: 2.136657 | AE20: 1.987407 | AG20: 2.005957 | AI20: 1.869402 | AK20: -1.113002 | AM20: -1.772412 | AO20: -1.629881 | AQ20: 4.431803 | AS20: 3.474521 | AU20: 3.389284 | AW20: 1.539759 | AY20: 3.265198 | BA20: 3.438757 | BC20: -0.516413 | BE20: 0.270661
A21: 50% S&PASX 200 + 50% Bbg AusBond Comp | B21: 4.758851 | D21: 7.581365 | F21: 6.98616 | G21: 5.481076 | I21: 6.813422 | K21: 0.696715 | M21: 0.245687 | O21: 2.198084 | Q21: -2.459875 | S21: 0.654959 | U21: 0.89319 | W21: 2.835664 | Y21: 0.837807 | AA21: 1.6376 | AC21: -1.593788 | AE21: 2.461979 | AG21: -1.322423 | AI21: 2.380685 | AK21: -1.430682 | AM21: -1.609023 | AO21: 2.660174 | AQ21: 2.18331 | AS21: 1.081531 | AU21: 1.161365 | AW21: 1.719115 | AY21: -0.340868 | BA21: 0.374439 | BC21: -1.769823 | BE21: 0.335492
A22: 50% S&PASX 300 A-REIT TR + 50% FTSE EPRANAREIT Developed Index TR (hedge | B22: 8.102878 | D22: 11.695876 | F22: 10.742876 | G22: 11.072803 | I22: 6.497197 | K22: 0.159222 | M22: 2.862207 | O22: 6.494448 | Q22: -6.558911 | S22: 1.469451 | U22: 0.16355 | W22: 7.628084 | Y22: 1.445324 | AA22: 3.668053 | AC22: -0.983137 | AE22: 2.669977 | AG22: -3.953499 | AI22: 2.794295 | AK22: -1.769806 | AM22: -3.57451 | AO22: 2.327862 | AQ22: 3.471154 | AS22: 0.456361 | AU22: 2.010019 | AW22: 3.553891 | AY22: -1.568892 | BA22: 0.154574 | BC22: -0.90978 | BE22: -0.345143
... A25: 60% Bloomberg AusBond Composite All Maturities Index and 40% Barclays Globa | B25: -0.483775 | D25: 3.826872 | F25: 3.162923 | G25: 3.008599 | I25: 3.672528 | K25: -0.001288 | M25: -0.502133 | O25: 0.996966 | Q25: -1.871739 | S25: 0.545587 | U25: 0.77767 | W25: 1.640145 | Y25: 1.118785 | AA25: 0.613139 | AC25: -1.731719 | AE25: 1.145814 | AG25: -0.038545 | AI25: 0.265962 | AK25: 1.035222 | AM25: -0.070783 | AO25: 1.397833 | AQ25: -0.045941 | AS25: 0.811201 | AU25: -0.082023 | AW25: 0.39855 | AY25: 0.331363 | BA25: 0.515444 | BC25: -0.4569 | BE25: -0.469718
A26: 60% Mercer Unlisted + 35% ASX 200 AREIT + 5% Bank Bill
A27: 65% S&PASX 300 TR + 35% RBA Cash Rate Target | B27: 7.46381 | D27: 8.945245 | F27: 8.712931 | G27: 5.905565 | I27: 8.408689 | K27: 0.846566 | M27: 0.762288 | O27: 2.252306 | Q27: -1.773211 | S27: 0.684372 | U27: 0.722595 | W27: 2.817367 | Y27: 0.420419 | AA27: 2.124732 | AC27: -0.710747 | AE27: 2.520832 | AG27: -1.867389 | AI27: 3.032646 | AK27: -2.348048 | AM27: -2.046636 | AO27: 2.458456 | AQ27: 2.848962 | AS27: 1.035375 | AU27: 1.697808 | AW27: 2.168416 | AY27: -0.318138 | BA27: 0.382546 | BC27: -1.609048 | BE27: 0.99736
A28: 70 Bloomberg AusBond Composite 0+Y 30 FTSE WGBI Hdge AUD | B28: -0.78995 | D28: 3.522786 | F28: 2.824138 | G28: 3.053784 | I28: 3.228482 | K28: 0.009682 | M28: -0.46366 | O28: 0.984754 | Q28: -1.910708 | S28: 0.418653 | U28: 0.75864 | W28: 1.603325 | Y28: 1.120432 | AA28: 0.513775 | AC28: -1.781702 | AE28: 1.14829 | AG28: 0.062058 | AI28: 0.210171 | AK28: 0.991396 | AM28: -0.040538 | AO28: 1.537125 | AQ28: -0.067383 | AS28: 0.752833 | AU28: -0.129273 | AW28: 0.322548 | AY28: 0.250182 | BA28: 0.504657 | BC28: -0.571948 | BE28: -0.557274
A29: 70% AusBond Comp, 30% Citi WGBI hdg | B29: -0.78995 | D29: 3.522786 | F29: 2.824138 | G29: 3.053784 | I29: 3.228482 | K29: 0.009682 | M29: -0.46366 | O29: 0.984754 | Q29: -1.910708 | S29: 0.418653 | U29: 0.75864 | W29: 1.603325 | Y29: 1.120432 | AA29: 0.513775 | AC29: -1.781702 | AE29: 1.14829 | AG29: 0.062058 | AI29: 0.210171 | AK29: 0.991396 | AM29: -0.040538 | AO29: 1.537125 | AQ29: -0.067383 | AS29: 0.752833 | AU29: -0.129273 | AW29: 0.322548 | AY29: 0.250182 | BA29: 0.504657 | BC29: -0.571948 | BE29: -0.557274
A30: 70% BBg Global Aggr Hdge AUD + 30% Bloomberg AusBond Composite 0+Y | B30: -0.530821 | D30: 3.903908 | F30: 3.242002 | G30: 3.013672 | I30: 4.044859 | K30: -0.157043 | M30: -0.653393 | O30: 0.903389 | Q30: -1.78721 | S30: 0.659903 | U30: 0.781244 | W30: 1.761156 | Y30: 1.052064 | AA30: 0.842125 | AC30: -1.619354 | AE30: 1.153683 | AG30: -0.447739 | AI30: 0.324517 | AK30: 1.116084 | AM30: -0.254438 | AO30: 1.17149 | AQ30: -0.202575 | AS30: 0.858483 | AU30: -0.117091 | AW30: 0.446422 | AY30: 0.505557 | BA30: 0.63125 | BC30: -0.140345 | BE30: -0.35141
A31: 70% Bloomberg AusBond Composite 0+Y, 30% BBg Global Aggr Hdge AUD | B31: -0.470038 | D31: 3.800177 | F31: 3.135878 | G31: 3.030334 | I31: 3.548064 | K31: 0.050631 | M31: -0.451713 | O31: 1.028158 | Q31: -1.899916 | S31: 0.507481 | U31: 0.776479 | W31: 1.599807 | Y31: 1.141025 | AA31: 0.536811 | AC31: -1.769175 | AE31: 1.143191 | AG31: 0.097853 | AI31: 0.246444 | AK31: 1.008268 | AM31: -0.009565 | AO31: 1.47328 | AQ31: 0.006271 | AS31: 0.795441 | AU31: -0.070333 | AW31: 0.382593 | AY31: 0.273299 | BA31: 0.476842 | BC31: -0.562418 | BE31: -0.509154
A32: 70% Global Agg (Hedged) + 30% Ausbond Composite | I32: 3.796815 | AA32: 0.689468 | AC32: -1.694264 | AE32: 1.148437 | AG32: -0.174943 | AI32: 0.28548 | AK32: 1.062176 | AM32: -0.132002 | AO32: 1.322385 | AQ32: -0.098152 | AS32: 0.826962 | AU32: -0.093712 | AW32: 0.414508 | AY32: 0.389428 | BA32: 0.554046 | BC32: -0.351382 | BE32: -0.430282
A33: 70% S&PASX MidCap and 30% S&PASX Small Ord | B33: 9.281366 | D33: 13.010103 | F33: 15.706603 | G33: 10.888834 | I33: 20.339568 | K33: -1.250535 | M33: 4.256572 | O33: 3.845427 | Q33: -2.405954 | S33: 0.348038 | U33: -1.389071 | W33: 3.96256 | Y33: 0.773526 | AA33: 3.663185 | AC33: -1.452933 | AE33: 4.389794 | AG33: -3.555981 | AI33: 5.269117 | AK33: -4.092089 | AM33: -3.545193 | AO33: 2.899885 | AQ33: 5.886785 | AS33: 0.797748 | AU33: 3.86337 | AW33: 6.391708 | AY33: 1.297147 | BA33: 1.194144 | BC33: -0.228943 | BE33: -0.437839
A34: 85% AusBond Govt, 15% AusBond Govt Infl | B34: -0.667216 | D34: 3.449793 | F34: 2.444169 | G34: 3.432896 | I34: 2.823964 | K34: 0.041397 | M34: -0.39226 | O34: 1.202854 | Q34: -2.180054 | S34: 0.235423 | U34: 0.812146 | W34: 1.51075 | Y34: 1.172402 | AA34: 0.312993 | AC34: -2.166421 | AE34: 1.228438 | AG34: 0.353215 | AI34: 0.082392 | AK34: 0.936808 | AM34: -0.023581 | AO34: 1.733037 | AQ34: 0.149003 | AS34: 0.783353 | AU34: -0.07111 | AW34: 0.367109 | AY34: 0.238688 | BA34: 0.393734 | BC34: -0.951292 | BE34: -0.821211
A35: AusBond Bank Bill Index + 10% | B35: 12.974329 | D35: 14.520516 | F35: 14.647091 | G35: 0.134915 | I35: 14.357062 | K35: 1.184737 | M35: 1.106802 | O35: 1.182181 | Q35: 1.14092 | S35: 1.18986 | U35: 1.138758 | W35: 1.188857 | Y35: 1.19305 | AA35: 1.147416 | AC35: 1.189517 | AE35: 1.14939 | AG35: 1.19177 | AI35: 1.197142 | AK35: 1.074692 | AM35: 1.161955 | AO35: 1.14121 | AQ35: 1.158311 | AS35: 1.106554 | AU35: 1.115506 | AW35: 1.135165 | AY35: 1.081035 | BA35: 1.110975 | BC35: 1.084029 | BE35: 1.124319
A36: Australia Fund Multisector Aggressive | B36: 9.791457 | D36: 13.820728 | F36: 13.670038 | G36: 6.747263 | I36: 10.969673 | K36: 1.79568 | M36: 3.08196 | O36: 3.04146 | Q36: -2.71585 | S36: 1.29528 | U36: 0.99533 | W36: 3.32613 | Y36: 0.14492 | AA36: 1.74961 | AC36: 0.37746 | AE36: 3.40902 | AG36: -0.99329 | AI36: 3.12102 | AK36: -1.59179 | AM36: -3.25797 | AO36: 0.43794 | AQ36: 4.25898 | AS36: 1.84611 | AU36: 2.12835 | AW36: 2.08689 | AY36: 0.85304 | BA36: 1.42635 | BC36: -0.79659 | BE36: 0.17796
A37: Australia Fund Multisector Balanced | B37: 6.028844 | D37: 9.095538 | F37: 9.056713 | G37: 4.089884 | I37: 8.176691 | K37: 0.89074 | M37: 1.47996 | O37: 2.16717 | Q37: -1.97321 | S37: 0.90645 | U37: 0.60116 | W37: 2.58506 | Y37: 0.36501 | AA37: 1.19403 | AC37: -0.26646 | AE37: 2.2316 | AG37: -0.57085 | AI37: 1.82698 | AK37: -0.35373 | AM37: -1.71905 | AO37: 0.58692 | AQ37: 2.28247 | AS37: 1.26151 | AU37: 1.14371 | AW37: 1.37855 | AY37: 0.73106 | BA37: 1.04167 | BC37: -0.35781 | BE37: 0.1293
A38: Australia Fund Multisector Conservative
A39: Australia Fund Multisector Growth | B39: 7.328655 | D39: 10.606592 | F39: 10.485019 | G39: 5.248671 | I39: 8.887533 | K39: 1.1675 | M39: 2.11224 | O39: 2.56794 | Q39: -2.39452 | S39: 1.01167 | U39: 0.79861 | W39: 2.85195 | Y39: 0.35391 | AA39: 1.50094 | AC39: -0.17181 | AE39: 2.71938 | AG39: -0.8996 | AI39: 2.3921 | AK39: -1.01884 | AM39: -2.37399 | AO39: 0.65848 | AQ39: 3.10793 | AS39: 1.46976 | AU39: 1.42171 | AW39: 1.61081 | AY39: 0.64942 | BA39: 1.1666 | BC39: -0.56704 | BE39: 0.15322
A40: Australia Fund Multisector Moderate | B40: 3.719378 | D40: 6.753208 | F40: 6.632839 | G40: 2.817034 | I40: 6.257314 | K40: 0.47916 | M40: 0.86064 | O40: 1.58 | Q40: -1.52079 | S40: 0.73336 | U40: 0.59128 | W40: 1.89389 | Y40: 0.65227 | AA40: 0.96759 | AC40: -0.60717 | AE40: 1.52616 | AG40: -0.30985 | AI40: 1.13224 | AK40: 0.08633 | AM40: -0.87861 | AO40: 0.67542 | AQ40: 1.31552 | AS40: 1.03194 | AU40: 0.63295 | AW40: 1.02806 | AY40: 0.59697 | BA40: 0.77149 | BC40: -0.26631 | BE40: -0.0179
A41: Australian CPI + 1% | B41: 5.310801 | D41: 4.394151 | F41: 4.047803 | G41: 1.45702 | I41: 4.661101 | K41: 0.084487 | M41: 0.079035 | O41: 1.01617 | Q41: 0.081761 | S41: 0.084487 | U41: 1.130698 | W41: 0.084487 | Y41: 0.084487 | AA41: 0.299753 | AC41: 0.084487 | AE41: 0.081761 | AG41: 0.281295 | AI41: 0.084487 | AK41: 0.076308 | AM41: 1.004566 | AO41: 0.081761 | AQ41: 0.084487 | AS41: 0.829537 | AU41: 0.084487 | AW41: 0.084487 | AY41: 1.40354 | BA41: 0.084487 | BC41: 0.081761 | BE41: 0.676568
A42: Australian CPI + 1.5% | B42: 5.83201 | D42: 4.911026 | F42: 4.563203 | G42: 1.457573 | I42: 5.17882 | K42: 0.126445 | M42: 0.118282 | O42: 1.058505 | Q42: 0.122363 | S42: 0.126445 | U42: 1.171711 | W42: 0.126445 | Y42: 0.126445 | AA42: 0.340441 | AC42: 0.126445 | AE42: 0.122363 | AG42: 0.323332 | AI42: 0.126445 | AK42: 0.114201 | AM42: 1.046896 | AO42: 0.122363 | AQ42: 0.126445 | AS42: 0.870432 | AU42: 0.126445 | AW42: 0.126445 | AY42: 1.444661 | BA42: 0.126445 | BC42: 0.122363 | BE42: 0.718766
A43: Australian CPI + 2% | B43: 6.353219 | D43: 5.4279 | F43: 5.078604 | G43: 1.458133 | I43: 5.696536 | K43: 0.168213 | M43: 0.157352 | O43: 1.10065 | Q43: 0.162782 | S43: 0.168213 | U43: 1.21254 | W43: 0.168213 | Y43: 0.168213 | AA43: 0.380945 | AC43: 0.168213 | AE43: 0.162782 | AG43: 0.36518 | AI43: 0.168213 | AK43: 0.151922 | AM43: 1.089036 | AO43: 0.162782 | AQ43: 0.168213 | AS43: 0.911143 | AU43: 0.168213 | AW43: 0.168213 | AY43: 1.485596 | BA43: 0.168213 | BC43: 0.162782 | BE43: 0.760773
A44: Australian CPI + 2.5% | B44: 6.874428 | D44: 5.944775 | F44: 5.594007 | G44: 1.4587 | I44: 6.21425 | K44: 0.209794 | M44: 0.196246 | O44: 1.142606 | Q44: 0.20302 | S44: 0.209794 | U44: 1.253185 | W44: 0.209794 | Y44: 0.209794 | AA44: 0.421267 | AC44: 0.209794 | AE44: 0.20302 | AG44: 0.40684 | AI44: 0.209794 | AK44: 0.189472 | AM44: 1.130987 | AO44: 0.20302 | AQ44: 0.209794 | AS44: 0.951671 | AU44: 0.209794 | AW44: 0.209794 | AY44: 1.526347 | BA44: 0.209794 | BC44: 0.20302 | BE44: 0.802593
A45: Australian CPI + 3% | B45: 7.395635 | D45: 6.461651 | F45: 6.109411 | G45: 1.459273 | I45: 6.731963 | K45: 0.25119 | M45: 0.234966 | O45: 1.184375 | Q45: 0.243078 | S45: 0.25119 | U45: 1.293649 | W45: 0.25119 | Y45: 0.25119 | AA45: 0.461409 | AC45: 0.25119 | AE45: 0.243078 | AG45: 0.448315 | AI45: 0.25119 | AK45: 0.226854 | AM45: 1.172752 | AO45: 0.243078 | AQ45: 0.25119 | AS45: 0.992019 | AU45: 0.25119 | AW45: 0.25119 | AY45: 1.566917 | BA45: 0.25119 | BC45: 0.243078 | BE45: 0.844226
A46: Australian CPI + 3.5% | B46: 7.916842 | D46: 6.978526 | F46: 6.624817 | G46: 1.459852 | I46: 7.249673 | K46: 0.292403 | M46: 0.273513 | O46: 1.225959 | Q46: 0.282957 | S46: 0.292403 | U46: 1.333932 | W46: 0.292403 | Y46: 0.292403 | AA46: 0.501373 | AC46: 0.292403 | AE46: 0.282957 | AG46: 0.489606 | AI46: 0.292403 | AK46: 0.264069 | AM46: 1.214331 | AO46: 0.282957 | AQ46: 0.292403 | AS46: 1.032186 | AU46: 0.292403 | AW46: 0.292403 | AY46: 1.607305 | BA46: 0.292403 | BC46: 0.282957 | BE46: 0.885674
A47: Australian CPI + 4.0% | B47: 8.438049 | D47: 7.495402 | F47: 7.140224 | G47: 1.460437 | I47: 7.767382 | K47: 0.333434 | M47: 0.311889 | O47: 1.267359 | Q47: 0.322661 | S47: 0.333434 | U47: 1.374038 | W47: 0.333434 | Y47: 0.333434 | AA47: 0.54116 | AC47: 0.333434 | AE47: 0.322661 | AG47: 0.530715 | AI47: 0.333434 | AK47: 0.301118 | AM47: 1.255727 | AO47: 0.322661 | AQ47: 0.333434 | AS47: 1.072176 | AU47: 0.333434 | AW47: 0.333434 | AY47: 1.647516 | BA47: 0.333434 | BC47: 0.322661 | BE47: 0.92694
A48: Australian CPI + 4.5% | B48: 8.959255 | D48: 8.012279 | F48: 7.655633 | G48: 1.461029 | I48: 8.285088 | K48: 0.374285 | M48: 0.350095 | O48: 1.308578 | Q48: 0.362189 | S48: 0.374285 | U48: 1.413967 | W48: 0.374285 | Y48: 0.374285 | AA48: 0.580772 | AC48: 0.374285 | AE48: 0.362189 | AG48: 0.571644 | AI48: 0.374285 | AK48: 0.338003 | AM48: 1.296941 | AO48: 0.362189 | AQ48: 0.374285 | AS48: 1.11199 | AU48: 0.374285 | AW48: 0.374285 | AY48: 1.687549 | BA48: 0.374285 | BC48: 0.362189 | BE48: 0.968025
A49: Australian CPI + 5% | B49: 9.48046 | D49: 8.529155 | F49: 8.171043 | G49: 1.461626 | I49: 8.802793 | K49: 0.414957 | M49: 0.388134 | O49: 1.349617 | Q49: 0.401545 | S49: 0.414957 | U49: 1.453721 | W49: 0.414957 | Y49: 0.414957 | AA49: 0.62021 | AC49: 0.414957 | AE49: 0.401545 | AG49: 0.612393 | AI49: 0.414957 | AK49: 0.374725 | AM49: 1.337975 | AO49: 0.401545 | AQ49: 0.414957 | AS49: 1.15163 | AU49: 0.414957 | AW49: 0.414957 | AY49: 1.727406 | BA49: 0.414957 | BC49: 0.401545 | BE49: 1.00893
A50: Australian CPI + 5.5% | B50: 10.001665 | D50: 9.046032 | F50: 8.686455 | G50: 1.46223 | I50: 9.320495 | K50: 0.455453 | M50: 0.426006 | O50: 1.390477 | Q50: 0.440728 | S50: 0.455453 | U50: 1.493301 | W50: 0.455453 | Y50: 0.455453 | AA50: 0.659476 | AC50: 0.455453 | AE50: 0.440728 | AG50: 0.652966 | AI50: 0.455453 | AK50: 0.411286 | AM50: 1.378831 | AO50: 0.440728 | AQ50: 0.455453 | AS50: 1.191097 | AU50: 0.455453 | AW50: 0.455453 | AY50: 1.76709 | BA50: 0.455453 | BC50: 0.440728 | BE50: 1.049657
... A119: CRSP US Total Market TR USD | B119: 16.429239 | D119: 22.928928 | F119: 21.80874 | G119: 11.931917 | I119: 8.773324 | K119: 4.372037 | M119: 7.009013 | O119: 3.018227 | Q119: -3.964892 | S119: 2.258132 | U119: 2.703984 | W119: 4.149116 | Y119: -1.669959 | AA119: -0.193455 | AC119: 5.121505 | AE119: 7.216243 | AG119: 2.034668 | AI119: 2.338652 | AK119: -1.608018 | AM119: -6.082386 | AO119: -3.258113 | AQ119: 5.729835 | AS119: 3.186636 | AU119: 4.114233 | AW119: 0.610308 | AY119: 2.17964 | BA119: 3.445334 | BC119: 0.114776 | BE119: -1.686232
A120: Custom Alternative Diversified
A121: Div Infra & Property hdg 50 FTSE CORE INFRA 50 NREIT DEVELOPED | B121: 5.092377 | D121: 6.936921 | F121: 8.414583 | G121: 9.526396 | I121: 9.555488 | K121: -2.822168 | M121: 0.20464 | O121: 3.647803 | Q121: -3.600257 | S121: 3.91409 | U121: -0.901876 | W121: 5.913326 | Y121: 4.017241 | AA121: 2.277182 | AC121: -2.266124 | AE121: 3.272082 | AG121: -5.844078 | AI121: 1.4695 | AK121: 2.130609 | AM121: -0.751174 | AO121: -0.181217 | AQ121: 1.936589 | AS121: 0.231204 | AU121: 0.662055 | AW121: 2.467446 | AY121: 1.249513 | BA121: -0.518677 | BC121: 2.499789 | BE121: -1.923979
A122: DJ Brookfield Global Infrastructure Net Accum (Hgd to AUD)
A123: DJ Cmmdty Crude Oil TR USD | B123: 19.479342 | D123: 1.119122 | F123: 3.989045 | G123: 25.998713 | I123: -14.249754 | K123: 9.663338 | M123: 5.315537 | O123: 7.119768 | Q123: 0.342293 | S123: -7.322659 | U123: 6.386174 | W123: -0.566813 | Y123: -7.176616 | AA123: -7.932626 | AC123: 9.006986 | AE123: -0.614606 | AG123: 11.918555 | AI123: 2.031782 | AK123: -2.912782 | AM123: 3.100632 | AO123: -19.799034 | AQ123: 4.893865 | AS123: 7.423692 | AU123: 10.805563 | AW123: -7.614856 | AY123: -2.936143 | BA123: 0.052193 | BC123: -3.76244 | BE123: -2.892161
A124: DJ Gbl Select RESI NR AUD | B124: 6.517428 | D124: 7.404585 | F124: 6.130012 | G124: 9.896492 | I124: 1.010745 | K124: -0.98782 | M124: 1.3313 | O124: 2.58861 | Q124: -5.9539 | S124: 1.04877 | U124: 0.39727 | W124: 8.32023 | Y124: 2.32007 | AA124: 0.41573 | AC124: 0.79696 | AE124: 3.34367 | AG124: -2.05545 | AI124: 1.10028 | AK124: 3.22776 | AM124: -2.72753 | AO124: -2.5987 | AQ124: 1.52943 | AS124: -1.79308 | AU124: 0.70367 | AW124: 2.85439 | AY124: -0.35591 | BA124: 0.00225 | BC124: 2.61472 | BE124: -3.26339
A125: EURO STOXX 50 NR USD | B125: 15.317521 | D125: 22.548227 | F125: 20.983921 | G125: 9.787775 | I125: 27.632648 | K125: 4.474757 | M125: 6.239302 | O125: 3.921672 | Q125: -2.954019 | S125: 1.232748 | U125: -3.397198 | W125: 2.933414 | Y125: 0.213604 | AA125: -0.49214 | AC125: -0.411579 | AE125: -2.5397 | AG125: 5.153925 | AI125: 7.722556 | AK125: 3.810112 | AM125: -0.331334 | AO125: 1.2869 | AQ125: 4.317529 | AS125: 0.401103 | AU125: -0.323395 | AW125: 1.245817 | AY125: 2.500634 | BA125: 1.928759 | BC125: 0.624578 | BE125: 1.744299
A126: Fidelity Digital Health TR USD | B126: -0.260781 | D126: 3.480522 | F126: 3.05832 | G126: 12.631462 | I126: -6.306617 | K126: -0.464307 | M126: 3.102678 | O126: 2.067348 | Q126: -3.599884 | S126: -1.766154 | U126: -2.304404 | W126: 3.98133 | Y126: 1.253039 | AA126: 3.295213 | AC126: 0.518413 | AE126: 8.13898 | AG126: -1.045315 | AI126: 6.778676 | AK126: -2.347521 | AM126: -7.888846 | AO126: 0.527978 | AQ126: 3.907744 | AS126: 1.508928 | AU126: 1.206869 | AW126: 0.746393 | AY126: -0.37036 | BA126: -1.665933 | BC126: -1.985899 | BE126: -6.034339
A127: FTSE 100 NR EUR | B127: 16.06062 | D127: 19.10015 | F127: 22.181485 | G127: 7.205522 | I127: 25.78127 | K127: 2.131607 | M127: 1.308942 | O127: 4.553211 | Q127: 2.280666 | S127: 1.324956 | U127: -2.192636 | W127: 6.519343 | Y127: -0.595191 | AA127: -1.769684 | AC127: 0.16238 | AE127: 1.890619 | AG127: 1.964204 | AI127: 4.970311 | AK127: 3.583859 | AM127: 0.301495 | AO127: 0.215458 | AQ127: 4.032146 | AS127: -0.206091 | AU127: 2.633509 | AW127: 1.672424 | AY127: 0.224312 | BA127: 2.827285 | BC127: 1.007308 | BE127: 2.050959
A128: FTSE Australia 300 Choice TR AUD | B128: 9.734565 | D128: 12.953731 | F128: 13.313486 | G128: 9.661792 | I128: 11.256306 | K128: 1.66834 | M128: 2.64431 | O128: 3.28655 | Q128: -3.05186 | S128: 0.51642 | U128: 1.1086 | W128: 4.82722 | Y128: 1.17658 | AA128: 2.09947 | AC128: -0.31173 | AE128: 4.13991 | AG128: -3.33466 | AI128: 5.05173 | AK128: -4.10553 | AM128: -3.19013 | AO128: 4.91798 | AQ128: 4.81819 | AS128: 1.08099 | AU128: 1.67742 | AW128: 2.83747 | AY128: 0.03247 | BA128: -0.17978 | BC128: -2.40139 | BE128: 0.71012
A129: FTSE AW Ex US NR AUD | B129: 11.22507 | D129: 17.894929 | F129: 19.41979 | G129: 5.902553 | I129: 22.510179 | K129: 2.18445 | M129: 4.04742 | O129: 2.89903 | Q129: -1.28625 | S129: 0.3692 | U129: -0.66123 | W129: 4.88091 | Y129: -1.16769 | AA129: 0.64564 | AC129: 0.71317 | AE129: -0.30664 | AG129: 3.20798 | AI129: 3.01008 | AK129: 1.50574 | AM129: -0.29618 | AO129: 0.84627 | AQ129: 3.94348 | AS129: 1.4596 | AU129: 1.68838 | AW129: 1.87997 | AY129: 2.15984 | BA129: 3.19918 | BC129: -0.11738 | BE129: 1.28224
A130: FTSE Bitcoin PR USD | D130: 75.177687 | F130: 45.163582 | G130: 53.929322 | I130: -13.120184 | K130: 2.882005 | M130: 46.747967 | O130: 15.279055 | Q130: -14.610562 | S130: 9.634151 | U130: -8.877579 | W130: 7.426488 | Y130: -12.50888 | AA130: 5.492889 | AC130: 17.079986 | AE130: 39.173044 | AG130: 1.116717 | AI130: 8.23527 | AK130: -17.289031 | AM130: -2.092333 | AO130: 11.379974 | AQ130: 10.137267 | AS130: 0.560298 | AU130: 10.61853 | AW130: -7.87282 | AY130: 3.447303 | BA130: -2.959822 | BC130: -16.898 | BE130: -5.484198
A131: FTSE China 50 TR HKD | B131: 2.314462 | D131: 15.057861 | F131: 32.465498 | G131: 21.685941 | I131: 20.242639 | K131: -6.489103 | M131: 11.148279 | O131: 1.337286 | Q131: 8.614506 | S131: -0.969407 | U131: -0.623248 | W131: 1.407598 | Y131: -0.45748 | AA131: 20.171467 | AC131: 1.746218 | AE131: -3.935857 | AG131: 9.322796 | AI131: 1.627278 | AK131: 11.929891 | AM131: 1.639452 | AO131: -6.953004 | AQ131: 3.589364 | AS131: 2.514457 | AU131: 4.488053 | AW131: 0.705902 | AY131: 6.827325 | BA131: -2.975415 | BC131: -0.920597 | BE131: -2.597954
A132: FTSE China A50 NR CNY | B132: 1.347772 | D132: 9.238145 | F132: 21.365942 | G132: 17.309909 | I132: 13.360004 | K132: -2.041677 | M132: 9.176489 | O132: 1.247236 | Q132: 3.480935 | S132: -2.841155 | U132: -2.916461 | W132: 2.888734 | Y132: -2.75417 | AA132: 17.882861 | AC132: -1.375296 | AE132: -1.349606 | AG132: 7.131668 | AI132: -4.089399 | AK132: 2.198018 | AM132: 1.073706 | AO132: -4.542436 | AQ132: 2.718496 | AS132: 0.627806 | AU132: 4.296314 | AW132: 7.789511 | AY132: 0.214352 | BA132: 2.34903 | BC132: -0.706943 | BE132: 1.287903
A133: FTSE Developed All Cap NR AUD | B133: 14.745046 | D133: 21.199394 | F133: 20.665797 | G133: 9.443352 | I133: 13.071053 | K133: 3.90914 | M133: 5.79459 | O133: 3.10164 | Q133: -3.43055 | S133: 1.87085 | U133: 1.2579 | W133: 4.52535 | Y133: -1.44951 | AA133: -0.47784 | AC133: 3.63027 | AE133: 5.17408 | AG133: 2.07514 | AI133: 2.85588 | AK133: -0.626 | AM133: -4.4601 | AO133: -1.65213 | AQ133: 5.27192 | AS133: 2.56913 | AU133: 3.11112 | AW133: 1.09573 | AY133: 1.83522 | BA133: 3.26417 | BC133: 0.1677 | BE133: -0.69825
A134: FTSE Dvlp Core Infra 50/50 NR AUD | B134: 9.902711 | D134: 9.140476 | F134: 13.116209 | G134: 9.116703 | I134: 6.256152 | K134: 0.18632 | M134: 1.66185 | O134: 3.36805 | Q134: -1.88175 | S134: 3.29484 | U134: -3.12347 | W134: 8.75358 | Y134: 0.42932 | AA134: 0.35179 | AC134: 3.50022 | AE134: 4.04157 | AG134: -1.2997 | AI134: 0.6007 | AK134: 2.79443 | AM134: 1.63263 | AO134: -1.03929 | AQ134: 0.81063 | AS134: -1.04353 | AU134: 2.38961 | AW134: 0.28749 | AY134: 0.28917 | BA134: 0.34278 | BC134: 2.84794 | BE134: -3.6396
A135: FTSE Dvlp Core Infra 5050 NR Hdg AUD | B135: 6.966507 | D135: 7.674279 | F135: 11.719777 | G135: 9.148108 | I135: 11.573833 | K135: -2.21756 | M135: 0.597376 | O135: 3.65278 | Q135: -1.848798 | S135: 4.987358 | U135: -2.455733 | W135: 6.30063 | Y135: 3.035473 | AA135: 2.101456 | AC135: -0.791632 | AE135: 3.914161 | AG135: -5.3202 | AI135: 1.329783 | AK135: 2.355756 | AM135: 1.283588 | AO135: 0.004477 | AQ135: 1.330095 | AS135: 0.054693 | AU135: 1.545906 | AW135: 1.305657 | AY135: 1.622917 | BA135: -0.243986 | BC135: 2.943039 | BE135: -2.421377
A136: FTSE Dvlp Core Infrastructure TR Hdg AUD | B136: 6.843968 | D136: 7.225266 | F136: 11.686704 | G136: 10.427426 | I136: 11.662059 | K136: -2.1164 | M136: 0.99795 | O136: 3.52115 | Q136: -2.00396 | S136: 4.68651 | U136: -2.66486 | W136: 7.53424 | Y136: 3.26009 | AA136: 2.05205 | AC136: -0.91873 | AE136: 4.40684 | AG136: -6.74861 | AI136: 1.47003 | AK136: 2.94515 | AM136: 1.28437 | AO136: -0.79109 | AQ136: 1.07819 | AS136: 0.41245 | AU136: 1.39904 | AW136: 0.79365 | AY136: 2.63113 | BA136: -0.88907 | BC136: 3.40302 | BE136: -2.49589
A137: FTSE Dvlp Core Infrastructure TR USD | B137: 10.321487 | D137: 8.651873 | F137: 13.037744 | G137: 10.454353 | I137: 5.199425 | K137: 0.634938 | M137: 2.159095 | O137: 3.346755 | Q137: -1.985209 | S137: 2.680382 | U137: -3.268958 | W137: 10.081233 | Y137: 0.28206 | AA137: 0.094044 | AC137: 3.864072 | AE137: 4.769858 | AG137: -2.339374 | AI137: 0.659844 | AK137: 3.445884 | AM137: 1.356313 | AO137: -2.263082 | AQ137: 0.540392 | AS137: -1.02046 | AU137: 2.523177 | AW137: -0.415122 | AY137: 1.198794 | BA137: -0.14931 | BC137: 3.280817 | BE137: -3.819523
A138: FTSE EMs AC China A Inclusion NR AUD | B138: 8.01449 | D138: 15.63575 | F138: 19.202518 | G138: 8.70887 | I138: 15.548618 | K138: -0.44449 | M138: 5.6646 | O138: 1.44887 | Q138: 2.07836 | S138: -1.42964 | U138: 2.5449 | W138: 2.85421 | Y138: -1.90737 | AA138: 5.51272 | AC138: 1.77317 | AE138: -2.32854 | AG138: 5.53724 | AI138: -0.45183 | AK138: 0.39079 | AM138: 0.61339 | AO138: -1.81088 | AQ138: 3.62516 | AS138: 2.67622 | AU138: 3.49423 | AW138: 0.56138 | AY138: 4.64211 | BA138: 3.02557 | BC138: -1.87126 | BE138: -0.09476
A139: FTSE Environmental Opp All-Shares TR USD | B139: 14.481385 | D139: 23.643181 | F139: 22.042854 | G139: 12.121638 | I139: 15.733046 | K139: 0.781843 | M139: 7.715775 | O139: 2.392904 | Q139: -3.108089 | S139: 1.125013 | U139: 1.364197 | W139: 4.928422 | Y139: -2.856073 | AA139: 2.054107 | AC139: 2.130476 | AE139: 5.288288 | AG139: 4.215054 | AI139: 2.502634 | AK139: -3.717399 | AM139: -4.931101 | AO139: 0.003286 | AQ139: 8.751526 | AS139: 2.47523 | AU139: 2.999201 | AW139: -0.096258 | AY139: 4.832391 | BA139: 4.787823 | BC139: -2.351331 | BE139: 0.271911
A140: FTSE EPRA Nareit Dev Rental Hdg NR AUD | B140: 2.323273 | D140: 4.967335 | F140: 3.774035 | G140: 11.404071 | I140: 5.337771 | K140: -3.80173 | M140: -0.41821 | O140: 2.82895 | Q140: -5.66851 | S140: 3.4991 | U140: 0.83029 | W140: 5.68889 | Y140: 5.5263 | AA140: 2.62237 | AC140: -3.98022 | AE140: 2.95729 | AG140: -6.82562 | AI140: 1.38075 | AK140: 2.5711 | AM140: -3.17179 | AO140: -0.74279 | AQ140: 2.304 | AS140: 0.14082 | AU140: -0.49484 | AW140: 3.40209 | AY140: 0.78919 | BA140: -0.84996 | BC140: 1.79471 | BE140: -1.70557
A141: FTSE EPRA Nareit Developed NR AUD | B141: 5.803152 | D141: 7.247587 | F141: 6.382477 | G141: 9.353353 | I141: 1.737074 | K141: -0.92478 | M141: 0.91395 | O141: 3.25076 | Q141: -5.53139 | S141: 0.96819 | U141: -0.07729 | W141: 8.44534 | Y141: 2.26614 | AA141: 0.74854 | AC141: 0.53305 | AE141: 2.94724 | AG141: -2.229 | AI141: 0.99115 | AK141: 2.53458 | AM141: -2.51969 | AO141: -1.68292 | AQ141: 1.93113 | AS141: -0.937 | AU141: 0.59923 | AW141: 2.66827 | AY141: -0.36515 | BA141: -0.31472 | BC141: 1.83653 | BE141: -2.81828
A142: FTSE EPRA Nareit Developed NR Hdg AUD | B142: 3.059548 | D142: 6.030049 | F142: 5.108316 | G142: 10.754631 | I142: 7.494028 | K142: -3.42678 | M142: -0.1881 | O142: 3.64283 | Q142: -5.35172 | S142: 2.84082 | U142: 0.65198 | W142: 5.52602 | Y142: 4.99901 | AA142: 2.45291 | AC142: -3.74062 | AE142: 2.63 | AG142: -6.36796 | AI142: 1.60922 | AK142: 1.90546 | AM142: -2.78594 | AO142: -0.36691 | AQ142: 2.54308 | AS142: 0.40771 | AU142: -0.2218 | AW142: 3.62924 | AY142: 0.87611 | BA142: -0.79337 | BC142: 2.05654 | BE142: -1.42658
... A147: FTSE EPRA Nareit Dv ExAUS Rtl TR Hgd AUD | B147: 3.284994 | D147: 6.046247 | F147: 4.726978 | G147: 11.409491 | I147: 6.141158 | K147: -3.90973 | M147: -0.32043 | O147: 2.87853 | Q147: -5.54301 | S147: 3.69745 | U147: 1.08591 | W147: 5.60944 | Y147: 5.65445 | AA147: 2.71852 | AC147: -3.89514 | AE147: 3.05834 | AG147: -6.70413 | AI147: 1.3278 | AK147: 2.7981 | AM147: -2.99971 | AO147: -0.89854 | AQ147: 2.3934 | AS147: 0.31171 | AU147: -0.58281 | AW147: 3.29873 | AY147: 1.00837 | BA147: -0.80141 | BC147: 1.9519 | BE147: -1.62635
A148: FTSE Ethereum PR USD | D148: 36.202482 | F148: 15.483633 | G148: 80.932765 | I148: -17.352176 | K148: 2.859036 | M148: 49.06381 | O148: 8.248623 | Q148: -17.277169 | S148: 23.840845 | U148: -10.254122 | W148: -2.967738 | Y148: -25.106045 | AA148: 1.357816 | AC148: 2.451971 | AE148: 43.075801 | AG148: -2.059587 | AI148: -1.63254 | AK148: -32.683473 | AM148: -18.098071 | AO148: -4.226185 | AQ148: 42.385792 | AS148: -4.902643 | AU148: 52.430079 | AW148: 17.968856 | AY148: -8.059529 | BA148: -6.171615 | BC148: -21.761348 | BE148: -3.176255
A149: FTSE Global Core Infra 50/50 NR AUD | B149: 10.114471 | D149: 9.191463 | F149: 13.208609 | G149: 8.606486 | I149: 6.176829 | K149: 0.70164 | M149: 2.19006 | O149: 3.21209 | Q149: -0.88295 | S149: 2.43844 | U149: -3.08638 | W149: 8.8093 | Y149: 0.006 | AA149: 0.49368 | AC149: 3.10757 | AE149: 3.3981 | AG149: -0.9343 | AI149: 0.02038 | AK149: 2.22283 | AM149: 1.85484 | AO149: -0.98745 | AQ149: 1.07771 | AS149: -0.91734 | AU149: 2.10224 | AW149: -0.15965 | AY149: 0.68553 | BA149: 0.49606 | BC149: 3.13507 | BE149: -3.3494
A150: FTSE Global Core Infra 50/50 NR Hdg AUD | B150: 6.691685 | D150: 7.408845 | F150: 11.745007 | G150: 8.527755 | I150: 11.41836 | K150: -1.79205 | M150: 0.99314 | O150: 3.38325 | Q150: -0.80443 | S150: 4.34825 | U150: -2.23715 | W150: 6.39338 | Y150: 2.883 | AA150: 2.1051 | AC150: -1.29077 | AE150: 3.2132 | AG150: -5.14487 | AI150: 0.67145 | AK150: 1.78431 | AM150: 1.55621 | AO150: 0.22216 | AQ150: 1.6166 | AS150: 0.22518 | AU150: 1.15965 | AW150: 0.87069 | AY150: 1.94603 | BA150: -0.22515 | BC150: 3.19227 | BE150: -2.06296
A151: FTSE WGBI Hdg AUD | B151: -1.644893 | D151: 3.053308 | F151: 2.279972 | G151: 3.214938 | I151: 3.345269 | K151: -0.44929 | M151: -0.84447 | O151: 0.66513 | Q151: -1.73866 | S151: 0.47813 | U151: 0.72536 | W151: 1.89389 | Y151: 0.9167 | AA151: 0.99432 | AC151: -1.54875 | AE151: 1.17855 | AG151: -0.97625 | AI151: 0.26216 | AK151: 1.14071 | AM151: -0.54134 | AO151: 1.15796 | AQ151: -0.60472 | AS151: 0.76374 | AU151: -0.34862 | AW151: 0.29414 | AY151: 0.60269 | BA151: 0.83977 | BC151: 0.14444 | BE151: -0.3935
A152: Indxx AI and Big Data TR USD | B152: 17.676913 | D152: 38.065645 | F152: 30.36076 | G152: 16.388453 | I152: 23.33411 | K152: 3.70882 | M152: 8.243395 | O152: 1.847212 | Q152: -5.066328 | S152: 1.348808 | U152: 6.568324 | W152: 0.600101 | Y152: -2.613896 | AA152: 2.85511 | AC152: 4.320436 | AE152: 6.5274 | AG152: 4.960348 | AI152: 3.937489 | AK152: -2.977828 | AM152: -7.289638 | AO152: -0.75028 | AQ152: 8.483606 | AS152: 6.460293 | AU152: 4.081813 | AW152: -0.578203 | AY152: 8.209171 | BA152: 8.953348 | BC152: -5.738125 | BE152: 0.076813
A153: Indxx Global Cloud Computing NTR USD | B153: -0.288326 | D153: 13.484416 | F153: 1.738268 | G153: 20.846854 | I153: -11.906995 | K153: 2.441091 | M153: -0.437414 | O153: -1.092306 | Q153: -7.027731 | S153: -5.440548 | U153: 0.491581 | W153: 4.235405 | Y153: -3.099509 | AA153: -0.224955 | AC153: 7.954797 | AE153: 18.286305 | AG153: 2.446984 | AI153: 6.081135 | AK153: -7.710332 | AM153: -11.160268 | AO153: 0.430888 | AQ153: 5.612164 | AS153: -0.013269 | AU153: -1.066599 | AW153: -0.553234 | AY153: 0.505697 | BA153: 4.845633 | BC153: -5.952772 | BE153: -2.051294
A154: Indxx Global Robotics & AI TR USD | B154: 5.817787 | D154: 22.393517 | F154: 15.085108 | G154: 16.782829 | I154: 6.021965 | K154: 4.275425 | M154: 9.753168 | O154: 2.026767 | Q154: -4.952924 | S154: -0.023073 | U154: -0.034429 | W154: 2.574411 | Y154: -1.627294 | AA154: -0.114264 | AC154: 4.895082 | AE154: 4.943318 | AG154: 1.511024 | AI154: 3.01194 | AK154: -3.460407 | AM154: -11.440912 | AO154: -1.936377 | AQ154: 7.811505 | AS154: 3.686981 | AU154: 4.799143 | AW154: -1.273824 | AY154: 4.091233 | BA154: 7.586621 | BC154: -6.771282 | BE154: 1.66237
A155: Indxx Global Robotics & AI TR USD | B155: 5.81778 | D155: 22.393502 | F155: 15.085093 | G155: 16.782827 | I155: 6.021951 | K155: 4.275422 | M155: 9.753171 | O155: 2.026767 | Q155: -4.952922 | S155: -0.023075 | U155: -0.034433 | W155: 2.574413 | Y155: -1.627296 | AA155: -0.114267 | AC155: 4.895079 | AE155: 4.943315 | AG155: 1.511026 | AI155: 3.011944 | AK155: -3.460403 | AM155: -11.44091 | AO155: -1.936377 | AQ155: 7.8115 | AS155: 3.686977 | AU155: 4.799142 | AW155: -1.273826 | AY155: 4.091228 | BA155: 7.58662 | BC155: -6.771286 | BE155: 1.662369
A156: JPM GBI-EM Global Diversified TR USD | B156: 4.118145 | D156: 10.091099 | F156: 9.145432 | G156: 4.699954 | I156: 10.730432 | K156: 1.650081 | M156: 0.938036 | O156: -0.219649 | Q156: -1.677151 | S156: -0.785178 | U156: -1.495285 | W156: 4.600426 | Y156: -0.803078 | AA156: 1.121827 | AC156: 1.028614 | AE156: -0.0255 | AG156: 3.190164 | AI156: 1.298937 | AK156: 0.96499 | AM156: 1.334172 | AO156: 0.551454 | AQ156: 0.830374 | AS156: 0.934721 | AU156: 1.022888 | AW156: 0.49143 | AY156: 0.135185 | BA156: 1.704003 | BC156: 1.171704 | BE156: -0.188073
A157: LBMA Gold Price PM USD | B157: 21.772547 | D157: 34.791079 | F157: 46.641588 | G157: 13.143165 | I157: 55.431735 | K157: 1.973005 | M157: 1.263309 | O157: 7.912937 | Q157: 4.673452 | S157: -0.614554 | U157: -1.155395 | W157: 6.459945 | Y157: -0.305083 | AA157: 2.338905 | AC157: 10.112763 | AE157: -2.510944 | AG157: 3.551862 | AI157: 6.983774 | AK157: 1.107584 | AM157: 9.668571 | AO157: 3.235036 | AQ157: -1.312916 | AS157: -1.504043 | AU157: 2.139452 | AW157: 2.257921 | AY157: 10.163756 | BA157: 6.165178 | BC157: 4.293265 | BE157: 2.490229
A158: MarketVector Bitcoin Bnchmk Rate TR USD | B158: 28.653996 | D158: 75.030879 | F158: 44.880323 | G158: 54.141731 | I158: -13.515193 | K158: 3.94574 | M158: 47.036113 | O158: 14.10753 | Q158: -15.109872 | S158: 9.886387 | U158: -8.653409 | W158: 8.817766 | Y158: -13.951331 | AA158: 5.303458 | AC158: 17.633224 | AE158: 38.499133 | AG158: 1.666273 | AI158: 7.932566 | AK158: -17.289641 | AM158: -1.460451 | AO158: 10.310927 | AQ158: 10.787591 | AS158: 0.774784 | AU158: 10.933168 | AW158: -8.441616 | AY158: 3.321639 | BA158: -2.697057 | BC158: -16.797546 | BE158: -6.040135
A159: Mercer Unlisted Property Index
A160: Morningstar APAC xJpn NR AUD | B160: 7.804497 | D160: 15.523226 | F160: 19.291487 | G160: 8.609351 | I160: 19.020728 | K160: -1.14514 | M160: 5.59815 | O160: 2.05231 | Q160: 1.02717 | S160: -0.58068 | U160: 3.14316 | W160: 2.55812 | Y160: -1.71617 | AA160: 4.84215 | AC160: 0.6324 | AE160: -1.68979 | AG160: 3.62039 | AI160: -0.03661 | AK160: -0.07406 | AM160: -0.60797 | AO160: -0.94803 | AQ160: 4.90113 | AS160: 3.67479 | AU160: 3.81869 | AW160: 0.2858 | AY160: 3.84036 | BA160: 4.81187 | BC160: -2.67632 | BE160: 0.90791
A161: Morningstar AUS Agg Tgt Alloc NR AUD | B161: 10.446274 | D161: 14.801448 | F161: 14.472671 | G161: 6.88133 | I161: 12.66758 | K161: 1.73761 | M161: 2.9386 | O161: 2.90775 | Q161: -3.04582 | S161: 1.54855 | U161: 1.25282 | W161: 3.63538 | Y161: 0.31521 | AA161: 1.68849 | AC161: -0.00325 | AE161: 3.57652 | AG161: -1.13204 | AI161: 3.15257 | AK161: -1.49121 | AM161: -3.2701 | AO161: 0.94484 | AQ161: 4.04767 | AS161: 1.99534 | AU161: 2.2421 | AW161: 2.21012 | AY161: 0.96925 | BA161: 1.79837 | BC161: -0.79166 | BE161: 0.41176
A162: Morningstar AUS Balance Tgt Alloc NR AUD | B162: 5.607414 | D162: 9.72249 | F162: 9.356532 | G162: 4.445597 | I162: 8.599614 | K162: 0.97442 | M162: 1.46685 | O162: 2.01317 | Q162: -2.38612 | S162: 1.09816 | U162: 0.99444 | W162: 2.71493 | Y162: 0.66696 | AA162: 1.18405 | AC162: -0.67899 | AE162: 2.41574 | AG162: -0.67086 | AI162: 1.87484 | AK162: -0.37671 | AM162: -1.78595 | AO162: 1.08211 | AQ162: 2.20645 | AS162: 1.40935 | AU162: 1.21245 | AW162: 1.42229 | AY162: 0.66659 | BA162: 1.18844 | BC162: -0.60468 | BE162: 0.05682
A163: Morningstar AUS Con Tgt Alloc NR AUD | B163: 1.405189 | D163: 4.702102 | F163: 4.247839 | G163: 2.447929 | I163: 4.168883 | K163: 0.38495 | M163: 0.01435 | O163: 1.09064 | Q163: -1.46206 | S163: 0.45841 | U163: 0.69934 | W163: 1.50224 | Y163: 0.8281 | AA163: 0.59372 | AC163: -1.10531 | AE163: 1.19002 | AG163: 0.09194 | AI163: 0.6569 | AK163: 0.40382 | AM163: -0.20478 | AO163: 1.30811 | AQ163: 0.53146 | AS163: 0.75915 | AU163: 0.26567 | AW163: 0.58848 | AY163: 0.16577 | BA163: 0.45345 | BC163: -0.64491 | BE163: -0.17738
A164: Morningstar AUS Growth Tgt Alloc NR AUD | B164: 7.978461 | D164: 12.08488 | F164: 11.746621 | G164: 5.689802 | I164: 10.699037 | K164: 1.29354 | M164: 2.07371 | O164: 2.50011 | Q164: -2.79026 | S164: 1.29266 | U164: 1.07962 | W164: 3.24376 | Y164: 0.52381 | AA164: 1.48625 | AC164: -0.42543 | AE164: 2.98139 | AG164: -0.98375 | AI164: 2.57332 | AK164: -0.99321 | AM164: -2.51298 | AO164: 1.15918 | AQ164: 3.09158 | AS164: 1.67158 | AU164: 1.7222 | AW164: 1.90057 | AY164: 0.74633 | BA164: 1.45925 | BC164: -0.73275 | BE164: 0.26523
A165: Morningstar AUS Mod Tgt Alloc NR AUD | B165: 3.382512 | D165: 7.201367 | F165: 6.771503 | G165: 3.381862 | I165: 6.56674 | K165: 0.59675 | M165: 0.67652 | O165: 1.58729 | Q165: -2.0119 | S165: 0.81376 | U165: 0.80348 | W165: 2.22882 | Y165: 0.82534 | AA165: 0.94076 | AC165: -0.94336 | AE165: 1.77574 | AG165: -0.45227 | AI165: 1.28107 | AK165: 0.10692 | AM165: -1.00802 | AO165: 1.18781 | AQ165: 1.2941 | AS165: 1.07077 | AU165: 0.71495 | AW165: 1.06078 | AY165: 0.46655 | BA165: 0.85046 | BC165: -0.52841 | BE165: -0.0883
A166: Morningstar China NR AUD | B166: -0.175752 | D166: 11.687375 | F166: 25.17884 | G166: 22.405303 | I166: 22.041367 | K166: -7.53708 | M166: 9.92856 | O166: 0.4253 | Q166: 6.67348 | S166: 0.04829 | U166: -2.72702 | W166: 0.7287 | Y166: -3.3987 | AA166: 21.26435 | AC166: -0.40858 | AE166: -3.97029 | AG166: 7.36884 | AI166: -0.10417 | AK166: 11.65903 | AM166: 1.66801 | AO166: -6.4978 | AQ166: 2.44786 | AS166: 2.21728 | AU166: 6.73698 | AW166: 3.55913 | AY166: 7.38599 | BA166: -2.41286 | BC166: -2.74906 | BE166: -2.43475
A167: Morningstar DM Tech Moat Foc NR USD | B167: 8.95486 | D167: 20.453959 | F167: 12.082651 | G167: 16.758841 | I167: 1.478591 | K167: 1.566125 | M167: 9.781187 | O167: 0.302973 | Q167: -6.831758 | S167: -2.033033 | U167: 2.540749 | W167: 3.200738 | Y167: 0.760691 | AA167: -1.943233 | AC167: 4.292768 | AE167: 10.171526 | AG167: 0.94682 | AI167: 3.945902 | AK167: -0.607863 | AM167: -9.60228 | AO167: -2.891473 | AQ167: 9.059534 | AS167: 5.012544 | AU167: 2.562578 | AW167: -1.803038 | AY167: -0.214254 | BA167: 2.752851 | BC167: -5.616334 | BE167: 0.241867
A168: Morningstar Gbl Tech NR AUD | B168: 19.874436 | D168: 35.65159 | F168: 28.462267 | G168: 17.092154 | I168: 15.965525 | K168: 6.14313 | M168: 7.8129 | O168: 1.96041 | Q168: -5.27509 | S168: 4.89068 | U168: 8.10394 | W168: 0.21453 | Y168: -2.24882 | AA168: -0.38755 | AC168: 4.78148 | AE168: 4.94024 | AG168: 5.82604 | AI168: -1.33391 | AK168: -1.67566 | AM168: -8.75556 | AO168: -0.80277 | AQ168: 9.42716 | AS168: 7.01275 | AU168: 5.50031 | AW168: -0.95256 | AY168: 5.9119 | BA168: 7.93445 | BC168: -4.73662 | BE168: -0.89273
A169: Morningstar India NR AUD | B169: 14.713733 | D169: 13.431979 | F169: 8.391948 | G169: 14.900071 | I169: -5.204095 | K169: 6.13556 | M169: 3.5517 | O169: -0.16154 | Q169: 3.84514 | S169: -1.70862 | U169: 6.89113 | W169: 6.40725 | Y169: -3.08152 | AA169: -0.10989 | AC169: -1.6421 | AE169: -0.09706 | AG169: 2.27214 | AI169: -5.27159 | AK169: -8.73689 | AM169: 9.54015 | AO169: 1.58129 | AQ169: 1.82397 | AS169: 1.66883 | AU169: -3.18353 | AW169: -3.99349 | AY169: -0.65063 | BA169: 5.49902 | BC169: -0.04681 | BE169: -2.24724
A170: MSCI AC Asia Ex Japan NR USD | B170: 6.807219 | D170: 16.862284 | F170: 23.094046 | G170: 10.815588 | I170: 22.801511 | K170: -2.405705 | M170: 7.202911 | O170: 2.343681 | Q170: 1.721203 | S170: -0.838982 | U170: 3.817593 | W170: 2.138266 | Y170: -1.881826 | AA170: 6.04811 | AC170: 1.049175 | AE170: -2.757966 | AG170: 5.372488 | AI170: 0.000889 | AK170: 1.342837 | AM170: -0.180337 | AO170: -1.889896 | AQ170: 4.65437 | AS170: 4.15017 | AU170: 4.39166 | AW170: -0.547532 | AY170: 5.490103 | BA170: 5.789321 | BC170: -3.011521 | BE170: 1.019346
A171: MSCI AC Asia Ex Japan NR USD | B171: 6.807224 | D171: 16.862292 | F171: 23.094053 | G171: 10.815588 | I171: 22.801512 | K171: -2.405706 | M171: 7.202914 | O171: 2.343679 | Q171: 1.7212 | S171: -0.838979 | U171: 3.817598 | W171: 2.138264 | Y171: -1.881825 | AA171: 6.048111 | AC171: 1.049176 | AE171: -2.757963 | AG171: 5.372491 | AI171: 0.000889 | AK171: 1.342839 | AM171: -0.180349 | AO171: -1.889883 | AQ171: 4.65437 | AS171: 4.150168 | AU171: 4.391661 | AW171: -0.547531 | AY171: 5.4901 | BA171: 5.789324 | BC171: -3.011525 | BE171: 1.019345
... A236: NYSE FANG+ TR USD | B236: 23.989989 | D236: 53.906972 | F236: 36.64984 | G236: 20.4298 | I236: 12.20107 | K236: 6.711662 | M236: 11.515887 | O236: 0.899409 | Q236: -2.409844 | S236: 3.81181 | U236: 9.161638 | W236: 0.929579 | Y236: -4.298721 | AA236: 0.599991 | AC236: 7.875927 | AE236: 7.334941 | AG236: 11.393891 | AI236: 2.445419 | AK236: -4.624296 | AM236: -10.61308 | AO236: 4.406095 | AQ236: 11.145088 | AS236: 6.630104 | AU236: 3.365673 | AW236: -1.081722 | AY236: 4.34774 | BA236: 6.013554 | BC236: -1.890847 | BE236: -6.440064
A237: OECD G7 Inflation + 5.5% | K237: 0.696223 | M237: 0.668897 | O237: 0.708794 | Q237: 0.680226 | S237: 0.694268 | U237: 0.663318 | W237: 0.67773 | Y237: 0.654677 | AA237: 0.620547 | AC237: 0.64952 | AE237: 0.652499 | AG237: 0.682757 | AI237: 0.694288 | AK237: 0.635547 | AM237: 0.65737 | AO237: 0.640108 | AQ237: 0.652657 | AS237: 0.653478 | AU237: 0.668937 | AW237: 0.677042 | AY237: 0.67213
A238: RBA Cash Rate | B238: 2.759361 | D238: 4.066377 | F238: 4.110378 | G238: 0.098745 | I238: 3.822528 | K238: 0.362299 | M238: 0.338095 | O238: 0.361538 | Q238: 0.351692 | S238: 0.363235 | U238: 0.353046 | W238: 0.371215 | Y238: 0.364349 | AA238: 0.35552 | AC238: 0.366844 | AE238: 0.355971 | AG238: 0.368947 | AI238: 0.361319 | AK238: 0.314491 | AM238: 0.342894 | AO238: 0.324575 | AQ238: 0.315572 | AS238: 0.297852 | AU238: 0.307414 | AW238: 0.302055 | AY238: 0.289254 | BA238: 0.297042 | BC238: 0.294876 | BE238: 0.309828
A239: RBA Cash Rate + 1.0% | B239: 3.786736 | D239: 5.107165 | F239: 5.152083 | G239: 0.100939 | I239: 4.859932 | K239: 0.447083 | M239: 0.417387 | O239: 0.446321 | Q239: 0.433731 | S239: 0.44802 | U239: 0.435086 | W239: 0.456006 | Y239: 0.449134 | AA239: 0.437562 | AC239: 0.451631 | AE239: 0.438013 | AG239: 0.453737 | AI239: 0.446102 | AK239: 0.391031 | AM239: 0.427662 | AO239: 0.406593 | AQ239: 0.400317 | AS239: 0.379848 | AU239: 0.392153 | AW239: 0.386789 | AY239: 0.371244 | BA239: 0.381772 | BC239: 0.37687 | BE239: 0.394569
A240: RBA Cash Rate + 1.5% | B240: 4.300423 | D240: 5.62756 | F240: 5.672937 | G240: 0.102211 | I240: 5.378631 | K240: 0.489187 | M240: 0.456763 | O240: 0.488425 | Q240: 0.474471 | S240: 0.490124 | U240: 0.475827 | W240: 0.498114 | Y240: 0.491239 | AA240: 0.478304 | AC240: 0.493737 | AE240: 0.478755 | AG240: 0.495843 | AI240: 0.488206 | AK240: 0.429038 | AM240: 0.469759 | AO240: 0.447322 | AQ240: 0.442403 | AS240: 0.420567 | AU240: 0.434235 | AW240: 0.428869 | AY240: 0.41196 | BA240: 0.42385 | BC240: 0.417588 | BE240: 0.436652
A241: RBA Cash Rate + 1.6% | B241: 4.40316 | D241: 5.731639 | F241: 5.777108 | G241: 0.102479 | I241: 5.482371 | K241: 0.497585 | M241: 0.464617 | O241: 0.496823 | Q241: 0.482597 | S241: 0.498523 | U241: 0.483953 | W241: 0.506513 | Y241: 0.499637 | AA241: 0.48643 | AC241: 0.502135 | AE241: 0.486881 | AG241: 0.504242 | AI241: 0.496604 | AK241: 0.436619 | AM241: 0.478155 | AO241: 0.455446 | AQ241: 0.450797 | AS241: 0.428689 | AU241: 0.442629 | AW241: 0.437262 | AY241: 0.420081 | BA241: 0.432243 | BC241: 0.42571 | BE241: 0.445046
...
