Workbook

Sheet Page One - IM Info
B2: MyNorth Investment Manager Onboarding Questionnaire
B3: Page One: Investment Manager Information
B4: All information required
G6: =D6 -> 0
B7: Part 1 - About the Investment Manager | D7: Response | E7: Progress | F7: =COUNTA(D8:F21)/ROWS(D8:F21) -> 1 | G7: =D7 -> Response
B8: 1 | C8: Investment Manager's full legal entity name as per ABN | D8: Salita Portfolio Services Pty Ltd | G8: =D8 -> Salita Portfolio Services Pty Ltd
B9: 2 | C9: Australian Business Number (ABN) | D9: 39 609 946 616 | G9: =D9 -> 39 609 946 616
B10: 3 | C10: Australian Financial Services License (AFSL) | D10: Salita Portfolio Services Pty Ltd is a corporate authorised representative of Personal Financial Services Ltd (PFS) CAR 1241713 | G10: =D10 -> Salita Portfolio Services Pty Ltd is a corporate authorised representative of Personal Financial Services Ltd (PFS) CAR 1241713
B11: =B10+1 -> 4 | C11: Street Address | D11: Level 6 88 Phillip Street Sydney NSW 2000 | G11: =D11 -> Level 6 88 Phillip Street Sydney NSW 2000
B12: =B11+1 -> 5 | C12: Postal Address | D12: Level 6 88 Phillip Street Sydney NSW 2001 | G12: =D12 -> Level 6 88 Phillip Street Sydney NSW 2001
B13: =B12+1 -> 6 | C13: Telephone number | D13: 0407494569 | G13: =D13 -> 0407494569
B14: =B13+1 -> 7 | C14: Email (General) | D14: jcarnevale@entireti.com.au | G14: =D14 -> jcarnevale@entireti.com.au
B15: =B14+1 -> 8 | C15: Email (Invoices) | D15: jcarnevale@entireti.com.au | G15: =D15 -> jcarnevale@entireti.com.au
B16: =B15+1 -> 9 | C16: Overview of the Investment Manager's business - Include any corporate authorised representative or if any other relevant entities different to the AFSL holder involved in the management/construction of the portfolio | D16: Salita Portfolio Services (“Salita”) is a wholly owned subsidiary of Entireti Limited and a corporate authorised representative of Personal Financial Services. Established in 2016, Salita provides professional investment research, analysis, and management services for a suite of managed portfolios. The Salita investment team oversees daily operations, drawing on the resources of the Entireti Group and external consultants to ensure a prudent, informed, and professional approach to implementing Salita’s investment philosophy across diverse portfolios tailored to specific risk and return objectives. | G16: =D16 -> Salita Portfolio Services (“Salita”) is a wholly owned subsidiary of Entireti Limited and a corporate authorised representative of Personal Financial Services. Established in 2016, Salita provides professional investment research, analysis, and management services for a suite of managed portfolios. The Salita investment team oversees daily operations, drawing on the resources of the Entireti Group and external consultants to ensure a prudent, informed, and professional approach to implementing Salita’s investment philosophy across diverse portfolios tailored to specific risk and return objectives.
B17: =B16+1 -> 10 | C17: About the investment manager (this is for disclosure purposes and should not include quantitative information that may go out of date quickly) (250 words max) | D17: Salita Portfolio Services (“Salita”) is a wholly owned subsidiary of Entireti Limited and a corporate authorised representative of Personal Financial Services. Established in 2016, Salita provides professional investment research, analysis, and management services for a suite of managed portfolios. The Salita investment team oversees daily operations, drawing on the resources of the Entireti Group and external consultants to ensure a prudent, informed, and professional approach to implementing Salita’s investment philosophy across diverse portfolios tailored to specific risk and return objectives.
B18: =B17+1 -> 11 | C18: Describe the investment philosophy and process | D18: At Salita Portfolio Services, the approach to portfolio construction is driven by the following investment principles: • Growing and preserving capital - The overarching goal is to grow investor wealth over time whilst minimising the risk of permanent capital loss. Whilst negative returns may be experienced over various time periods, Salita Portfolio Services' focus is on minimising drawdowns and preserving capital over the medium to long term. • Long term approach - Salita Portfolio Services ensures the Strategic Asset Allocation (SAA) is aligned to client risk profiles. The SAA is built around medium to long term capital market assumptions and is reviewed annually to ensure consistency with overall portfolio objectives. Salita Portfolio Services believe that timing the market is difficult and therefore do not intend to take a short-term tactical asset allocation approach. Rather they interrogate the SAA on a regular basis to determine if changes are warranted to support a high conviction medium term view. • Managing turnover - As part of a longer-term approach, Salita Portfolio Services aim to keep turnover within the portfolio to a minimum. Part of this approach is to ensure investment products are measured over the appropriate time horizon. • Active and passive investment strategies - Salita Portfolio Services assess the merits of active management across each asset class and will use active management where they have strong conviction that it will lead to a superior outcome, either via outperformance and/or lowering drawdown risk. Typically, this results in a blend of active and passive investment strategies in portfolios. • A focus on fees - Assessing the level and appropriateness of fees, both at the individual investment product and overall portfolio level is an important feature of Salita Portfolio Services' approach. Lower fees are the preference but paying an appropriate fee to gain access to superior investment skills is also worthy of consideration. • Diversification - Salita Portfolio Services believe that diversification is an effective way to manage risk. It enables portfolios to perform through varied market conditions and not be wholly reliant on a particular style (i.e. Growth or Value) being in favour. | G18: =D18 -> At Salita Portfolio Services, the approach to portfolio construction is driven by the following investment principles: • Growing and preserving capital - The overarching goal is to grow investor wealth over time whilst minimising the risk of permanent capital loss. Whilst negative returns may be experienced over various time periods, Salita Portfolio Services' focus is on minimising drawdowns and preserving capital over the medium to long term. • Long term approach - Salita Portfolio Services ensures the Strategic Asset Allocation (SAA) is aligned to client risk profiles. The SAA is built around medium to long term capital market assumptions and is reviewed annually to ensure consistency with overall portfolio objectives. Salita Portfolio Services believe that timing the market is difficult and therefore do not intend to take a short-term tactical asset allocation approach. Rather they interrogate the SAA on a regular basis to determine if changes are warranted to support a high conviction medium term view. • Managing turnover - As part of a longer-term approach, Salita Portfolio Services aim to keep turnover within the portfolio to a minimum. Part of this approach is to ensure investment products are measured over the appropriate time horizon. • Active and passive investment strategies - Salita Portfolio Services assess the merits of active management across each asset class and will use active management where they have strong conviction that it will lead to a superior outcome, either via outperformance and/or lowering drawdown risk. Typically, this results in a blend of active and passive investment strategies in portfolios. • A focus on fees - Assessing the level and appropriateness of fees, both at the individual investment product and overall portfolio level is an important feature of Salita Portfolio Services' approach. Lower fees are the preference but paying an appropriate fee to gain access to superior investment skills is also worthy of consideration. • Diversification - Salita Portfolio Services believe that diversification is an effective way to manage risk. It enables portfolios to perform through varied market conditions and not be wholly reliant on a particular style (i.e. Growth or Value) being in favour.
B19: =B18+1 -> 12 | C19: Investment philosophy and process (this is for disclosure purposes and should not include quantitative information that may go out of date quickly) (180 words max) | D19: Salita Portfolio Services focuses on growing and preserving capital while minimising permanent loss. We avoid short-term tactical shifts, instead reviewing the Strategic Asset Allocation regularly to support high-conviction medium-term views. We maintain low turnover and blend active and passive strategies, using active management where conviction is strong. Fees are assessed carefully, balancing cost with value. Diversification across styles reduces volatility and enhances consistency, ensuring portfolios perform across varied market conditions while supporting sustainable, long-term wealth creation.
B20: =B19+1 -> 13 | C20: What is the strategy's capacity and FUM? | D20: N/A
B21: =B20+1 -> 14 | C21: What is the company's website? | D21: https://salitaportfolioservices.com.au/ | G21: =D21 -> https://salitaportfolioservices.com.au/
G22: =D22 -> 0
B23: Part 2 - About the Portfolio Manager | D23: Response | E23: Progress | F23: =COUNTA(D24:F26)/ROWS(D24:F26) -> 1 | G23: =D23 -> Response
B24: 1 | C24: Name of portfolio manager | D24: Aman Ramrakha | G24: =D24 -> Aman Ramrakha
B25: 2 | C25: Company position of portfolio manager (include any qualification reference) | D25: Chief Investment Officer | G25: =D25 -> Chief Investment Officer
B26: 3 | C26: Brief bio of portfolio manager | D26: Aman brings over 30 years’ experience in financial services, spanning technical, consulting, and advisory roles. Before joining Entireti in 2025, he was Executive Director of Research at Rainmaker Information. His career includes senior positions at Morningstar, where he oversaw Manager Research and provided investment consulting services, and at Commonwealth Bank, where he led investment and insurance research for over $60B of funds under advice. Aman has also held roles at BT Financial Group, Colonial First State, KPMG and Commonwealth Private. He holds a Bachelor of Commerce, a Graduate Diploma in Applied Finance and Investments, a Diploma of Financial Planning, and is a Certified Investment Management Consultant. | G26: =D26 -> Aman brings over 30 years’ experience in financial services, spanning technical, consulting, and advisory roles. Before joining Entireti in 2025, he was Executive Director of Research at Rainmaker Information. His career includes senior positions at Morningstar, where he oversaw Manager Research and provided investment consulting services, and at Commonwealth Bank, where he led investment and insurance research for over $60B of funds under advice. Aman has also held roles at BT Financial Group, Colonial First State, KPMG and Commonwealth Private. He holds a Bachelor of Commerce, a Graduate Diploma in Applied Finance and Investments, a Diploma of Financial Planning, and is a Certified Investment Management Consultant.
G27: =D27 -> 0
B28: Part 3 - Portfolio attachment checklist | D28: Response | E28: Progress | F28: =COUNTA(D29:F35)/ROWS(D29:F35) -> 1 | G28: =D28 -> Response
B29: 1 | C29: FSC Document or standard RFP | D29: Not available | G29: =D29 -> Not available
B30: 2 | C30: Monthly return series of flagship SMAs since inception | D30: Attached
B31: 4 | C31: Pitch pack / fact sheet (Investment Team, process, portfolio & performance) | D31: Attached | G31: =D31 -> Attached
B32: 5 | C32: Certificates of Insurance | D32: Attached | G32: =D32 -> Attached
B33: 6 | C33: Copy of AFSL | D33: Not available | G33: =D33 -> Not available
B34: 7 | C34: Conflicts of Interest Policy | D34: Attached | G34: =D34 -> Attached
B35: 8 | C35: Any relevant biographies or org charts | D35: Attached | G35: =D35 -> Attached
B37: Part 4 - Corporate Actions likelihood of involvement | D37: Response | E37: Progress | F37: =COUNTA(D38:F44)/ROWS(D38:F44) -> 1
B38: 1 | C38: Interest to participate in IPOs? | D38: No
B39: 2 | C39: Interest to participate in placements? | D39: No
B40: 3 | C40: Interest to participate in entitlements? | D40: No
B41: 4 | C41: Interest to participate in rights issues? | D41: No
B42: 5 | C42: Interest to participate in SPPs? | D42: No
B43: 6 | C43: Interest to participate in bonus option issues? | D43: No
B44: 7 | C44: Interest to participate in voting at AGMs etc? | D44: No
B46: Part 5 - Transparency of Holdings | D46: Response | E46: Progress | F46: =COUNTA(D47)/ROWS(D47) -> 1
B47: 1 | C47: What is your preference on the extent of disclosure of holdings on the platform? | D47: None
B49: Part 6 - Investment Manager's Bank Account (only applicable to new investment managers not avaliable on MyNorth Managed Portfolios) | D49: Response | E49: Progress | F49: =COUNTA(D50:F53)/ROWS(D50:F53) -> 1
B50: 1 | C50: Name of bank | D50: Westpac Banking Corporation
B51: 2 | C51: Account name | D51: Salita Portfolio Services Pty Ltd
B52: 3 | C52: BSB | D52: 033 009
B53: 4 | C53: Account number | D53: 642545
B55: Part 7 - Investment Manager's Trademark (only applicable to new investment managers not avaliable on MyNorth Managed Portfolios) | D55: Response | E55: Progress | F55: =COUNTA(D56)/ROWS(D56) -> 0
B56: 1 | C56: Company logo

Sheet Page Two - IM Info contd
B2: MyNorth Investment Manager Onboarding Questionnaire
B3: Page Two: Investment Manager Information
B4: All information required - Insert new rows as required
B7: Part 6 - Current Investment Team | D7: Response
B8: Name & title/position | D8: Number of years with the firm | E8: Total years of investment experience | F8: Describe their role and contribution to the strategy
C9: John Carnevale (Executive GM – Investment Services) | D9: 6 | E9: 35 | F9: Oversight of Research & Investment Team
C10: Aman Ramrakha (Chief Investment Officer) | D10: <1 | E10: 30 | F10: Overall responsibility for portfolios
C11: Tim Schroeders (Senior Portfolio Manager) | D11: 6 | E11: 30 | F11: Overall responsibility for portfolios
C12: Sean Webster (Head of Research & Senior Portfolio Manager) | D12: 7 | E12: 29 | F12: Provides portfolio management support
C13: Calvin Yap (Senior Investment Research Analyst) | D13: 3 | E13: 4 | F13: Provides support to portfolio managers
C14: Julia Tao (Senior Investment Research Analyst) | D14: 6 | E14: 18 | F14: Provides support to portfolio managers
C15: Frank Mach (Investment Research Analyst) | D15: 5 | E15: 15 | F15: Provides support to portfolio managers
C16: Cindy Zhao (Manager, Investment Governance) | D16: 5 | E16: 15 | F16: Governance oversight for portfolios
C17: Ekta Badola (Investmengt Research Analyst) | D17: 2 | E17: 5 | F17: Provides support to portfolio managers
B19: Team additions in the last three years
B20: Name & title/position | D20: Date joined | E20: Total years of investment experience | F20: Previous employment
C21: Aman Ramrakha (Chief Investment Officer) | D21: 45686 | E21: 30 | F21: Rainmaker, Morningstar, CBA
B24: Team departures in the last three years
B25: Name & title/position | D25: Date joined | E25: Date departed | F25: Reason for departure
C26: Ian Holliday (Head of Research Services) | D26: 43405

Sheet Page Four - Portfolio Details
B2: MyNorth Investment Manager Onboarding Questionnaire
B3: Page Four: Portfolio Details
B4: All information required
B6: Part 1: General portfolio details | D6: Response | G6: Progress | H6: =COUNTA(D7:H19)/ROWS(D7:H19) -> 1 | L6: Part 1: General portfolio details | N6: Response | Q6: Progress | R6: =COUNTA(N7:R19)/ROWS(N7:R19) -> 1 | V6: Part 1: General portfolio details | X6: Response | AA6: Progress | AB6: =COUNTA(X7:AB19)/ROWS(X7:AB19) -> 0.076923077 | AF6: Part 1: General portfolio details | AH6: Response | AK6: Progress | AL6: =COUNTA(AH7:AL19)/ROWS(AH7:AL19) -> 0.076923077 | AP6: Part 1: General portfolio details | AR6: Response | AU6: Progress | AV6: =COUNTA(AR7:AV19)/ROWS(AR7:AV19) -> 0.076923077 | AZ6: Part 1: General portfolio details | BB6: Response | BE6: Progress | BF6: =COUNTA(BB7:BF19)/ROWS(BB7:BF19) -> 0.076923077 | BJ6: Part 1: General portfolio details | BL6: Response | BO6: Progress | BP6: =COUNTA(BL7:BP19)/ROWS(BL7:BP19) -> 0.076923077 | BT6: Part 1: General portfolio details | BV6: Response | BY6: Progress | BZ6: =COUNTA(BV7:BZ19)/ROWS(BV7:BZ19) -> 0.076923077 | CD6: Part 1: General portfolio details | CF6: Response | CI6: Progress | CJ6: =COUNTA(CF7:CJ19)/ROWS(CF7:CJ19) -> 0.076923077 | CN6: Part 1: General portfolio details | CP6: Response | CS6: Progress | CT6: =COUNTA(CP7:CT19)/ROWS(CP7:CT19) -> 0.076923077
B7: 1 | C7: Proposed managed portfolio name | D7: Aurora Growth Managed Portfolio | L7: 1 | M7: Proposed managed portfolio name | N7: Aurora Defensive Managed Portfolio | V7: 1 | W7: Proposed managed portfolio name | X7: ='Page Two - IM Info contd'!#REF! -> #REF! | AF7: 1 | AG7: Proposed managed portfolio name | AH7: ='Page Two - IM Info contd'!#REF! -> #REF! | AP7: 1 | AQ7: Proposed managed portfolio name | AR7: ='Page Two - IM Info contd'!#REF! -> #REF! | AZ7: 1 | BA7: Proposed managed portfolio name | BB7: ='Page Two - IM Info contd'!#REF! -> #REF! | BJ7: 1 | BK7: Proposed managed portfolio name | BL7: ='Page Two - IM Info contd'!#REF! -> #REF! | BT7: 1 | BU7: Proposed managed portfolio name | BV7: ='Page Two - IM Info contd'!#REF! -> #REF! | CD7: 1 | CE7: Proposed managed portfolio name | CF7: ='Page Two - IM Info contd'!#REF! -> #REF! | CN7: 1 | CO7: Proposed managed portfolio name | CP7: ='Page Two - IM Info contd'!#REF! -> #REF!
B8: 2 | C8: Proposed Asset Class | D8: Diversified | L8: 2 | M8: Proposed Asset Class | N8: Diversified | V8: 2 | W8: Proposed Asset Class | AF8: 2 | AG8: Proposed Asset Class | AP8: 2 | AQ8: Proposed Asset Class | AZ8: 2 | BA8: Proposed Asset Class | BJ8: 2 | BK8: Proposed Asset Class | BT8: 2 | BU8: Proposed Asset Class | CD8: 2 | CE8: Proposed Asset Class | CN8: 2 | CO8: Proposed Asset Class
B9: 3 | C9: Portfolio type | D9: Diversified | L9: 3 | M9: Portfolio type | N9: Diversified | V9: 3 | W9: Portfolio type | AF9: 3 | AG9: Portfolio type | AP9: 3 | AQ9: Portfolio type | AZ9: 3 | BA9: Portfolio type | BJ9: 3 | BK9: Portfolio type | BT9: 3 | BU9: Portfolio type | CD9: 3 | CE9: Portfolio type | CN9: 3 | CO9: Portfolio type
B10: 4 | C10: Investment style | D10: Active & Index | L10: 4 | M10: Investment style | N10: Active & Index | V10: 4 | W10: Investment style | AF10: 4 | AG10: Investment style | AP10: 4 | AQ10: Investment style | AZ10: 4 | BA10: Investment style | BJ10: 4 | BK10: Investment style | BT10: 4 | BU10: Investment style | CD10: 4 | CE10: Investment style | CN10: 4 | CO10: Investment style
B11: 5 | C11: Investment universe | D11: Managed funds and ETFs | L11: 5 | M11: Investment universe | N11: Managed funds and ETFs | V11: 5 | W11: Investment universe | AF11: 5 | AG11: Investment universe | AP11: 5 | AQ11: Investment universe | AZ11: 5 | BA11: Investment universe | BJ11: 5 | BK11: Investment universe | BT11: 5 | BU11: Investment universe | CD11: 5 | CE11: Investment universe | CN11: 5 | CO11: Investment universe
B12: 6 | C12: Standard Risk Measure (SRM) as per FSC guidance paper | D12: 6 | L12: 6 | M12: Standard Risk Measure (SRM) as per FSC guidance paper | N12: 3 | V12: 6 | W12: Standard Risk Measure (SRM) as per FSC guidance paper | AF12: 6 | AG12: Standard Risk Measure (SRM) as per FSC guidance paper | AP12: 6 | AQ12: Standard Risk Measure (SRM) as per FSC guidance paper | AZ12: 6 | BA12: Standard Risk Measure (SRM) as per FSC guidance paper | BJ12: 6 | BK12: Standard Risk Measure (SRM) as per FSC guidance paper | BT12: 6 | BU12: Standard Risk Measure (SRM) as per FSC guidance paper | CD12: 6 | CE12: Standard Risk Measure (SRM) as per FSC guidance paper | CN12: 6 | CO12: Standard Risk Measure (SRM) as per FSC guidance paper
B13: 7 | C13: Describe the investment objective of the portfolio starting with "Aims to deliver…" | D13: Aims to achieve a return in excess of CPI + 3.75% p.a. and outperform the Benchmark over a rolling 10 year period, net of indirect fees. | L13: 7 | M13: Describe the investment objective of the portfolio starting with "Aims to deliver…" | N13: Aims to achieve a return in excess of CPI + 0.5% p.a. and outperform the Benchmark over a rolling 2 year period, net of indirect fees. | V13: 7 | W13: Describe the investment objective of the portfolio starting with "Aims to deliver…" | AF13: 7 | AG13: Describe the investment objective of the portfolio starting with "Aims to deliver…" | AP13: 7 | AQ13: Describe the investment objective of the portfolio starting with "Aims to deliver…" | AZ13: 7 | BA13: Describe the investment objective of the portfolio starting with "Aims to deliver…" | BJ13: 7 | BK13: Describe the investment objective of the portfolio starting with "Aims to deliver…" | BT13: 7 | BU13: Describe the investment objective of the portfolio starting with "Aims to deliver…" | CD13: 7 | CE13: Describe the investment objective of the portfolio starting with "Aims to deliver…" | CN13: 7 | CO13: Describe the investment objective of the portfolio starting with "Aims to deliver…"
B14: 8 | C14: Managed portfolio benchmark (include one for each of the below if applicable; note composite benchmarks are not accepted) - Declared benchmark for Disclosure - Portfolio performance | D14: Morningstar AUS Agg Tgt Alloc NR AUD | L14: 8 | M14: Managed portfolio benchmark (include one for each of the below if applicable; note composite benchmarks are not accepted) - Declared benchmark for Disclosure - Portfolio performance | N14: Morningstar AUS Con Tgt Alloc NR AUD | V14: 8 | W14: Managed portfolio benchmark (include one for each of the below if applicable; note composite benchmarks are not accepted) - Declared benchmark for Disclosure - Portfolio performance | AF14: 8 | AG14: Managed portfolio benchmark (include one for each of the below if applicable; note composite benchmarks are not accepted) - Declared benchmark for Disclosure - Portfolio performance | AP14: 8 | AQ14: Managed portfolio benchmark (include one for each of the below if applicable; note composite benchmarks are not accepted) - Declared benchmark for Disclosure - Portfolio performance | AZ14: 8 | BA14: Managed portfolio benchmark (include one for each of the below if applicable; note composite benchmarks are not accepted) - Declared benchmark for Disclosure - Portfolio performance | BJ14: 8 | BK14: Managed portfolio benchmark (include one for each of the below if applicable; note composite benchmarks are not accepted) - Declared benchmark for Disclosure - Portfolio performance | BT14: 8 | BU14: Managed portfolio benchmark (include one for each of the below if applicable; note composite benchmarks are not accepted) - Declared benchmark for Disclosure - Portfolio performance | CD14: 8 | CE14: Managed portfolio benchmark (include one for each of the below if applicable; note composite benchmarks are not accepted) - Declared benchmark for Disclosure - Portfolio performance | CN14: 8 | CO14: Managed portfolio benchmark (include one for each of the below if applicable; note composite benchmarks are not accepted) - Declared benchmark for Disclosure - Portfolio performance
B15: =B14+1 -> 9 | C15: Income Target (only applicable for Income/Retirement strategies) | D15: N/A | L15: =L14+1 -> 9 | M15: Income Target (only applicable for Income/Retirement strategies) | N15: N/A | V15: =V14+1 -> 9 | W15: Income Target (only applicable for Income/Retirement strategies) | AF15: =AF14+1 -> 9 | AG15: Income Target (only applicable for Income/Retirement strategies) | AP15: =AP14+1 -> 9 | AQ15: Income Target (only applicable for Income/Retirement strategies) | AZ15: =AZ14+1 -> 9 | BA15: Income Target (only applicable for Income/Retirement strategies) | BJ15: =BJ14+1 -> 9 | BK15: Income Target (only applicable for Income/Retirement strategies) | BT15: =BT14+1 -> 9 | BU15: Income Target (only applicable for Income/Retirement strategies) | CD15: =CD14+1 -> 9 | CE15: Income Target (only applicable for Income/Retirement strategies) | CN15: =CN14+1 -> 9 | CO15: Income Target (only applicable for Income/Retirement strategies)
B16: =B15+1 -> 10 | C16: Target investors suitable for the portfolio "Designed for investors who seek a…" | D16: Designed for investors with a minimum 10 year timeframe, who are comfortable with high investment risk, and/or require high returns to meet their long term objectives. | L16: =L15+1 -> 10 | M16: Target investors suitable for the portfolio "Designed for investors who seek a…" | N16: Designed for investors with a minimum 2 year timeframe, who have a low tolerance to investment risk, and/or require low returns to meet their objectives | V16: =V15+1 -> 10 | W16: Target investors suitable for the portfolio "Designed for investors who seek a…" | AF16: =AF15+1 -> 10 | AG16: Target investors suitable for the portfolio "Designed for investors who seek a…" | AP16: =AP15+1 -> 10 | AQ16: Target investors suitable for the portfolio "Designed for investors who seek a…" | AZ16: =AZ15+1 -> 10 | BA16: Target investors suitable for the portfolio "Designed for investors who seek a…" | BJ16: =BJ15+1 -> 10 | BK16: Target investors suitable for the portfolio "Designed for investors who seek a…" | BT16: =BT15+1 -> 10 | BU16: Target investors suitable for the portfolio "Designed for investors who seek a…" | CD16: =CD15+1 -> 10 | CE16: Target investors suitable for the portfolio "Designed for investors who seek a…" | CN16: =CN15+1 -> 10 | CO16: Target investors suitable for the portfolio "Designed for investors who seek a…"
B17: =B16+1 -> 11 | C17: Minimum investment horizon | D17: 10 years plus | L17: =L16+1 -> 11 | M17: Minimum investment horizon | N17: 2 years plus | V17: =V16+1 -> 11 | W17: Minimum investment horizon | AF17: =AF16+1 -> 11 | AG17: Minimum investment horizon | AP17: =AP16+1 -> 11 | AQ17: Minimum investment horizon | AZ17: =AZ16+1 -> 11 | BA17: Minimum investment horizon | BJ17: =BJ16+1 -> 11 | BK17: Minimum investment horizon | BT17: =BT16+1 -> 11 | BU17: Minimum investment horizon | CD17: =CD16+1 -> 11 | CE17: Minimum investment horizon | CN17: =CN16+1 -> 11 | CO17: Minimum investment horizon
B18: =B17+1 -> 12 | C18: Probability of achieving portfolio objectives | D18: 0.6058 | L18: =L17+1 -> 12 | M18: Probability of achieving portfolio objectives | N18: 0.797 | V18: =V17+1 -> 12 | W18: Probability of achieving portfolio objectives | AF18: =AF17+1 -> 12 | AG18: Probability of achieving portfolio objectives | AP18: =AP17+1 -> 12 | AQ18: Probability of achieving portfolio objectives | AZ18: =AZ17+1 -> 12 | BA18: Probability of achieving portfolio objectives | BJ18: =BJ17+1 -> 12 | BK18: Probability of achieving portfolio objectives | BT18: =BT17+1 -> 12 | BU18: Probability of achieving portfolio objectives | CD18: =CD17+1 -> 12 | CE18: Probability of achieving portfolio objectives | CN18: =CN17+1 -> 12 | CO18: Probability of achieving portfolio objectives
B19: =B18+1 -> 13 | C19: Describe the investment strategy and approach for this portfolio - Include ESG information if applicable | D19: The portfolio is actively managed within allowable ranges and contains exposure to approximately 2% of income assets (cash and fixed interest) and 98% of growth assets (shares, property, infrastructure and alternatives), depending on market conditions. Over the medium term the portfolio manager may adjust the portfolio, within allowable ranges, in response to evolving market conditions, economic indicators and valuation signals. The aim is to enhance returns or manage risk by taking into account cyclical trends rather than relying on static long-term assumptions. | L19: =L18+1 -> 13 | M19: Describe the investment strategy and approach for this portfolio - Include ESG information if applicable | N19: The portfolio is actively managed within allowable ranges and contains exposure to approximately 100% of income assets (cash and fixed interest) and 0% of growth assets (shares, property, infrastructure and alternatives), depending on market conditions. Over the medium term the portfolio manager may adjust the portfolio, within allowable ranges, in response to evolving market conditions, economic indicators and valuation signals. The aim is to enhance returns or manage risk by taking into account cyclical trends rather than relying on static long-term assumptions. | V19: =V18+1 -> 13 | W19: Describe the investment strategy and approach for this portfolio - Include ESG information if applicable | AF19: =AF18+1 -> 13 | AG19: Describe the investment strategy and approach for this portfolio - Include ESG information if applicable | AP19: =AP18+1 -> 13 | AQ19: Describe the investment strategy and approach for this portfolio - Include ESG information if applicable | AZ19: =AZ18+1 -> 13 | BA19: Describe the investment strategy and approach for this portfolio - Include ESG information if applicable | BJ19: =BJ18+1 -> 13 | BK19: Describe the investment strategy and approach for this portfolio - Include ESG information if applicable | BT19: =BT18+1 -> 13 | BU19: Describe the investment strategy and approach for this portfolio - Include ESG information if applicable | CD19: =CD18+1 -> 13 | CE19: Describe the investment strategy and approach for this portfolio - Include ESG information if applicable | CN19: =CN18+1 -> 13 | CO19: Describe the investment strategy and approach for this portfolio - Include ESG information if applicable
B21: Part 2: Equivalent strategies - Managed fund/SMA/Model (if applicable) | D21: Response | G21: Progress | H21: =COUNTA(D22:H29)/ROWS(D22:H29) -> 1 | L21: Part 2: Equivalent strategies - Managed fund/SMA/Model (if applicable) | N21: Response | Q21: Progress | R21: =COUNTA(N22:R29)/ROWS(N22:R29) -> 1 | V21: Part 2: Equivalent strategies - Managed fund/SMA/Model (if applicable) | X21: Response | AA21: Progress | AB21: =COUNTA(X22:AB29)/ROWS(X22:AB29) -> 0 | AF21: Part 2: Equivalent strategies - Managed fund/SMA/Model (if applicable) | AH21: Response | AK21: Progress | AL21: =COUNTA(AH22:AL29)/ROWS(AH22:AL29) -> 0 | AP21: Part 2: Equivalent strategies - Managed fund/SMA/Model (if applicable) | AR21: Response | AU21: Progress | AV21: =COUNTA(AR22:AV29)/ROWS(AR22:AV29) -> 0 | AZ21: Part 2: Equivalent strategies - Managed fund/SMA/Model (if applicable) | BB21: Response | BE21: Progress | BF21: =COUNTA(BB22:BF29)/ROWS(BB22:BF29) -> 0 | BJ21: Part 2: Equivalent strategies - Managed fund/SMA/Model (if applicable) | BL21: Response | BO21: Progress | BP21: =COUNTA(BL22:BP29)/ROWS(BL22:BP29) -> 0 | BT21: Part 2: Equivalent strategies - Managed fund/SMA/Model (if applicable) | BV21: Response | BY21: Progress | BZ21: =COUNTA(BV22:BZ29)/ROWS(BV22:BZ29) -> 0 | CD21: Part 2: Equivalent strategies - Managed fund/SMA/Model (if applicable) | CF21: Response | CI21: Progress | CJ21: =COUNTA(CF22:CJ29)/ROWS(CF22:CJ29) -> 0 | CN21: Part 2: Equivalent strategies - Managed fund/SMA/Model (if applicable) | CP21: Response | CS21: Progress | CT21: =COUNTA(CP22:CT29)/ROWS(CP22:CT29) -> 0
B22: 1 | C22: Is the portfolio based on an equivalent existing strategy that has a track record? | D22: No | L22: 1 | M22: Is the portfolio based on an equivalent existing strategy that has a track record? | N22: No | V22: 1 | W22: Is the portfolio based on an equivalent existing strategy that has a track record? | AF22: 1 | AG22: Is the portfolio based on an equivalent existing strategy that has a track record? | AP22: 1 | AQ22: Is the portfolio based on an equivalent existing strategy that has a track record? | AZ22: 1 | BA22: Is the portfolio based on an equivalent existing strategy that has a track record? | BJ22: 1 | BK22: Is the portfolio based on an equivalent existing strategy that has a track record? | BT22: 1 | BU22: Is the portfolio based on an equivalent existing strategy that has a track record? | CD22: 1 | CE22: Is the portfolio based on an equivalent existing strategy that has a track record? | CN22: 1 | CO22: Is the portfolio based on an equivalent existing strategy that has a track record?
B23: 2 | C23: If yes, please provide the name of the equivalent strategy | D23: N/A | L23: 2 | M23: If yes, please provide the name of the equivalent strategy | N23: N/A | V23: 2 | W23: If yes, please provide the name of the equivalent strategy | AF23: 2 | AG23: If yes, please provide the name of the equivalent strategy | AP23: 2 | AQ23: If yes, please provide the name of the equivalent strategy | AZ23: 2 | BA23: If yes, please provide the name of the equivalent strategy | BJ23: 2 | BK23: If yes, please provide the name of the equivalent strategy | BT23: 2 | BU23: If yes, please provide the name of the equivalent strategy | CD23: 2 | CE23: If yes, please provide the name of the equivalent strategy | CN23: 2 | CO23: If yes, please provide the name of the equivalent strategy
B24: 3 | C24: Provide the equivalent strategy APIR code (if applicable) | D24: N/A | L24: 3 | M24: Provide the equivalent strategy APIR code (if applicable) | N24: N/A | V24: 3 | W24: Provide the equivalent strategy APIR code (if applicable) | AF24: 3 | AG24: Provide the equivalent strategy APIR code (if applicable) | AP24: 3 | AQ24: Provide the equivalent strategy APIR code (if applicable) | AZ24: 3 | BA24: Provide the equivalent strategy APIR code (if applicable) | BJ24: 3 | BK24: Provide the equivalent strategy APIR code (if applicable) | BT24: 3 | BU24: Provide the equivalent strategy APIR code (if applicable) | CD24: 3 | CE24: Provide the equivalent strategy APIR code (if applicable) | CN24: 3 | CO24: Provide the equivalent strategy APIR code (if applicable)
B25: 4 | C25: Explain any actual or likely differences between the portfolio and the equivalent strategy? | D25: N/A | L25: 4 | M25: Explain any actual or likely differences between the portfolio and the equivalent strategy? | N25: N/A | V25: 4 | W25: Explain any actual or likely differences between the portfolio and the equivalent strategy? | AF25: 4 | AG25: Explain any actual or likely differences between the portfolio and the equivalent strategy? | AP25: 4 | AQ25: Explain any actual or likely differences between the portfolio and the equivalent strategy? | AZ25: 4 | BA25: Explain any actual or likely differences between the portfolio and the equivalent strategy? | BJ25: 4 | BK25: Explain any actual or likely differences between the portfolio and the equivalent strategy? | BT25: 4 | BU25: Explain any actual or likely differences between the portfolio and the equivalent strategy? | CD25: 4 | CE25: Explain any actual or likely differences between the portfolio and the equivalent strategy? | CN25: 4 | CO25: Explain any actual or likely differences between the portfolio and the equivalent strategy?
B26: 5 | C26: How does you approach any potential conflicts arising as a result of running a similar strategy across different structures? E.g. timing of trades and the potential to 'front run' | D26: N/A | L26: 5 | M26: How does you approach any potential conflicts arising as a result of running a similar strategy across different structures? E.g. timing of trades and the potential to 'front run' | N26: N/A | V26: 5 | W26: How does you approach any potential conflicts arising as a result of running a similar strategy across different structures? E.g. timing of trades and the potential to 'front run' | AF26: 5 | AG26: How does you approach any potential conflicts arising as a result of running a similar strategy across different structures? E.g. timing of trades and the potential to 'front run' | AP26: 5 | AQ26: How does you approach any potential conflicts arising as a result of running a similar strategy across different structures? E.g. timing of trades and the potential to 'front run' | AZ26: 5 | BA26: How does you approach any potential conflicts arising as a result of running a similar strategy across different structures? E.g. timing of trades and the potential to 'front run' | BJ26: 5 | BK26: How does you approach any potential conflicts arising as a result of running a similar strategy across different structures? E.g. timing of trades and the potential to 'front run' | BT26: 5 | BU26: How does you approach any potential conflicts arising as a result of running a similar strategy across different structures? E.g. timing of trades and the potential to 'front run' | CD26: 5 | CE26: How does you approach any potential conflicts arising as a result of running a similar strategy across different structures? E.g. timing of trades and the potential to 'front run' | CN26: 5 | CO26: How does you approach any potential conflicts arising as a result of running a similar strategy across different structures? E.g. timing of trades and the potential to 'front run'
B27: 6 | C27: Provide the monthly Managed Portfolio performance (net of fees) | D27: N/A | L27: 6 | M27: Provide the monthly Managed Portfolio performance (net of fees) | N27: N/A | V27: 6 | W27: Provide the monthly Managed Portfolio performance (net of fees) | AF27: 6 | AG27: Provide the monthly Managed Portfolio performance (net of fees) | AP27: 6 | AQ27: Provide the monthly Managed Portfolio performance (net of fees) | AZ27: 6 | BA27: Provide the monthly Managed Portfolio performance (net of fees) | BJ27: 6 | BK27: Provide the monthly Managed Portfolio performance (net of fees) | BT27: 6 | BU27: Provide the monthly Managed Portfolio performance (net of fees) | CD27: 6 | CE27: Provide the monthly Managed Portfolio performance (net of fees) | CN27: 6 | CO27: Provide the monthly Managed Portfolio performance (net of fees)
B28: 7 | C28: Provide the monthly Implemented Portfolio performance of the portfolio on a pre existing platform | D28: N/A | L28: 7 | M28: Provide the monthly Implemented Portfolio performance of the portfolio on a pre existing platform | N28: N/A | V28: 7 | W28: Provide the monthly Implemented Portfolio performance of the portfolio on a pre existing platform | AF28: 7 | AG28: Provide the monthly Implemented Portfolio performance of the portfolio on a pre existing platform | AP28: 7 | AQ28: Provide the monthly Implemented Portfolio performance of the portfolio on a pre existing platform | AZ28: 7 | BA28: Provide the monthly Implemented Portfolio performance of the portfolio on a pre existing platform | BJ28: 7 | BK28: Provide the monthly Implemented Portfolio performance of the portfolio on a pre existing platform | BT28: 7 | BU28: Provide the monthly Implemented Portfolio performance of the portfolio on a pre existing platform | CD28: 7 | CE28: Provide the monthly Implemented Portfolio performance of the portfolio on a pre existing platform | CN28: 7 | CO28: Provide the monthly Implemented Portfolio performance of the portfolio on a pre existing platform
B29: 8 | C29: What is the expected stock holdings (MIS vs managed portfolio) overlap with any of your funds? | D29: N/A | L29: 8 | M29: What is the expected stock holdings (MIS vs managed portfolio) overlap with any of your funds? | N29: N/A | V29: 8 | W29: What is the expected stock holdings (MIS vs managed portfolio) overlap with any of your funds? | AF29: 8 | AG29: What is the expected stock holdings (MIS vs managed portfolio) overlap with any of your funds? | AP29: 8 | AQ29: What is the expected stock holdings (MIS vs managed portfolio) overlap with any of your funds? | AZ29: 8 | BA29: What is the expected stock holdings (MIS vs managed portfolio) overlap with any of your funds? | BJ29: 8 | BK29: What is the expected stock holdings (MIS vs managed portfolio) overlap with any of your funds? | BT29: 8 | BU29: What is the expected stock holdings (MIS vs managed portfolio) overlap with any of your funds? | CD29: 8 | CE29: What is the expected stock holdings (MIS vs managed portfolio) overlap with any of your funds? | CN29: 8 | CO29: What is the expected stock holdings (MIS vs managed portfolio) overlap with any of your funds?
B31: Part 3: Portfolio management information | D31: Response | G31: Progress | H31: =COUNTA(D32:H40)/ROWS(D32:H40) -> 1 | L31: Part 3: Portfolio management information | N31: Response | Q31: Progress | R31: =COUNTA(N32:R40)/ROWS(N32:R40) -> 1 | V31: Part 3: Portfolio management information | X31: Response | AA31: Progress | AB31: =COUNTA(X32:AB40)/ROWS(X32:AB40) -> 0 | AF31: Part 3: Portfolio management information | AH31: Response | AK31: Progress | AL31: =COUNTA(AH32:AL40)/ROWS(AH32:AL40) -> 0 | AP31: Part 3: Portfolio management information | AR31: Response | AU31: Progress | AV31: =COUNTA(AR32:AV40)/ROWS(AR32:AV40) -> 0 | AZ31: Part 3: Portfolio management information | BB31: Response | BE31: Progress | BF31: =COUNTA(BB32:BF40)/ROWS(BB32:BF40) -> 0 | BJ31: Part 3: Portfolio management information | BL31: Response | BO31: Progress | BP31: =COUNTA(BL32:BP40)/ROWS(BL32:BP40) -> 0 | BT31: Part 3: Portfolio management information | BV31: Response | BY31: Progress | BZ31: =COUNTA(BV32:BZ40)/ROWS(BV32:BZ40) -> 0 | CD31: Part 3: Portfolio management information | CF31: Response | CI31: Progress | CJ31: =COUNTA(CF32:CJ40)/ROWS(CF32:CJ40) -> 0 | CN31: Part 3: Portfolio management information | CP31: Response | CS31: Progress | CT31: =COUNTA(CP32:CT40)/ROWS(CP32:CT40) -> 0
B32: 1 | C32: What is the minimum number of investment options held in the portfolio? (please clarify the asset category of investment options) | D32: 10 | L32: 1 | M32: What is the minimum number of investment options held in the portfolio? (please clarify the asset category of investment options) | N32: 10 | V32: 1 | W32: What is the minimum number of investment options held in the portfolio? (please clarify the asset category of investment options) | AF32: 1 | AG32: What is the minimum number of investment options held in the portfolio? (please clarify the asset category of investment options) | AP32: 1 | AQ32: What is the minimum number of investment options held in the portfolio? (please clarify the asset category of investment options) | AZ32: 1 | BA32: What is the minimum number of investment options held in the portfolio? (please clarify the asset category of investment options) | BJ32: 1 | BK32: What is the minimum number of investment options held in the portfolio? (please clarify the asset category of investment options) | BT32: 1 | BU32: What is the minimum number of investment options held in the portfolio? (please clarify the asset category of investment options) | CD32: 1 | CE32: What is the minimum number of investment options held in the portfolio? (please clarify the asset category of investment options) | CN32: 1 | CO32: What is the minimum number of investment options held in the portfolio? (please clarify the asset category of investment options)
B33: 2 | C33: What is the maximum number of investment options held in the portfolio? (please clarify the asset category of investment options) | D33: 30 | L33: 2 | M33: What is the maximum number of investment options held in the portfolio? (please clarify the asset category of investment options) | N33: 30 | V33: 2 | W33: What is the maximum number of investment options held in the portfolio? (please clarify the asset category of investment options) | AF33: 2 | AG33: What is the maximum number of investment options held in the portfolio? (please clarify the asset category of investment options) | AP33: 2 | AQ33: What is the maximum number of investment options held in the portfolio? (please clarify the asset category of investment options) | AZ33: 2 | BA33: What is the maximum number of investment options held in the portfolio? (please clarify the asset category of investment options) | BJ33: 2 | BK33: What is the maximum number of investment options held in the portfolio? (please clarify the asset category of investment options) | BT33: 2 | BU33: What is the maximum number of investment options held in the portfolio? (please clarify the asset category of investment options) | CD33: 2 | CE33: What is the maximum number of investment options held in the portfolio? (please clarify the asset category of investment options) | CN33: 2 | CO33: What is the maximum number of investment options held in the portfolio? (please clarify the asset category of investment options)
B34: 3 | C34: What is the minimum absolute single asset position? (%) | D34: 0.01 | L34: 3 | M34: What is the minimum absolute single asset position? (%) | N34: 0.01 | V34: 3 | W34: What is the minimum absolute single asset position? (%) | AF34: 3 | AG34: What is the minimum absolute single asset position? (%) | AP34: 3 | AQ34: What is the minimum absolute single asset position? (%) | AZ34: 3 | BA34: What is the minimum absolute single asset position? (%) | BJ34: 3 | BK34: What is the minimum absolute single asset position? (%) | BT34: 3 | BU34: What is the minimum absolute single asset position? (%) | CD34: 3 | CE34: What is the minimum absolute single asset position? (%) | CN34: 3 | CO34: What is the minimum absolute single asset position? (%)
B35: 4 | C35: What is the maximum absolute single asset position? (%) | D35: 0.3 | L35: 4 | M35: What is the maximum absolute single asset position? (%) | N35: 0.3 | V35: 4 | W35: What is the maximum absolute single asset position? (%) | AF35: 4 | AG35: What is the maximum absolute single asset position? (%) | AP35: 4 | AQ35: What is the maximum absolute single asset position? (%) | AZ35: 4 | BA35: What is the maximum absolute single asset position? (%) | BJ35: 4 | BK35: What is the maximum absolute single asset position? (%) | BT35: 4 | BU35: What is the maximum absolute single asset position? (%) | CD35: 4 | CE35: What is the maximum absolute single asset position? (%) | CN35: 4 | CO35: What is the maximum absolute single asset position? (%)
B36: 5 | C36: What is the minimum single asset position for any new asset? (%) | D36: 0.01 | L36: 5 | M36: What is the minimum single asset position for any new asset? (%) | N36: 0.01 | V36: 5 | W36: What is the minimum single asset position for any new asset? (%) | AF36: 5 | AG36: What is the minimum single asset position for any new asset? (%) | AP36: 5 | AQ36: What is the minimum single asset position for any new asset? (%) | AZ36: 5 | BA36: What is the minimum single asset position for any new asset? (%) | BJ36: 5 | BK36: What is the minimum single asset position for any new asset? (%) | BT36: 5 | BU36: What is the minimum single asset position for any new asset? (%) | CD36: 5 | CE36: What is the minimum single asset position for any new asset? (%) | CN36: 5 | CO36: What is the minimum single asset position for any new asset? (%)
B37: 6 | C37: Target volatility (or other risk target TE, VaR, CVaR) | D37: N/A | L37: 6 | M37: Target volatility (or other risk target TE, VaR, CVaR) | N37: N/A | V37: 6 | W37: Target volatility (or other risk target TE, VaR, CVaR) | AF37: 6 | AG37: Target volatility (or other risk target TE, VaR, CVaR) | AP37: 6 | AQ37: Target volatility (or other risk target TE, VaR, CVaR) | AZ37: 6 | BA37: Target volatility (or other risk target TE, VaR, CVaR) | BJ37: 6 | BK37: Target volatility (or other risk target TE, VaR, CVaR) | BT37: 6 | BU37: Target volatility (or other risk target TE, VaR, CVaR) | CD37: 6 | CE37: Target volatility (or other risk target TE, VaR, CVaR) | CN37: 6 | CO37: Target volatility (or other risk target TE, VaR, CVaR)
B38: 7 | C38: Will income be reinvested or paid to the platform cash account by default? | D38: Reinvested | L38: 7 | M38: Will income be reinvested or paid to the platform cash account by default? | N38: Reinvested | V38: 7 | W38: Will income be reinvested or paid to the platform cash account by default? | AF38: 7 | AG38: Will income be reinvested or paid to the platform cash account by default? | AP38: 7 | AQ38: Will income be reinvested or paid to the platform cash account by default? | AZ38: 7 | BA38: Will income be reinvested or paid to the platform cash account by default? | BJ38: 7 | BK38: Will income be reinvested or paid to the platform cash account by default? | BT38: 7 | BU38: Will income be reinvested or paid to the platform cash account by default? | CD38: 7 | CE38: Will income be reinvested or paid to the platform cash account by default? | CN38: 7 | CO38: Will income be reinvested or paid to the platform cash account by default?
B39: 8 | C39: Minimum Cash buffer? (1% minimum required) | D39: 0.01 | L39: 8 | M39: Minimum Cash buffer? (1% minimum required) | N39: 0.01 | V39: 8 | W39: Minimum Cash buffer? (1% minimum required) | AF39: 8 | AG39: Minimum Cash buffer? (1% minimum required) | AP39: 8 | AQ39: Minimum Cash buffer? (1% minimum required) | AZ39: 8 | BA39: Minimum Cash buffer? (1% minimum required) | BJ39: 8 | BK39: Minimum Cash buffer? (1% minimum required) | BT39: 8 | BU39: Minimum Cash buffer? (1% minimum required) | CD39: 8 | CE39: Minimum Cash buffer? (1% minimum required) | CN39: 8 | CO39: Minimum Cash buffer? (1% minimum required)
B40: 9 | C40: Is the trading preference active or rebalance? | D40: Active | L40: 9 | M40: Is the trading preference active or rebalance? | N40: Active | V40: 9 | W40: Is the trading preference active or rebalance? | AF40: 9 | AG40: Is the trading preference active or rebalance? | AP40: 9 | AQ40: Is the trading preference active or rebalance? | AZ40: 9 | BA40: Is the trading preference active or rebalance? | BJ40: 9 | BK40: Is the trading preference active or rebalance? | BT40: 9 | BU40: Is the trading preference active or rebalance? | CD40: 9 | CE40: Is the trading preference active or rebalance? | CN40: 9 | CO40: Is the trading preference active or rebalance?
B41: Portfolio management - Listed Assets ONLY | D41: Response | L41: Portfolio management - Listed Assets ONLY | N41: Response | V41: Portfolio management - Listed Assets ONLY | X41: Response | AF41: Portfolio management - Listed Assets ONLY | AH41: Response | AP41: Portfolio management - Listed Assets ONLY | AR41: Response | AZ41: Portfolio management - Listed Assets ONLY | BB41: Response | BJ41: Portfolio management - Listed Assets ONLY | BL41: Response | BT41: Portfolio management - Listed Assets ONLY | BV41: Response | CD41: Portfolio management - Listed Assets ONLY | CF41: Response | CN41: Portfolio management - Listed Assets ONLY | CP41: Response
B42: 1 | C42: Expected Turnover (p.a.) | L42: 1 | M42: Expected Turnover (p.a.) | V42: 1 | W42: Expected Turnover (p.a.) | AF42: 1 | AG42: Expected Turnover (p.a.) | AP42: 1 | AQ42: Expected Turnover (p.a.) | AZ42: 1 | BA42: Expected Turnover (p.a.) | BJ42: 1 | BK42: Expected Turnover (p.a.) | BT42: 1 | BU42: Expected Turnover (p.a.) | CD42: 1 | CE42: Expected Turnover (p.a.) | CN42: 1 | CO42: Expected Turnover (p.a.)
B43: 2 | C43: Active Stock Limits (+/- benchmark weight) | L43: 2 | M43: Active Stock Limits (+/- benchmark weight) | V43: 2 | W43: Active Stock Limits (+/- benchmark weight) | AF43: 2 | AG43: Active Stock Limits (+/- benchmark weight) | AP43: 2 | AQ43: Active Stock Limits (+/- benchmark weight) | AZ43: 2 | BA43: Active Stock Limits (+/- benchmark weight) | BJ43: 2 | BK43: Active Stock Limits (+/- benchmark weight) | BT43: 2 | BU43: Active Stock Limits (+/- benchmark weight) | CD43: 2 | CE43: Active Stock Limits (+/- benchmark weight) | CN43: 2 | CO43: Active Stock Limits (+/- benchmark weight)
B44: 3 | C44: Active GICS Sector Limits (+/- benchmark weight) | L44: 3 | M44: Active GICS Sector Limits (+/- benchmark weight) | V44: 3 | W44: Active GICS Sector Limits (+/- benchmark weight) | AF44: 3 | AG44: Active GICS Sector Limits (+/- benchmark weight) | AP44: 3 | AQ44: Active GICS Sector Limits (+/- benchmark weight) | AZ44: 3 | BA44: Active GICS Sector Limits (+/- benchmark weight) | BJ44: 3 | BK44: Active GICS Sector Limits (+/- benchmark weight) | BT44: 3 | BU44: Active GICS Sector Limits (+/- benchmark weight) | CD44: 3 | CE44: Active GICS Sector Limits (+/- benchmark weight) | CN44: 3 | CO44: Active GICS Sector Limits (+/- benchmark weight)
B45: 4 | C45: Ex-ante tracking error target | L45: 4 | M45: Ex-ante tracking error target | V45: 4 | W45: Ex-ante tracking error target | AF45: 4 | AG45: Ex-ante tracking error target | AP45: 4 | AQ45: Ex-ante tracking error target | AZ45: 4 | BA45: Ex-ante tracking error target | BJ45: 4 | BK45: Ex-ante tracking error target | BT45: 4 | BU45: Ex-ante tracking error target | CD45: 4 | CE45: Ex-ante tracking error target | CN45: 4 | CO45: Ex-ante tracking error target
B46: 5 | C46: Target benchmark outperformance | L46: 5 | M46: Target benchmark outperformance | V46: 5 | W46: Target benchmark outperformance | AF46: 5 | AG46: Target benchmark outperformance | AP46: 5 | AQ46: Target benchmark outperformance | AZ46: 5 | BA46: Target benchmark outperformance | BJ46: 5 | BK46: Target benchmark outperformance | BT46: 5 | BU46: Target benchmark outperformance | CD46: 5 | CE46: Target benchmark outperformance | CN46: 5 | CO46: Target benchmark outperformance
B48: Part 4: Strategic Asset Allocation | G48: Correctly Completed | H48: =IF(AND(E60=100%,G60=100%),"Yes","No") -> No | L48: Part 4: Strategic Asset Allocation | Q48: Correctly Completed | R48: =IF(AND(O60=100%,Q60=100%),"Yes","No") -> Yes | V48: Part 4: Strategic Asset Allocation | AA48: Correctly Completed | AB48: =IF(AND(Y60=100%,AA60=100%),"Yes","No") -> No | AF48: Part 4: Strategic Asset Allocation | AK48: Correctly Completed | AL48: =IF(AND(AI60=100%,AK60=100%),"Yes","No") -> No | AP48: Part 4: Strategic Asset Allocation | AU48: Correctly Completed | AV48: =IF(AND(AS60=100%,AU60=100%),"Yes","No") -> No | AZ48: Part 4: Strategic Asset Allocation | BE48: Correctly Completed | BF48: =IF(AND(BC60=100%,BE60=100%),"Yes","No") -> No | BJ48: Part 4: Strategic Asset Allocation | BO48: Correctly Completed | BP48: =IF(AND(BM60=100%,BO60=100%),"Yes","No") -> No | BT48: Part 4: Strategic Asset Allocation | BY48: Correctly Completed | BZ48: =IF(AND(BW60=100%,BY60=100%),"Yes","No") -> No | CD48: Part 4: Strategic Asset Allocation | CI48: Correctly Completed | CJ48: =IF(AND(CG60=100%,CI60=100%),"Yes","No") -> No | CN48: Part 4: Strategic Asset Allocation | CS48: Correctly Completed | CT48: =IF(AND(CQ60=100%,CS60=100%),"Yes","No") -> No
C49: Asset classes available on North | D49: Minimum Range | E49: SAA | F49: Maximum Range | G49: Current Weight in Portfolio | H49: Active Weight | M49: Asset classes available on North | N49: Minimum Range | O49: SAA | P49: Maximum Range | Q49: Current Weight in Portfolio | R49: Active Weight | W49: Asset classes available on North | X49: Minimum Range | Y49: SAA | Z49: Maximum Range | AA49: Current Weight in Portfolio | AB49: Active Weight | AG49: Asset classes available on North | AH49: Minimum Range | AI49: SAA | AJ49: Maximum Range | AK49: Current Weight in Portfolio | AL49: Active Weight | AQ49: Asset classes available on North | AR49: Minimum Range | AS49: SAA | AT49: Maximum Range | AU49: Current Weight in Portfolio | AV49: Active Weight | BA49: Asset classes available on North | BB49: Minimum Range | BC49: SAA | BD49: Maximum Range | BE49: Current Weight in Portfolio | BF49: Active Weight | BK49: Asset classes available on North | BL49: Minimum Range | BM49: SAA | BN49: Maximum Range | BO49: Current Weight in Portfolio | BP49: Active Weight | BU49: Asset classes available on North | BV49: Minimum Range | BW49: SAA | BX49: Maximum Range | BY49: Current Weight in Portfolio | BZ49: Active Weight | CE49: Asset classes available on North | CF49: Minimum Range | CG49: SAA | CH49: Maximum Range | CI49: Current Weight in Portfolio | CJ49: Active Weight | CO49: Asset classes available on North | CP49: Minimum Range | CQ49: SAA | CR49: Maximum Range | CS49: Current Weight in Portfolio | CT49: Active Weight
C50: Growth | M50: Growth | W50: Growth | AG50: Growth | AQ50: Growth | BA50: Growth | BK50: Growth | BU50: Growth | CE50: Growth | CO50: Growth
C51: Australian Equities | D51: 0 | E51: 0.36 | F51: 0.85 | G51: 0.36 | M51: Australian Equities | N51: 0 | O51: 0 | P51: 0.2 | Q51: 0 | W51: Australian Equities | AG51: Australian Equities | AQ51: Australian Equities | BA51: Australian Equities | BK51: Australian Equities | BU51: Australian Equities | CE51: Australian Equities | CO51: Australian Equities
C52: International Equities | D52: 0 | E52: 0.45 | F52: 0.85 | G52: 0.45 | M52: International Equities | N52: 0 | O52: 0 | P52: 0.2 | Q52: 0 | W52: International Equities | AG52: International Equities | AQ52: International Equities | BA52: International Equities | BK52: International Equities | BU52: International Equities | CE52: International Equities | CO52: International Equities
C53: Domestic Property and Infrastructure | D53: 0 | E53: 0.03 | F53: 0.35 | G53: 0.17 | M53: Domestic Property and Infrastructure | N53: 0 | O53: 0 | P53: 0.2 | Q53: 0 | W53: Domestic Property and Infrastructure | AG53: Domestic Property and Infrastructure | AQ53: Domestic Property and Infrastructure | BA53: Domestic Property and Infrastructure | BK53: Domestic Property and Infrastructure | BU53: Domestic Property and Infrastructure | CE53: Domestic Property and Infrastructure | CO53: Domestic Property and Infrastructure
C54: International Property and Infrastructure | E54: 0.14 | M54: International Property and Infrastructure | O54: 0 | W54: International Property and Infrastructure | AG54: International Property and Infrastructure | AQ54: International Property and Infrastructure | BA54: International Property and Infrastructure | BK54: International Property and Infrastructure | BU54: International Property and Infrastructure | CE54: International Property and Infrastructure | CO54: International Property and Infrastructure
C55: Alternatives | D55: 0 | E55: 0 | F55: 0.2 | G55: 0 | M55: Alternatives | N55: 0 | O55: 0 | P55: 0.2 | Q55: 0 | W55: Alternatives | AG55: Alternatives | AQ55: Alternatives | BA55: Alternatives | BK55: Alternatives | BU55: Alternatives | CE55: Alternatives | CO55: Alternatives
C56: Defensive | M56: Defensive | W56: Defensive | AG56: Defensive | AQ56: Defensive | BA56: Defensive | BK56: Defensive | BU56: Defensive | CE56: Defensive | CO56: Defensive
C57: Australian Fixed Interest | D57: 0 | E57: 0 | F57: 0.19 | G57: 0 | M57: Australian Fixed Interest | N57: 0 | O57: 0.59 | P57: 0.98 | Q57: 0.59 | W57: Australian Fixed Interest | AG57: Australian Fixed Interest | AQ57: Australian Fixed Interest | BA57: Australian Fixed Interest | BK57: Australian Fixed Interest | BU57: Australian Fixed Interest | CE57: Australian Fixed Interest | CO57: Australian Fixed Interest
C58: International Fixed Interest | D58: 0 | E58: 0 | F58: 0.19 | G58: 0 | M58: International Fixed Interest | N58: 0 | O58: 0.39 | P58: 0.98 | Q58: 0.39 | W58: International Fixed Interest | AG58: International Fixed Interest | AQ58: International Fixed Interest | BA58: International Fixed Interest | BK58: International Fixed Interest | BU58: International Fixed Interest | CE58: International Fixed Interest | CO58: International Fixed Interest
C59: Cash (1% minimum required) | D59: 0.01 | E59: 0.02 | F59: 0.2 | G59: 0.02 | M59: Cash (1% minimum required) | N59: 0.01 | O59: 0.02 | P59: 1 | Q59: 0.02 | W59: Cash (1% minimum required) | AG59: Cash (1% minimum required) | AQ59: Cash (1% minimum required) | BA59: Cash (1% minimum required) | BK59: Cash (1% minimum required) | BU59: Cash (1% minimum required) | CE59: Cash (1% minimum required) | CO59: Cash (1% minimum required)
C60: Total | M60: Total | O60: 1 | Q60: 1 | R60: =SUM(R51:R55,R57:R59) -> 0 | W60: Total | X60: =SUM(X51:X55,X57:X59) -> 0 | Y60: =SUM(Y51:Y55,Y57:Y59) -> 0 | Z60: =SUM(Z51:Z55,Z57:Z59) -> 0 | AA60: =SUM(AA51:AA55,AA57:AA59) -> 0 | AB60: =SUM(AB51:AB55,AB57:AB59) -> 0 | AG60: Total | AH60: =SUM(AH51:AH55,AH57:AH59) -> 0 | AI60: =SUM(AI51:AI55,AI57:AI59) -> 0 | AJ60: =SUM(AJ51:AJ55,AJ57:AJ59) -> 0 | AK60: =SUM(AK51:AK55,AK57:AK59) -> 0 | AL60: =SUM(AL51:AL55,AL57:AL59) -> 0 | AQ60: Total | AR60: =SUM(AR51:AR55,AR57:AR59) -> 0 | AS60: =SUM(AS51:AS55,AS57:AS59) -> 0 | AT60: =SUM(AT51:AT55,AT57:AT59) -> 0 | AU60: =SUM(AU51:AU55,AU57:AU59) -> 0 | AV60: =SUM(AV51:AV55,AV57:AV59) -> 0 | BA60: Total | BB60: =SUM(BB51:BB55,BB57:BB59) -> 0 | BC60: =SUM(BC51:BC55,BC57:BC59) -> 0 | BD60: =SUM(BD51:BD55,BD57:BD59) -> 0 | BE60: =SUM(BE51:BE55,BE57:BE59) -> 0 | BF60: =SUM(BF51:BF55,BF57:BF59) -> 0 | BK60: Total | BL60: =SUM(BL51:BL55,BL57:BL59) -> 0 | BM60: =SUM(BM51:BM55,BM57:BM59) -> 0 | BN60: =SUM(BN51:BN55,BN57:BN59) -> 0 | BO60: =SUM(BO51:BO55,BO57:BO59) -> 0 | BP60: =SUM(BP51:BP55,BP57:BP59) -> 0 | BU60: Total | BV60: =SUM(BV51:BV55,BV57:BV59) -> 0 | BW60: =SUM(BW51:BW55,BW57:BW59) -> 0 | BX60: =SUM(BX51:BX55,BX57:BX59) -> 0 | BY60: =SUM(BY51:BY55,BY57:BY59) -> 0 | BZ60: =SUM(BZ51:BZ55,BZ57:BZ59) -> 0 | CE60: Total | CF60: =SUM(CF51:CF55,CF57:CF59) -> 0 | CG60: =SUM(CG51:CG55,CG57:CG59) -> 0 | CH60: =SUM(CH51:CH55,CH57:CH59) -> 0 | CI60: =SUM(CI51:CI55,CI57:CI59) -> 0 | CJ60: =SUM(CJ51:CJ55,CJ57:CJ59) -> 0 | CO60: Total | CP60: =SUM(CP51:CP55,CP57:CP59) -> 0 | CQ60: =SUM(CQ51:CQ55,CQ57:CQ59) -> 0 | CR60: =SUM(CR51:CR55,CR57:CR59) -> 0 | CS60: =SUM(CS51:CS55,CS57:CS59) -> 0 | CT60: =SUM(CT51:CT55,CT57:CT59) -> 0
B62: Part 5: Fees | D62: Response | F62: Progress | G62: =COUNTA(D63:G64)/ROWS(D63:G64) -> 1 | L62: Part 5: Fees | N62: Response | P62: Progress | Q62: =COUNTA(N63:Q64)/ROWS(N63:Q64) -> 1 | V62: Part 5: Fees | X62: Response | Z62: Progress | AA62: =COUNTA(X63:AA64)/ROWS(X63:AA64) -> 0 | AF62: Part 5: Fees | AH62: Response | AJ62: Progress | AK62: =COUNTA(AH63:AK64)/ROWS(AH63:AK64) -> 0 | AP62: Part 5: Fees | AR62: Response | AT62: Progress | AU62: =COUNTA(AR63:AU64)/ROWS(AR63:AU64) -> 0 | AZ62: Part 5: Fees | BB62: Response | BD62: Progress | BE62: =COUNTA(BB63:BE64)/ROWS(BB63:BE64) -> 0 | BJ62: Part 5: Fees | BL62: Response | BN62: Progress | BO62: =COUNTA(BL63:BO64)/ROWS(BL63:BO64) -> 0 | BT62: Part 5: Fees | BV62: Response | BX62: Progress | BY62: =COUNTA(BV63:BY64)/ROWS(BV63:BY64) -> 0 | CD62: Part 5: Fees | CF62: Response | CH62: Progress | CI62: =COUNTA(CF63:CI64)/ROWS(CF63:CI64) -> 0 | CN62: Part 5: Fees | CP62: Response | CR62: Progress | CS62: =COUNTA(CP63:CS64)/ROWS(CP63:CS64) -> 0
B63: 1 | C63: Proposed fee paid by NMMT to the investment manager (exclusive of GST) | D63: 0.00075 | H63: =D63 -> 0.00075 | L63: 1 | M63: Proposed fee paid by NMMT to the investment manager (exclusive of GST) | N63: 0.00075 | R63: =N63 -> 0.00075 | V63: 1 | W63: Proposed fee paid by NMMT to the investment manager (exclusive of GST) | AB63: =X63 -> 0 | AF63: 1 | AG63: Proposed fee paid by NMMT to the investment manager (exclusive of GST) | AL63: =AH63 -> 0 | AP63: 1 | AQ63: Proposed fee paid by NMMT to the investment manager (exclusive of GST) | AV63: =AR63 -> 0 | AZ63: 1 | BA63: Proposed fee paid by NMMT to the investment manager (exclusive of GST) | BF63: =BB63 -> 0 | BJ63: 1 | BK63: Proposed fee paid by NMMT to the investment manager (exclusive of GST) | BP63: =BL63 -> 0 | BT63: 1 | BU63: Proposed fee paid by NMMT to the investment manager (exclusive of GST) | BZ63: =BV63 -> 0 | CD63: 1 | CE63: Proposed fee paid by NMMT to the investment manager (exclusive of GST) | CJ63: =CF63 -> 0 | CN63: 1 | CO63: Proposed fee paid by NMMT to the investment manager (exclusive of GST) | CT63: =CP63 -> 0
B64: 2 | C64: Is there a proposed performance fee? If so: What is the hurdle rate? How is it calculated? | D64: No | H64: =D64 -> No | L64: 2 | M64: Is there a proposed performance fee? If so: What is the hurdle rate? How is it calculated? | N64: No | R64: =N64 -> No | V64: 2 | W64: Is there a proposed performance fee? If so: What is the hurdle rate? How is it calculated? | AB64: =X64 -> 0 | AF64: 2 | AG64: Is there a proposed performance fee? If so: What is the hurdle rate? How is it calculated? | AL64: =AH64 -> 0 | AP64: 2 | AQ64: Is there a proposed performance fee? If so: What is the hurdle rate? How is it calculated? | AV64: =AR64 -> 0 | AZ64: 2 | BA64: Is there a proposed performance fee? If so: What is the hurdle rate? How is it calculated? | BF64: =BB64 -> 0 | BJ64: 2 | BK64: Is there a proposed performance fee? If so: What is the hurdle rate? How is it calculated? | BP64: =BL64 -> 0 | BT64: 2 | BU64: Is there a proposed performance fee? If so: What is the hurdle rate? How is it calculated? | BZ64: =BV64 -> 0 | CD64: 2 | CE64: Is there a proposed performance fee? If so: What is the hurdle rate? How is it calculated? | CJ64: =CF64 -> 0 | CN64: 2 | CO64: Is there a proposed performance fee? If so: What is the hurdle rate? How is it calculated? | CT64: =CP64 -> 0

Sheet Page Five - Portfolio Snapshot
B2: MyNorth Investment Manager Onboarding Questionnaire
B3: Page Five: Portfolio Snapshot
B4: All information required
C5: PLEASE POPULATE THIS WORKSHEET FOR THE AUSTRALIAN EQUITIES PORTFOLIO ONLY
B6: Portfolio name | D6: ='Page Two - IM Info contd'!#REF! -> #REF! | J6: Contributors and Detractors | R6: Portfolio name | T6: ='Page Two - IM Info contd'!#REF! -> #REF! | Z6: Contributors and Detractors | AH6: Portfolio name | AJ6: ='Page Two - IM Info contd'!#REF! -> #REF! | AP6: Contributors and Detractors | AX6: Portfolio name | AZ6: ='Page Two - IM Info contd'!#REF! -> #REF! | BF6: Contributors and Detractors | BN6: Portfolio name | BP6: ='Page Two - IM Info contd'!#REF! -> #REF! | BV6: Contributors and Detractors | CD6: Portfolio name | CF6: ='Page Two - IM Info contd'!#REF! -> #REF! | CL6: Contributors and Detractors | CT6: Portfolio name | CV6: ='Page Two - IM Info contd'!#REF! -> #REF! | DB6: Contributors and Detractors | DJ6: Portfolio name | DL6: ='Page Two - IM Info contd'!#REF! -> #REF! | DR6: Contributors and Detractors | DZ6: Portfolio name | EB6: ='Page Two - IM Info contd'!#REF! -> #REF! | EH6: Contributors and Detractors | EP6: Portfolio name | ER6: ='Page Two - IM Info contd'!#REF! -> #REF! | EX6: Contributors and Detractors
B7: Portfolio type | D7: ='Page Four - Portfolio Details'!E81 -> 0 | R7: Portfolio type | T7: ='Page Four - Portfolio Details'!O81 -> 0 | AH7: Portfolio type | AJ7: ='Page Four - Portfolio Details'!Y81 -> 0 | AX7: Portfolio type | AZ7: ='Page Four - Portfolio Details'!AI81 -> 0 | BN7: Portfolio type | BP7: ='Page Four - Portfolio Details'!AS81 -> 0 | CD7: Portfolio type | CF7: ='Page Four - Portfolio Details'!BC81 -> 0 | CT7: Portfolio type | CV7: ='Page Four - Portfolio Details'!BM81 -> 0 | DJ7: Portfolio type | DL7: ='Page Four - Portfolio Details'!BW81 -> 0 | DZ7: Portfolio type | EB7: ='Page Four - Portfolio Details'!CG81 -> 0 | EP7: Portfolio type | ER7: ='Page Four - Portfolio Details'!CQ81 -> 0
B8: Benchmark | D8: ='Page Four - Portfolio Details'!E86 -> 0 | J8: Top 5 Contributors - 1 year | R8: Benchmark | T8: ='Page Four - Portfolio Details'!O86 -> 0 | Z8: Top 5 Contributors - 1 year | AH8: Benchmark | AJ8: ='Page Four - Portfolio Details'!Y86 -> 0 | AP8: Top 5 Contributors - 1 year | AX8: Benchmark | AZ8: ='Page Four - Portfolio Details'!AI86 -> 0 | BF8: Top 5 Contributors - 1 year | BN8: Benchmark | BP8: ='Page Four - Portfolio Details'!AS86 -> 0 | BV8: Top 5 Contributors - 1 year | CD8: Benchmark | CF8: ='Page Four - Portfolio Details'!BC86 -> 0 | CL8: Top 5 Contributors - 1 year | CT8: Benchmark | CV8: ='Page Four - Portfolio Details'!BM86 -> 0 | DB8: Top 5 Contributors - 1 year | DJ8: Benchmark | DL8: ='Page Four - Portfolio Details'!BW86 -> 0 | DR8: Top 5 Contributors - 1 year | DZ8: Benchmark | EB8: ='Page Four - Portfolio Details'!CG86 -> 0 | EH8: Top 5 Contributors - 1 year | EP8: Benchmark | ER8: ='Page Four - Portfolio Details'!CQ86 -> 0 | EX8: Top 5 Contributors - 1 year
J9: Security name | L9: Sector | M9: Relative contribution % | Z9: Security name | AB9: Sector | AC9: Relative contribution % | AP9: Security name | AR9: Sector | AS9: Relative contribution % | BF9: Security name | BH9: Sector | BI9: Relative contribution % | BV9: Security name | BX9: Sector | BY9: Relative contribution % | CL9: Security name | CN9: Sector | CO9: Relative contribution % | DB9: Security name | DD9: Sector | DE9: Relative contribution % | DR9: Security name | DT9: Sector | DU9: Relative contribution % | EH9: Security name | EJ9: Sector | EK9: Relative contribution % | EX9: Security name | EZ9: Sector | FA9: Relative contribution %
I10: 1 | Y10: 1 | AO10: 1 | BE10: 1 | BU10: 1 | CK10: 1 | DA10: 1 | DQ10: 1 | EG10: 1 | EW10: 1
B11: GICS Sector exposures | I11: 2 | R11: GICS Sector exposures | Y11: 2 | AH11: GICS Sector exposures | AO11: 2 | AX11: GICS Sector exposures | BE11: 2 | BN11: GICS Sector exposures | BU11: 2 | CD11: GICS Sector exposures | CK11: 2 | CT11: GICS Sector exposures | DA11: 2 | DJ11: GICS Sector exposures | DQ11: 2 | DZ11: GICS Sector exposures | EG11: 2 | EP11: GICS Sector exposures | EW11: 2
D12: Portfolio Weight % | E12: Index Weight % | F12: Active Weight % | I12: 3 | T12: Portfolio Weight % | U12: Index Weight % | V12: Active Weight % | Y12: 3 | AJ12: Portfolio Weight % | AK12: Index Weight % | AL12: Active Weight % | AO12: 3 | AZ12: Portfolio Weight % | BA12: Index Weight % | BB12: Active Weight % | BE12: 3 | BP12: Portfolio Weight % | BQ12: Index Weight % | BR12: Active Weight % | BU12: 3 | CF12: Portfolio Weight % | CG12: Index Weight % | CH12: Active Weight % | CK12: 3 | CV12: Portfolio Weight % | CW12: Index Weight % | CX12: Active Weight % | DA12: 3 | DL12: Portfolio Weight % | DM12: Index Weight % | DN12: Active Weight % | DQ12: 3 | EB12: Portfolio Weight % | EC12: Index Weight % | ED12: Active Weight % | EG12: 3 | ER12: Portfolio Weight % | ES12: Index Weight % | ET12: Active Weight % | EW12: 3
B13: Materials | I13: 4 | R13: Materials | Y13: 4 | AH13: Materials | AO13: 4 | AX13: Materials | BE13: 4 | BN13: Materials | BU13: 4 | CD13: Materials | CK13: 4 | CT13: Materials | DA13: 4 | DJ13: Materials | DQ13: 4 | DZ13: Materials | EG13: 4 | EP13: Materials | EW13: 4
B14: Metals and Mining | I14: 5 | R14: Metals and Mining | Y14: 5 | AH14: Metals and Mining | AO14: 5 | AX14: Metals and Mining | BE14: 5 | BN14: Metals and Mining | BU14: 5 | CD14: Metals and Mining | CK14: 5 | CT14: Metals and Mining | DA14: 5 | DJ14: Metals and Mining | DQ14: 5 | DZ14: Metals and Mining | EG14: 5 | EP14: Metals and Mining | EW14: 5
B15: Energy | R15: Energy | AH15: Energy | AX15: Energy | BN15: Energy | CD15: Energy | CT15: Energy | DJ15: Energy | DZ15: Energy | EP15: Energy
B16: Industrials | J16: Top 5 Contributors - 3 years (annualised) | R16: Industrials | Z16: Top 5 Contributors - 3 years (annualised) | AH16: Industrials | AP16: Top 5 Contributors - 3 years (annualised) | AX16: Industrials | BF16: Top 5 Contributors - 3 years (annualised) | BN16: Industrials | BV16: Top 5 Contributors - 3 years (annualised) | CD16: Industrials | CL16: Top 5 Contributors - 3 years (annualised) | CT16: Industrials | DB16: Top 5 Contributors - 3 years (annualised) | DJ16: Industrials | DR16: Top 5 Contributors - 3 years (annualised) | DZ16: Industrials | EH16: Top 5 Contributors - 3 years (annualised) | EP16: Industrials | EX16: Top 5 Contributors - 3 years (annualised)
B17: Consumer Discretionary | J17: Security name | L17: Sector | M17: Relative contribution % | R17: Consumer Discretionary | Z17: Security name | AB17: Sector | AC17: Relative contribution % | AH17: Consumer Discretionary | AP17: Security name | AR17: Sector | AS17: Relative contribution % | AX17: Consumer Discretionary | BF17: Security name | BH17: Sector | BI17: Relative contribution % | BN17: Consumer Discretionary | BV17: Security name | BX17: Sector | BY17: Relative contribution % | CD17: Consumer Discretionary | CL17: Security name | CN17: Sector | CO17: Relative contribution % | CT17: Consumer Discretionary | DB17: Security name | DD17: Sector | DE17: Relative contribution % | DJ17: Consumer Discretionary | DR17: Security name | DT17: Sector | DU17: Relative contribution % | DZ17: Consumer Discretionary | EH17: Security name | EJ17: Sector | EK17: Relative contribution % | EP17: Consumer Discretionary | EX17: Security name | EZ17: Sector | FA17: Relative contribution %
B18: Consumer Staples | I18: 1 | R18: Consumer Staples | Y18: 1 | AH18: Consumer Staples | AO18: 1 | AX18: Consumer Staples | BE18: 1 | BN18: Consumer Staples | BU18: 1 | CD18: Consumer Staples | CK18: 1 | CT18: Consumer Staples | DA18: 1 | DJ18: Consumer Staples | DQ18: 1 | DZ18: Consumer Staples | EG18: 1 | EP18: Consumer Staples | EW18: 1
B19: Health Care | I19: 2 | R19: Health Care | Y19: 2 | AH19: Health Care | AO19: 2 | AX19: Health Care | BE19: 2 | BN19: Health Care | BU19: 2 | CD19: Health Care | CK19: 2 | CT19: Health Care | DA19: 2 | DJ19: Health Care | DQ19: 2 | DZ19: Health Care | EG19: 2 | EP19: Health Care | EW19: 2
B20: Financials | I20: 3 | R20: Financials | Y20: 3 | AH20: Financials | AO20: 3 | AX20: Financials | BE20: 3 | BN20: Financials | BU20: 3 | CD20: Financials | CK20: 3 | CT20: Financials | DA20: 3 | DJ20: Financials | DQ20: 3 | DZ20: Financials | EG20: 3 | EP20: Financials | EW20: 3
B21: Financials (ex-AREITs) | I21: 4 | R21: Financials (ex-AREITs) | Y21: 4 | AH21: Financials (ex-AREITs) | AO21: 4 | AX21: Financials (ex-AREITs) | BE21: 4 | BN21: Financials (ex-AREITs) | BU21: 4 | CD21: Financials (ex-AREITs) | CK21: 4 | CT21: Financials (ex-AREITs) | DA21: 4 | DJ21: Financials (ex-AREITs) | DQ21: 4 | DZ21: Financials (ex-AREITs) | EG21: 4 | EP21: Financials (ex-AREITs) | EW21: 4
B22: AREITs | I22: 5 | R22: AREITs | Y22: 5 | AH22: AREITs | AO22: 5 | AX22: AREITs | BE22: 5 | BN22: AREITs | BU22: 5 | CD22: AREITs | CK22: 5 | CT22: AREITs | DA22: 5 | DJ22: AREITs | DQ22: 5 | DZ22: AREITs | EG22: 5 | EP22: AREITs | EW22: 5
B23: Information Technology | R23: Information Technology | AH23: Information Technology | AX23: Information Technology | BN23: Information Technology | CD23: Information Technology | CT23: Information Technology | DJ23: Information Technology | DZ23: Information Technology | EP23: Information Technology
B24: Telecommunication Services | J24: Top 5 Detractors - 1 year | R24: Telecommunication Services | Z24: Top 5 Detractors - 1 year | AH24: Telecommunication Services | AP24: Top 5 Detractors - 1 year | AX24: Telecommunication Services | BF24: Top 5 Detractors - 1 year | BN24: Telecommunication Services | BV24: Top 5 Detractors - 1 year | CD24: Telecommunication Services | CL24: Top 5 Detractors - 1 year | CT24: Telecommunication Services | DB24: Top 5 Detractors - 1 year | DJ24: Telecommunication Services | DR24: Top 5 Detractors - 1 year | DZ24: Telecommunication Services | EH24: Top 5 Detractors - 1 year | EP24: Telecommunication Services | EX24: Top 5 Detractors - 1 year
B25: Utilities | J25: Security name | L25: Sector | M25: Relative contribution % | R25: Utilities | Z25: Security name | AB25: Sector | AC25: Relative contribution % | AH25: Utilities | AP25: Security name | AR25: Sector | AS25: Relative contribution % | AX25: Utilities | BF25: Security name | BH25: Sector | BI25: Relative contribution % | BN25: Utilities | BV25: Security name | BX25: Sector | BY25: Relative contribution % | CD25: Utilities | CL25: Security name | CN25: Sector | CO25: Relative contribution % | CT25: Utilities | DB25: Security name | DD25: Sector | DE25: Relative contribution % | DJ25: Utilities | DR25: Security name | DT25: Sector | DU25: Relative contribution % | DZ25: Utilities | EH25: Security name | EJ25: Sector | EK25: Relative contribution % | EP25: Utilities | EX25: Security name | EZ25: Sector | FA25: Relative contribution %
I26: 1 | Y26: 1 | AO26: 1 | BE26: 1 | BU26: 1 | CK26: 1 | DA26: 1 | DQ26: 1 | EG26: 1 | EW26: 1
B27: Top 5 Overweights | I27: 2 | R27: Top 5 Overweights | Y27: 2 | AH27: Top 5 Overweights | AO27: 2 | AX27: Top 5 Overweights | BE27: 2 | BN27: Top 5 Overweights | BU27: 2 | CD27: Top 5 Overweights | CK27: 2 | CT27: Top 5 Overweights | DA27: 2 | DJ27: Top 5 Overweights | DQ27: 2 | DZ27: Top 5 Overweights | EG27: 2 | EP27: Top 5 Overweights | EW27: 2
B28: Security name | D28: Sector | E28: Position % | F28: Active Weight % | I28: 3 | R28: Security name | T28: Sector | U28: Position % | V28: Active Weight % | Y28: 3 | AH28: Security name | AJ28: Sector | AK28: Position % | AL28: Active Weight % | AO28: 3 | AX28: Security name | AZ28: Sector | BA28: Position % | BB28: Active Weight % | BE28: 3 | BN28: Security name | BP28: Sector | BQ28: Position % | BR28: Active Weight % | BU28: 3 | CD28: Security name | CF28: Sector | CG28: Position % | CH28: Active Weight % | CK28: 3 | CT28: Security name | CV28: Sector | CW28: Position % | CX28: Active Weight % | DA28: 3 | DJ28: Security name | DL28: Sector | DM28: Position % | DN28: Active Weight % | DQ28: 3 | DZ28: Security name | EB28: Sector | EC28: Position % | ED28: Active Weight % | EG28: 3 | EP28: Security name | ER28: Sector | ES28: Position % | ET28: Active Weight % | EW28: 3
I29: 4 | Y29: 4 | AO29: 4 | BE29: 4 | BU29: 4 | CK29: 4 | DA29: 4 | DQ29: 4 | EG29: 4 | EW29: 4
I30: 5 | Y30: 5 | AO30: 5 | BE30: 5 | BU30: 5 | CK30: 5 | DA30: 5 | DQ30: 5 | EG30: 5 | EW30: 5
J32: Top 5 Detractors - 3 year (annualised) | Z32: Top 5 Detractors - 3 year (annualised) | AP32: Top 5 Detractors - 3 year (annualised) | BF32: Top 5 Detractors - 3 year (annualised) | BV32: Top 5 Detractors - 3 year (annualised) | CL32: Top 5 Detractors - 3 year (annualised) | DB32: Top 5 Detractors - 3 year (annualised) | DR32: Top 5 Detractors - 3 year (annualised) | EH32: Top 5 Detractors - 3 year (annualised) | EX32: Top 5 Detractors - 3 year (annualised)
J33: Security name | L33: Sector | M33: Relative contribution % | Z33: Security name | AB33: Sector | AC33: Relative contribution % | AP33: Security name | AR33: Sector | AS33: Relative contribution % | BF33: Security name | BH33: Sector | BI33: Relative contribution % | BV33: Security name | BX33: Sector | BY33: Relative contribution % | CL33: Security name | CN33: Sector | CO33: Relative contribution % | DB33: Security name | DD33: Sector | DE33: Relative contribution % | DR33: Security name | DT33: Sector | DU33: Relative contribution % | EH33: Security name | EJ33: Sector | EK33: Relative contribution % | EX33: Security name | EZ33: Sector | FA33: Relative contribution %
I34: 1 | Y34: 1 | AO34: 1 | BE34: 1 | BU34: 1 | CK34: 1 | DA34: 1 | DQ34: 1 | EG34: 1 | EW34: 1
B35: Top 5 Underweights | I35: 2 | R35: Top 5 Underweights | Y35: 2 | AH35: Top 5 Underweights | AO35: 2 | AX35: Top 5 Underweights | BE35: 2 | BN35: Top 5 Underweights | BU35: 2 | CD35: Top 5 Underweights | CK35: 2 | CT35: Top 5 Underweights | DA35: 2 | DJ35: Top 5 Underweights | DQ35: 2 | DZ35: Top 5 Underweights | EG35: 2 | EP35: Top 5 Underweights | EW35: 2
B36: Security name | D36: Sector | E36: Position % | F36: Active Weight % | I36: 3 | R36: Security name | T36: Sector | U36: Position % | V36: Active Weight % | Y36: 3 | AH36: Security name | AJ36: Sector | AK36: Position % | AL36: Active Weight % | AO36: 3 | AX36: Security name | AZ36: Sector | BA36: Position % | BB36: Active Weight % | BE36: 3 | BN36: Security name | BP36: Sector | BQ36: Position % | BR36: Active Weight % | BU36: 3 | CD36: Security name | CF36: Sector | CG36: Position % | CH36: Active Weight % | CK36: 3 | CT36: Security name | CV36: Sector | CW36: Position % | CX36: Active Weight % | DA36: 3 | DJ36: Security name | DL36: Sector | DM36: Position % | DN36: Active Weight % | DQ36: 3 | DZ36: Security name | EB36: Sector | EC36: Position % | ED36: Active Weight % | EG36: 3 | EP36: Security name | ER36: Sector | ES36: Position % | ET36: Active Weight % | EW36: 3
I37: 4 | Y37: 4 | AO37: 4 | BE37: 4 | BU37: 4 | CK37: 4 | DA37: 4 | DQ37: 4 | EG37: 4 | EW37: 4
I38: 5 | Y38: 5 | AO38: 5 | BE38: 5 | BU38: 5 | CK38: 5 | DA38: 5 | DQ38: 5 | EG38: 5 | EW38: 5
B43: Current allocation by size | D43: % of portfolio | R43: Current allocation by size | T43: % of portfolio | AH43: Current allocation by size | AJ43: % of portfolio | AX43: Current allocation by size | AZ43: % of portfolio | BN43: Current allocation by size | BP43: % of portfolio | CD43: Current allocation by size | CF43: % of portfolio | CT43: Current allocation by size | CV43: % of portfolio | DJ43: Current allocation by size | DL43: % of portfolio | DZ43: Current allocation by size | EB43: % of portfolio | EP43: Current allocation by size | ER43: % of portfolio
B44: S&P/ASX 20 | R44: S&P/ASX 20 | AH44: S&P/ASX 20 | AX44: S&P/ASX 20 | BN44: S&P/ASX 20 | CD44: S&P/ASX 20 | CT44: S&P/ASX 20 | DJ44: S&P/ASX 20 | DZ44: S&P/ASX 20 | EP44: S&P/ASX 20
B45: S&P/ASX 21-50 | R45: S&P/ASX 21-50 | AH45: S&P/ASX 21-50 | AX45: S&P/ASX 21-50 | BN45: S&P/ASX 21-50 | CD45: S&P/ASX 21-50 | CT45: S&P/ASX 21-50 | DJ45: S&P/ASX 21-50 | DZ45: S&P/ASX 21-50 | EP45: S&P/ASX 21-50
B46: S&P/ASX 51-100 | R46: S&P/ASX 51-100 | AH46: S&P/ASX 51-100 | AX46: S&P/ASX 51-100 | BN46: S&P/ASX 51-100 | CD46: S&P/ASX 51-100 | CT46: S&P/ASX 51-100 | DJ46: S&P/ASX 51-100 | DZ46: S&P/ASX 51-100 | EP46: S&P/ASX 51-100
B47: S&P/ASX 101-200 | R47: S&P/ASX 101-200 | AH47: S&P/ASX 101-200 | AX47: S&P/ASX 101-200 | BN47: S&P/ASX 101-200 | CD47: S&P/ASX 101-200 | CT47: S&P/ASX 101-200 | DJ47: S&P/ASX 101-200 | DZ47: S&P/ASX 101-200 | EP47: S&P/ASX 101-200
B48: S&P / ASX 300 (ex-S&P / ASX 200) | R48: S&P / ASX 300 (ex-S&P / ASX 200) | AH48: S&P / ASX 300 (ex-S&P / ASX 200) | AX48: S&P / ASX 300 (ex-S&P / ASX 200) | BN48: S&P / ASX 300 (ex-S&P / ASX 200) | CD48: S&P / ASX 300 (ex-S&P / ASX 200) | CT48: S&P / ASX 300 (ex-S&P / ASX 200) | DJ48: S&P / ASX 300 (ex-S&P / ASX 200) | DZ48: S&P / ASX 300 (ex-S&P / ASX 200) | EP48: S&P / ASX 300 (ex-S&P / ASX 200)
N66: =I66 -> 0 | AD66: =Y66 -> 0 | AT66: =AO66 -> 0 | BJ66: =BE66 -> 0 | BZ66: =BU66 -> 0 | CP66: =CK66 -> 0 | DF66: =DA66 -> 0 | DV66: =DQ66 -> 0 | EL66: =EG66 -> 0
N67: =I67 -> 0 | AD67: =Y67 -> 0 | AT67: =AO67 -> 0 | BJ67: =BE67 -> 0 | BZ67: =BU67 -> 0 | CP67: =CK67 -> 0 | DF67: =DA67 -> 0 | DV67: =DQ67 -> 0 | EL67: =EG67 -> 0
N68: =I68 -> 0 | AD68: =Y68 -> 0 | AT68: =AO68 -> 0 | BJ68: =BE68 -> 0 | BZ68: =BU68 -> 0 | CP68: =CK68 -> 0 | DF68: =DA68 -> 0 | DV68: =DQ68 -> 0 | EL68: =EG68 -> 0
N69: =I69 -> 0 | AD69: =Y69 -> 0 | AT69: =AO69 -> 0 | BJ69: =BE69 -> 0 | BZ69: =BU69 -> 0 | CP69: =CK69 -> 0 | DF69: =DA69 -> 0 | DV69: =DQ69 -> 0 | EL69: =EG69 -> 0

Sheet Page Six - Liquidity Testing
A1: Liquidity stress testing - normal and stressed market conditions
A3: - Please provide the participation rate used and how liquidity for listed and unlisted assets are determined - Percentage of portfolio liquidated within 30 trading days assuming 25% of Average Daily Volume (ADV) over the past 12 months.
B4: Liquidity in Normal Stress (25% ADV) market conditions - # Trading Days to liquidate 100% of Fund
B5: 1 to 3 trading days | C5: >3 to 21 trading days | D5: >21 to 30 trading days | E5: >30 days to 3 months | F5: >3 months to 6 months | G5: <1 year | H5: >1 year
A6: Portfolio 1
A7: Portfolio 2
A8: Portfolio 3
A9: Portfolio 4
A10: Portfolio 5
B12: Liquidity in Stressed (12.5% ADV) market conditions - # Trading Days to liquidate 100% of Fund
B13: 1 to 3 trading days | C13: >3 to 21 trading days | D13: >21 to 30 trading days | E13: >30 days to 3 months | F13: >3 months to 6 months | G13: <1 year | H13: >1 year
A14: Portfolio 1
A15: Portfolio 2
A16: Portfolio 3
A17: Portfolio 4
A18: Portfolio 5
A23: Low Stress (Sell 25% of average daily volume)
B24: 7 Days | C24: 10 Days | D24: 1 Month | E24: 3 Months | F24: 12 Months | G24: >12 Months
A25: 100% Growth | B25: 0.9032 | C25: 0.9172 | D25: 0.9653 | E25: 0.9979 | F25: 0.9979 | G25: 1
A27: Moderate Stress (Sell 12.5% of average daily volume)
B28: 7 Days | C28: 10 Days | D28: 1 Month | E28: 3 Months | F28: 12 Months | G28: >12 Months
A29: 100% Growth | B29: 0.8151 | C29: 0.8436 | D29: 0.9017 | E29: 0.9788 | F29: 0.9979 | G29: 1
A31: Extreme Stress (Sell 5% of average daily volume)
B32: 7 Days | C32: 10 Days | D32: 1 Month | E32: 3 Months | F32: 12 Months | G32: >12 Months
A33: 100% Growth | B33: 0.723 | C33: 0.7665 | D33: 0.843 | E33: 0.9019 | F33: 0.9972 | G33: 0.9993
A35: Low Stress (Sell 25% of average daily volume)
B36: 7 Days | C36: 10 Days | D36: 1 Month | E36: 3 Months | F36: 12 Months | G36: >12 Months
A37: 0% Growth | B37: 0.9114 | C37: 0.9682 | D37: 0.9936 | E37: 0.9942 | F37: 0.9944 | G37: 1
A39: Moderate Stress (Sell 12.5% of average daily volume)
B40: 7 Days | C40: 10 Days | D40: 1 Month | E40: 3 Months | F40: 12 Months | G40: >12 Months
A41: 0% Growth | B41: 0.7927 | C41: 0.9039 | D41: 0.9778 | E41: 0.994 | F41: 0.9944 | G41: 1
A43: Extreme Stress (Sell 5% of average daily volume)
B44: 7 Days | C44: 10 Days | D44: 1 Month | E44: 3 Months | F44: 12 Months | G44: >12 Months
A45: 0% Growth | B45: 0.672 | C45: 0.7414 | D45: 0.9451 | E45: 0.9781 | F45: 0.9944 | G45: 1

Sheet Page Seven - Scenario Testing
A1: Scenario testing - Total Portfolio Analysis (TPA) for the following periods:
A4: Scenario | B4: Portfolio 1 | C4: Benchmark | D4: Portfolio 2 | E4: Benchmark | F4: Portfolio 3 | G4: Benchmark | H4: Portfolio 4 | I4: Benchmark | J4: Portfolio 5 | K4: Benchmark
A5: 1987 crash
A6: 1990s bull market
A7: 2003-2007
A8: GFC (Sep 2008 – Nov 2008)
A9: Post GFC
A10: ASX200 down 35%
A11: AU Yields up 250bps

Sheet Page Eight - Underlying Funds
A3: Fund | B3: Role in portfolio | C3: Benchmark for the strategy | D3: Target excess return | E3: Strategy highlights: style, factor biases | F3: Risk assessment: Tracking error (vs benchmark)
A4: Pendal MidCap Fund | B4: Australian Equity - Mid Cap | C4: S&P/ASX Mid Small TR Index AUD | D4: 3-5% | E4: Mid cap | F4: 3-8%
A5: Ausbil Australian Active Equity Fund | B5: Australian Equity - Large Cap | C5: S&P/ASX 300 TR Index AUD | D5: 0.03 | E5: Core/Style Neutral | F5: 0.05
A6: Allan Gray Australian Equity Fund | B6: Australian Equity - Large Cap | C6: S&P/ASX 300 TR Index AUD | D6: N/A | E6: Value | F6: N/A
A7: Firetrail Australian Small Companies Fund (Class A) | B7: Australian Equity - Small Cap | C7: S&P/ASX Small Ordinaries TR Index AUD | D7: 0.07 | E7: Small cap | F7: 0.08
A8: Vanguard Australian Shares Index Fund (W) | B8: Australian Equity - Index | C8: S&P/ASX 300 TR Index AUD | D8: N/A | E8: Index | F8: N/A
A9: Plato Global Alpha Fund | B9: International Equity - Large Cap | C9: MSCI World NR Index AUD | D9: 4-5% | E9: Long/short | F9: 3-5%
A10: Arrowstreet Global Eqity Fund | B10: International Equity - Large Cap | C10: MSCI AC World ex Australia NR Index AUD | D10: 0.03 | E10: Quantitative | F10: 3-7%
A11: Munro Global Growth Small & Mid Cap Fund - Class A | B11: International Equity - SMID | C11: MSCI AC World SMID NR Index AUD | D11: N/A | E11: Global mid cap | F11: N/A
A12: Magellan Global Opportunities Fund No. 2 | B12: International Equity - Large Cap | C12: MSCI World NR Index AUD | D12: N/A | E12: Global growth | F12: N/A
A13: Orbis Global Equity Fund | B13: International Equity - Large Cap | C13: MSCI AC World NR Index AUD | D13: N/A | E13: Global value | F13: N/A
A14: Fidelity Asia Fund | B14: International Equity - Regional | C14: MSCI AC Asia ex Japan NR Index AUD | D14: N/A | E14: Global emerging markets | F14: 4-7%
A15: Vanguard International Shares Index Fund | B15: International Equity - Index | C15: MSCI World ex Australia NR Index AUD | D15: N/A | E15: Index | F15: N/A
A16: Vanguard Australian Property Securities Index Fund (W) | B16: AREIT - Index | C16: S&P/ASX 300 A-REIT TR Index AUD | D16: N/A | E16: Index | F16: N/A
A17: Quay Global Real Estate Fund (Unhedged) Active ETF | B17: GREIT | C17: FTSE EPRA/NAREIT Developed NR Index AUD | D17: N/A | E17: GREIT | F17: N/A
A18: Clearbridge RARE Infrastructure Value Fund - Unhedged | B18: International Infrastructure | C18: FTSE Global Core Infrastructure 50/50 NR Index AUD | D18: N/A | E18: Infrastructure | F18: N/A
A19: Pendal Dynamic Income Fund | B19: Australian Fixed Income | C19: RBA Cash Rate | D19: 2-3% | E19: Unconstrained Bond | F19: N/A
A20: Franklin Australia Absolute Return Bond Fund - Class A | B20: Australian Fixed Income | C20: Bloomberg AusBond Bank Bill Index AUD | D20: 2-3% | E20: Unconstrained Bond | F20: 2-4%
A21: UBS Income Solutions Fund | B21: Australian Fixed Income | C21: RBA Cash Rate | D21: 0.02 | E21: Specialised Income | F21: 2.5-5%
A22: Schroder Fixed Income - Client Class | B22: Australian Fixed Income | C22: Bloomberg AusBond Composite 0+ Year Index AUD | D22: 1-1.5% | E22: Diversified Bonds | F22: 0.015
A23: PIMCO Diversified Fixed Interest Fund - Wholesale Class | B23: Australian/Global Fixed Income Core | C23: 50% Bloomberg AusBond Composite 0+ Year Index AUD / 50% Bloomberg Global Aggregate TR Index (AUD Hedged) | D23: 0.01 | E23: Diversified Bonds | F23: 0.03
A24: Macquarie Dynamic Bond Fund | B24: Global Bonds | C24: Bloomberg Global Aggregate TR Index (AUD Hedged) | D24: 1-2% | E24: Global Bonds | F24: N/A
A25: Bentham Global Income Fund | B25: Global High Yield | C25: 50% Bloomberg AusBond Bank Bill Index AUD / 50% Bloomberg AusBond Composite 0+ Year Index AUD | D25: 0.02 | E25: Specialised High Income | F25: N/A
A26: Daintree High Income Trust | B26: Global High Yield | C26: RBA Cash Rate | D26: 3-4% | E26: Specialised High Income | F26: N/A

Sheet Page Ten - Rebates
B2: MyNorth Investment Manager Onboarding Questionnaire
B3: Page Ten: Rebates required in the managed portfolios
B4: All information required - Insert new rows as required
B7: Rebate details | E7: Fund Manager Contact Person
B8: ASX/APIR code | C8: Investment option name | D8: Rebate Rate (% rebate payable) | E8: Fund Manager | F8: Primary Contact Person | G8: Phone | H8: Email
B9: e.g APR1234AU | C9: XYZ Australian Equities Fund A | D9: 0.002 | E9: Fund Manager XYZ | F9: John Smith | G9: 0423567890 | H9: example@xyz.com

Sheet Page Nine - Directy Equity 
A1: Australian Equities -for a portfolio of direct equities; please provide charts on market cap, sector allocation, style bias

Sheet Internal Use Only - PDS
B2: MyNorth Investment Manager Onboarding Questionnaire
B3: Mandate
B5: Managed Portfolio Name | D5: ='Page Two - IM Info contd'!#REF! -> #REF! | J5: Managed Portfolio Name | L5: ='Page Two - IM Info contd'!#REF! -> #REF! | R5: Managed Portfolio Name | T5: ='Page Two - IM Info contd'!#REF! -> #REF! | Z5: Managed Portfolio Name | AB5: ='Page Two - IM Info contd'!#REF! -> #REF! | AH5: Managed Portfolio Name | AJ5: ='Page Two - IM Info contd'!#REF! -> #REF! | AP5: Managed Portfolio Name | AR5: ='Page Two - IM Info contd'!#REF! -> #REF! | AX5: Managed Portfolio Name | AZ5: ='Page Two - IM Info contd'!#REF! -> #REF! | BF5: Managed Portfolio Name | BH5: ='Page Two - IM Info contd'!#REF! -> #REF! | BN5: Managed Portfolio Name | BP5: ='Page Two - IM Info contd'!#REF! -> #REF! | BV5: Managed Portfolio Name | BX5: ='Page Two - IM Info contd'!#REF! -> #REF!
C7: Investment Manager Information | D7: Response | K7: Investment Manager Information | L7: Response | S7: Investment Manager Information | T7: Response | AA7: Investment Manager Information | AB7: Response | AI7: Investment Manager Information | AJ7: Response | AQ7: Investment Manager Information | AR7: Response | AY7: Investment Manager Information | AZ7: Response | BG7: Investment Manager Information | BH7: Response | BO7: Investment Manager Information | BP7: Response | BW7: Investment Manager Information | BX7: Response
C8: Legal entity name | D8: ='Page One - IM Info'!$G$8 -> Salita Portfolio Services Pty Ltd | K8: Legal entity name | L8: ='Page One - IM Info'!$G$8 -> Salita Portfolio Services Pty Ltd | S8: Legal entity name | T8: ='Page One - IM Info'!$G$8 -> Salita Portfolio Services Pty Ltd | AA8: Legal entity name | AB8: ='Page One - IM Info'!$G$8 -> Salita Portfolio Services Pty Ltd | AI8: Legal entity name | AJ8: ='Page One - IM Info'!$G$8 -> Salita Portfolio Services Pty Ltd | AQ8: Legal entity name | AR8: ='Page One - IM Info'!$G$8 -> Salita Portfolio Services Pty Ltd | AY8: Legal entity name | AZ8: ='Page One - IM Info'!$G$8 -> Salita Portfolio Services Pty Ltd | BG8: Legal entity name | BH8: ='Page One - IM Info'!$G$8 -> Salita Portfolio Services Pty Ltd | BO8: Legal entity name | BP8: ='Page One - IM Info'!$G$8 -> Salita Portfolio Services Pty Ltd | BW8: Legal entity name | BX8: ='Page One - IM Info'!$G$8 -> Salita Portfolio Services Pty Ltd
C9: ABN | D9: ='Page One - IM Info'!$G$9 -> 39 609 946 616 | K9: ABN | L9: ='Page One - IM Info'!$G$9 -> 39 609 946 616 | S9: ABN | T9: ='Page One - IM Info'!$G$9 -> 39 609 946 616 | AA9: ABN | AB9: ='Page One - IM Info'!$G$9 -> 39 609 946 616 | AI9: ABN | AJ9: ='Page One - IM Info'!$G$9 -> 39 609 946 616 | AQ9: ABN | AR9: ='Page One - IM Info'!$G$9 -> 39 609 946 616 | AY9: ABN | AZ9: ='Page One - IM Info'!$G$9 -> 39 609 946 616 | BG9: ABN | BH9: ='Page One - IM Info'!$G$9 -> 39 609 946 616 | BO9: ABN | BP9: ='Page One - IM Info'!$G$9 -> 39 609 946 616 | BW9: ABN | BX9: ='Page One - IM Info'!$G$9 -> 39 609 946 616
C10: AFSL Number | D10: ='Page One - IM Info'!$G$10 -> Salita Portfolio Services Pty Ltd is a corporate authorised representative of Personal Financial Services Ltd (PFS) CAR 1241713 | K10: AFSL Number | L10: ='Page One - IM Info'!$G$10 -> Salita Portfolio Services Pty Ltd is a corporate authorised representative of Personal Financial Services Ltd (PFS) CAR 1241713 | S10: AFSL Number | T10: ='Page One - IM Info'!$G$10 -> Salita Portfolio Services Pty Ltd is a corporate authorised representative of Personal Financial Services Ltd (PFS) CAR 1241713 | AA10: AFSL Number | AB10: ='Page One - IM Info'!$G$10 -> Salita Portfolio Services Pty Ltd is a corporate authorised representative of Personal Financial Services Ltd (PFS) CAR 1241713 | AI10: AFSL Number | AJ10: ='Page One - IM Info'!$G$10 -> Salita Portfolio Services Pty Ltd is a corporate authorised representative of Personal Financial Services Ltd (PFS) CAR 1241713 | AQ10: AFSL Number | AR10: ='Page One - IM Info'!$G$10 -> Salita Portfolio Services Pty Ltd is a corporate authorised representative of Personal Financial Services Ltd (PFS) CAR 1241713 | AY10: AFSL Number | AZ10: ='Page One - IM Info'!$G$10 -> Salita Portfolio Services Pty Ltd is a corporate authorised representative of Personal Financial Services Ltd (PFS) CAR 1241713 | BG10: AFSL Number | BH10: ='Page One - IM Info'!$G$10 -> Salita Portfolio Services Pty Ltd is a corporate authorised representative of Personal Financial Services Ltd (PFS) CAR 1241713 | BO10: AFSL Number | BP10: ='Page One - IM Info'!$G$10 -> Salita Portfolio Services Pty Ltd is a corporate authorised representative of Personal Financial Services Ltd (PFS) CAR 1241713 | BW10: AFSL Number | BX10: ='Page One - IM Info'!$G$10 -> Salita Portfolio Services Pty Ltd is a corporate authorised representative of Personal Financial Services Ltd (PFS) CAR 1241713
C11: About the Investment Manager | D11: ='Page One - IM Info'!$G$17 -> 0 | K11: About the Investment Manager | L11: ='Page One - IM Info'!$G$17 -> 0 | S11: About the Investment Manager | T11: ='Page One - IM Info'!$G$17 -> 0 | AA11: About the Investment Manager | AB11: ='Page One - IM Info'!$G$17 -> 0 | AI11: About the Investment Manager | AJ11: ='Page One - IM Info'!$G$17 -> 0 | AQ11: About the Investment Manager | AR11: ='Page One - IM Info'!$G$17 -> 0 | AY11: About the Investment Manager | AZ11: ='Page One - IM Info'!$G$17 -> 0 | BG11: About the Investment Manager | BH11: ='Page One - IM Info'!$G$17 -> 0 | BO11: About the Investment Manager | BP11: ='Page One - IM Info'!$G$17 -> 0 | BW11: About the Investment Manager | BX11: ='Page One - IM Info'!$G$17 -> 0
C12: Investment philosophy and process | D12: ='Page One - IM Info'!$G$18 -> At Salita Portfolio Services, the approach to portfolio construction is driven by the following investment principles: • Growing and preserving capital - The overarching goal is to grow investor wealth over time whilst minimising the risk of permanent capital loss. Whilst negative returns may be experienced over various time periods, Salita Portfolio Services' focus is on minimising drawdowns and preserving capital over the medium to long term. • Long term approach - Salita Portfolio Services ensures the Strategic Asset Allocation (SAA) is aligned to client risk profiles. The SAA is built around medium to long term capital market assumptions and is reviewed annually to ensure consistency with overall portfolio objectives. Salita Portfolio Services believe that timing the market is difficult and therefore do not intend to take a short-term tactical asset allocation approach. Rather they interrogate the SAA on a regular basis to determine if changes are warranted to support a high conviction medium term view. • Managing turnover - As part of a longer-term approach, Salita Portfolio Services aim to keep turnover within the portfolio to a minimum. Part of this approach is to ensure investment products are measured over the appropriate time horizon. • Active and passive investment strategies - Salita Portfolio Services assess the merits of active management across each asset class and will use active management where they have strong conviction that it will lead to a superior outcome, either via outperformance and/or lowering drawdown risk. Typically, this results in a blend of active and passive investment strategies in portfolios. • A focus on fees - Assessing the level and appropriateness of fees, both at the individual investment product and overall portfolio level is an important feature of Salita Portfolio Services' approach. Lower fees are the preference but paying an appropriate fee to gain access to superior investment skills is also worthy of consideration. • Diversification - Salita Portfolio Services believe that diversification is an effective way to manage risk. It enables portfolios to perform through varied market conditions and not be wholly reliant on a particular style (i.e. Growth or Value) being in favour. | K12: Investment philosophy and process | L12: ='Page One - IM Info'!$G$18 -> At Salita Portfolio Services, the approach to portfolio construction is driven by the following investment principles: • Growing and preserving capital - The overarching goal is to grow investor wealth over time whilst minimising the risk of permanent capital loss. Whilst negative returns may be experienced over various time periods, Salita Portfolio Services' focus is on minimising drawdowns and preserving capital over the medium to long term. • Long term approach - Salita Portfolio Services ensures the Strategic Asset Allocation (SAA) is aligned to client risk profiles. The SAA is built around medium to long term capital market assumptions and is reviewed annually to ensure consistency with overall portfolio objectives. Salita Portfolio Services believe that timing the market is difficult and therefore do not intend to take a short-term tactical asset allocation approach. Rather they interrogate the SAA on a regular basis to determine if changes are warranted to support a high conviction medium term view. • Managing turnover - As part of a longer-term approach, Salita Portfolio Services aim to keep turnover within the portfolio to a minimum. Part of this approach is to ensure investment products are measured over the appropriate time horizon. • Active and passive investment strategies - Salita Portfolio Services assess the merits of active management across each asset class and will use active management where they have strong conviction that it will lead to a superior outcome, either via outperformance and/or lowering drawdown risk. Typically, this results in a blend of active and passive investment strategies in portfolios. • A focus on fees - Assessing the level and appropriateness of fees, both at the individual investment product and overall portfolio level is an important feature of Salita Portfolio Services' approach. Lower fees are the preference but paying an appropriate fee to gain access to superior investment skills is also worthy of consideration. • Diversification - Salita Portfolio Services believe that diversification is an effective way to manage risk. It enables portfolios to perform through varied market conditions and not be wholly reliant on a particular style (i.e. Growth or Value) being in favour. | S12: Investment philosophy and process | T12: ='Page One - IM Info'!$G$18 -> At Salita Portfolio Services, the approach to portfolio construction is driven by the following investment principles: • Growing and preserving capital - The overarching goal is to grow investor wealth over time whilst minimising the risk of permanent capital loss. Whilst negative returns may be experienced over various time periods, Salita Portfolio Services' focus is on minimising drawdowns and preserving capital over the medium to long term. • Long term approach - Salita Portfolio Services ensures the Strategic Asset Allocation (SAA) is aligned to client risk profiles. The SAA is built around medium to long term capital market assumptions and is reviewed annually to ensure consistency with overall portfolio objectives. Salita Portfolio Services believe that timing the market is difficult and therefore do not intend to take a short-term tactical asset allocation approach. Rather they interrogate the SAA on a regular basis to determine if changes are warranted to support a high conviction medium term view. • Managing turnover - As part of a longer-term approach, Salita Portfolio Services aim to keep turnover within the portfolio to a minimum. Part of this approach is to ensure investment products are measured over the appropriate time horizon. • Active and passive investment strategies - Salita Portfolio Services assess the merits of active management across each asset class and will use active management where they have strong conviction that it will lead to a superior outcome, either via outperformance and/or lowering drawdown risk. Typically, this results in a blend of active and passive investment strategies in portfolios. • A focus on fees - Assessing the level and appropriateness of fees, both at the individual investment product and overall portfolio level is an important feature of Salita Portfolio Services' approach. Lower fees are the preference but paying an appropriate fee to gain access to superior investment skills is also worthy of consideration. • Diversification - Salita Portfolio Services believe that diversification is an effective way to manage risk. It enables portfolios to perform through varied market conditions and not be wholly reliant on a particular style (i.e. Growth or Value) being in favour. | AA12: Investment philosophy and process | AB12: ='Page One - IM Info'!$G$18 -> At Salita Portfolio Services, the approach to portfolio construction is driven by the following investment principles: • Growing and preserving capital - The overarching goal is to grow investor wealth over time whilst minimising the risk of permanent capital loss. Whilst negative returns may be experienced over various time periods, Salita Portfolio Services' focus is on minimising drawdowns and preserving capital over the medium to long term. • Long term approach - Salita Portfolio Services ensures the Strategic Asset Allocation (SAA) is aligned to client risk profiles. The SAA is built around medium to long term capital market assumptions and is reviewed annually to ensure consistency with overall portfolio objectives. Salita Portfolio Services believe that timing the market is difficult and therefore do not intend to take a short-term tactical asset allocation approach. Rather they interrogate the SAA on a regular basis to determine if changes are warranted to support a high conviction medium term view. • Managing turnover - As part of a longer-term approach, Salita Portfolio Services aim to keep turnover within the portfolio to a minimum. Part of this approach is to ensure investment products are measured over the appropriate time horizon. • Active and passive investment strategies - Salita Portfolio Services assess the merits of active management across each asset class and will use active management where they have strong conviction that it will lead to a superior outcome, either via outperformance and/or lowering drawdown risk. Typically, this results in a blend of active and passive investment strategies in portfolios. • A focus on fees - Assessing the level and appropriateness of fees, both at the individual investment product and overall portfolio level is an important feature of Salita Portfolio Services' approach. Lower fees are the preference but paying an appropriate fee to gain access to superior investment skills is also worthy of consideration. • Diversification - Salita Portfolio Services believe that diversification is an effective way to manage risk. It enables portfolios to perform through varied market conditions and not be wholly reliant on a particular style (i.e. Growth or Value) being in favour. | AI12: Investment philosophy and process | AJ12: ='Page One - IM Info'!$G$18 -> At Salita Portfolio Services, the approach to portfolio construction is driven by the following investment principles: • Growing and preserving capital - The overarching goal is to grow investor wealth over time whilst minimising the risk of permanent capital loss. Whilst negative returns may be experienced over various time periods, Salita Portfolio Services' focus is on minimising drawdowns and preserving capital over the medium to long term. • Long term approach - Salita Portfolio Services ensures the Strategic Asset Allocation (SAA) is aligned to client risk profiles. The SAA is built around medium to long term capital market assumptions and is reviewed annually to ensure consistency with overall portfolio objectives. Salita Portfolio Services believe that timing the market is difficult and therefore do not intend to take a short-term tactical asset allocation approach. Rather they interrogate the SAA on a regular basis to determine if changes are warranted to support a high conviction medium term view. • Managing turnover - As part of a longer-term approach, Salita Portfolio Services aim to keep turnover within the portfolio to a minimum. Part of this approach is to ensure investment products are measured over the appropriate time horizon. • Active and passive investment strategies - Salita Portfolio Services assess the merits of active management across each asset class and will use active management where they have strong conviction that it will lead to a superior outcome, either via outperformance and/or lowering drawdown risk. Typically, this results in a blend of active and passive investment strategies in portfolios. • A focus on fees - Assessing the level and appropriateness of fees, both at the individual investment product and overall portfolio level is an important feature of Salita Portfolio Services' approach. Lower fees are the preference but paying an appropriate fee to gain access to superior investment skills is also worthy of consideration. • Diversification - Salita Portfolio Services believe that diversification is an effective way to manage risk. It enables portfolios to perform through varied market conditions and not be wholly reliant on a particular style (i.e. Growth or Value) being in favour. | AQ12: Investment philosophy and process | AR12: ='Page One - IM Info'!$G$18 -> At Salita Portfolio Services, the approach to portfolio construction is driven by the following investment principles: • Growing and preserving capital - The overarching goal is to grow investor wealth over time whilst minimising the risk of permanent capital loss. Whilst negative returns may be experienced over various time periods, Salita Portfolio Services' focus is on minimising drawdowns and preserving capital over the medium to long term. • Long term approach - Salita Portfolio Services ensures the Strategic Asset Allocation (SAA) is aligned to client risk profiles. The SAA is built around medium to long term capital market assumptions and is reviewed annually to ensure consistency with overall portfolio objectives. Salita Portfolio Services believe that timing the market is difficult and therefore do not intend to take a short-term tactical asset allocation approach. Rather they interrogate the SAA on a regular basis to determine if changes are warranted to support a high conviction medium term view. • Managing turnover - As part of a longer-term approach, Salita Portfolio Services aim to keep turnover within the portfolio to a minimum. Part of this approach is to ensure investment products are measured over the appropriate time horizon. • Active and passive investment strategies - Salita Portfolio Services assess the merits of active management across each asset class and will use active management where they have strong conviction that it will lead to a superior outcome, either via outperformance and/or lowering drawdown risk. Typically, this results in a blend of active and passive investment strategies in portfolios. • A focus on fees - Assessing the level and appropriateness of fees, both at the individual investment product and overall portfolio level is an important feature of Salita Portfolio Services' approach. Lower fees are the preference but paying an appropriate fee to gain access to superior investment skills is also worthy of consideration. • Diversification - Salita Portfolio Services believe that diversification is an effective way to manage risk. It enables portfolios to perform through varied market conditions and not be wholly reliant on a particular style (i.e. Growth or Value) being in favour. | AY12: Investment philosophy and process | AZ12: ='Page One - IM Info'!$G$18 -> At Salita Portfolio Services, the approach to portfolio construction is driven by the following investment principles: • Growing and preserving capital - The overarching goal is to grow investor wealth over time whilst minimising the risk of permanent capital loss. Whilst negative returns may be experienced over various time periods, Salita Portfolio Services' focus is on minimising drawdowns and preserving capital over the medium to long term. • Long term approach - Salita Portfolio Services ensures the Strategic Asset Allocation (SAA) is aligned to client risk profiles. The SAA is built around medium to long term capital market assumptions and is reviewed annually to ensure consistency with overall portfolio objectives. Salita Portfolio Services believe that timing the market is difficult and therefore do not intend to take a short-term tactical asset allocation approach. Rather they interrogate the SAA on a regular basis to determine if changes are warranted to support a high conviction medium term view. • Managing turnover - As part of a longer-term approach, Salita Portfolio Services aim to keep turnover within the portfolio to a minimum. Part of this approach is to ensure investment products are measured over the appropriate time horizon. • Active and passive investment strategies - Salita Portfolio Services assess the merits of active management across each asset class and will use active management where they have strong conviction that it will lead to a superior outcome, either via outperformance and/or lowering drawdown risk. Typically, this results in a blend of active and passive investment strategies in portfolios. • A focus on fees - Assessing the level and appropriateness of fees, both at the individual investment product and overall portfolio level is an important feature of Salita Portfolio Services' approach. Lower fees are the preference but paying an appropriate fee to gain access to superior investment skills is also worthy of consideration. • Diversification - Salita Portfolio Services believe that diversification is an effective way to manage risk. It enables portfolios to perform through varied market conditions and not be wholly reliant on a particular style (i.e. Growth or Value) being in favour. | BG12: Investment philosophy and process | BH12: ='Page One - IM Info'!$G$18 -> At Salita Portfolio Services, the approach to portfolio construction is driven by the following investment principles: • Growing and preserving capital - The overarching goal is to grow investor wealth over time whilst minimising the risk of permanent capital loss. Whilst negative returns may be experienced over various time periods, Salita Portfolio Services' focus is on minimising drawdowns and preserving capital over the medium to long term. • Long term approach - Salita Portfolio Services ensures the Strategic Asset Allocation (SAA) is aligned to client risk profiles. The SAA is built around medium to long term capital market assumptions and is reviewed annually to ensure consistency with overall portfolio objectives. Salita Portfolio Services believe that timing the market is difficult and therefore do not intend to take a short-term tactical asset allocation approach. Rather they interrogate the SAA on a regular basis to determine if changes are warranted to support a high conviction medium term view. • Managing turnover - As part of a longer-term approach, Salita Portfolio Services aim to keep turnover within the portfolio to a minimum. Part of this approach is to ensure investment products are measured over the appropriate time horizon. • Active and passive investment strategies - Salita Portfolio Services assess the merits of active management across each asset class and will use active management where they have strong conviction that it will lead to a superior outcome, either via outperformance and/or lowering drawdown risk. Typically, this results in a blend of active and passive investment strategies in portfolios. • A focus on fees - Assessing the level and appropriateness of fees, both at the individual investment product and overall portfolio level is an important feature of Salita Portfolio Services' approach. Lower fees are the preference but paying an appropriate fee to gain access to superior investment skills is also worthy of consideration. • Diversification - Salita Portfolio Services believe that diversification is an effective way to manage risk. It enables portfolios to perform through varied market conditions and not be wholly reliant on a particular style (i.e. Growth or Value) being in favour. | BO12: Investment philosophy and process | BP12: ='Page One - IM Info'!$G$18 -> At Salita Portfolio Services, the approach to portfolio construction is driven by the following investment principles: • Growing and preserving capital - The overarching goal is to grow investor wealth over time whilst minimising the risk of permanent capital loss. Whilst negative returns may be experienced over various time periods, Salita Portfolio Services' focus is on minimising drawdowns and preserving capital over the medium to long term. • Long term approach - Salita Portfolio Services ensures the Strategic Asset Allocation (SAA) is aligned to client risk profiles. The SAA is built around medium to long term capital market assumptions and is reviewed annually to ensure consistency with overall portfolio objectives. Salita Portfolio Services believe that timing the market is difficult and therefore do not intend to take a short-term tactical asset allocation approach. Rather they interrogate the SAA on a regular basis to determine if changes are warranted to support a high conviction medium term view. • Managing turnover - As part of a longer-term approach, Salita Portfolio Services aim to keep turnover within the portfolio to a minimum. Part of this approach is to ensure investment products are measured over the appropriate time horizon. • Active and passive investment strategies - Salita Portfolio Services assess the merits of active management across each asset class and will use active management where they have strong conviction that it will lead to a superior outcome, either via outperformance and/or lowering drawdown risk. Typically, this results in a blend of active and passive investment strategies in portfolios. • A focus on fees - Assessing the level and appropriateness of fees, both at the individual investment product and overall portfolio level is an important feature of Salita Portfolio Services' approach. Lower fees are the preference but paying an appropriate fee to gain access to superior investment skills is also worthy of consideration. • Diversification - Salita Portfolio Services believe that diversification is an effective way to manage risk. It enables portfolios to perform through varied market conditions and not be wholly reliant on a particular style (i.e. Growth or Value) being in favour. | BW12: Investment philosophy and process | BX12: ='Page One - IM Info'!$G$18 -> At Salita Portfolio Services, the approach to portfolio construction is driven by the following investment principles: • Growing and preserving capital - The overarching goal is to grow investor wealth over time whilst minimising the risk of permanent capital loss. Whilst negative returns may be experienced over various time periods, Salita Portfolio Services' focus is on minimising drawdowns and preserving capital over the medium to long term. • Long term approach - Salita Portfolio Services ensures the Strategic Asset Allocation (SAA) is aligned to client risk profiles. The SAA is built around medium to long term capital market assumptions and is reviewed annually to ensure consistency with overall portfolio objectives. Salita Portfolio Services believe that timing the market is difficult and therefore do not intend to take a short-term tactical asset allocation approach. Rather they interrogate the SAA on a regular basis to determine if changes are warranted to support a high conviction medium term view. • Managing turnover - As part of a longer-term approach, Salita Portfolio Services aim to keep turnover within the portfolio to a minimum. Part of this approach is to ensure investment products are measured over the appropriate time horizon. • Active and passive investment strategies - Salita Portfolio Services assess the merits of active management across each asset class and will use active management where they have strong conviction that it will lead to a superior outcome, either via outperformance and/or lowering drawdown risk. Typically, this results in a blend of active and passive investment strategies in portfolios. • A focus on fees - Assessing the level and appropriateness of fees, both at the individual investment product and overall portfolio level is an important feature of Salita Portfolio Services' approach. Lower fees are the preference but paying an appropriate fee to gain access to superior investment skills is also worthy of consideration. • Diversification - Salita Portfolio Services believe that diversification is an effective way to manage risk. It enables portfolios to perform through varied market conditions and not be wholly reliant on a particular style (i.e. Growth or Value) being in favour.
C13: Website | D13: ='Page One - IM Info'!$G$21 -> https://salitaportfolioservices.com.au/ | K13: Website | L13: ='Page One - IM Info'!$G$21 -> https://salitaportfolioservices.com.au/ | S13: Website | T13: ='Page One - IM Info'!$G$21 -> https://salitaportfolioservices.com.au/ | AA13: Website | AB13: ='Page One - IM Info'!$G$21 -> https://salitaportfolioservices.com.au/ | AI13: Website | AJ13: ='Page One - IM Info'!$G$21 -> https://salitaportfolioservices.com.au/ | AQ13: Website | AR13: ='Page One - IM Info'!$G$21 -> https://salitaportfolioservices.com.au/ | AY13: Website | AZ13: ='Page One - IM Info'!$G$21 -> https://salitaportfolioservices.com.au/ | BG13: Website | BH13: ='Page One - IM Info'!$G$21 -> https://salitaportfolioservices.com.au/ | BO13: Website | BP13: ='Page One - IM Info'!$G$21 -> https://salitaportfolioservices.com.au/ | BW13: Website | BX13: ='Page One - IM Info'!$G$21 -> https://salitaportfolioservices.com.au/
C15: Managed Portfolio Information | D15: Response | K15: Managed Portfolio Information | L15: Response | S15: Managed Portfolio Information | T15: Response | AA15: Managed Portfolio Information | AB15: Response | AI15: Managed Portfolio Information | AJ15: Response | AQ15: Managed Portfolio Information | AR15: Response | AY15: Managed Portfolio Information | AZ15: Response | BG15: Managed Portfolio Information | BH15: Response | BO15: Managed Portfolio Information | BP15: Response | BW15: Managed Portfolio Information | BX15: Response
C16: Code | D16: TBC | K16: Code | L16: TBC | S16: Code | T16: TBC | AA16: Code | AB16: TBC | AI16: Code | AJ16: TBC | AQ16: Code | AR16: TBC | AY16: Code | AZ16: TBC | BG16: Code | BH16: TBC | BO16: Code | BP16: TBC | BW16: Code | BX16: TBC
C17: Investment manager | D17: =D8 -> Salita Portfolio Services Pty Ltd | K17: Investment manager | L17: =L8 -> Salita Portfolio Services Pty Ltd | S17: Investment manager | T17: =T8 -> Salita Portfolio Services Pty Ltd | AA17: Investment manager | AB17: =AB8 -> Salita Portfolio Services Pty Ltd | AI17: Investment manager | AJ17: =AJ8 -> Salita Portfolio Services Pty Ltd | AQ17: Investment manager | AR17: =AR8 -> Salita Portfolio Services Pty Ltd | AY17: Investment manager | AZ17: =AZ8 -> Salita Portfolio Services Pty Ltd | BG17: Investment manager | BH17: =BH8 -> Salita Portfolio Services Pty Ltd | BO17: Investment manager | BP17: =BP8 -> Salita Portfolio Services Pty Ltd | BW17: Investment manager | BX17: =BX8 -> Salita Portfolio Services Pty Ltd
C18: Asset Class | D18: ='Page Four - Portfolio Details'!E80 -> 0 | K18: Asset Class | L18: ='Page Four - Portfolio Details'!O80 -> 0 | S18: Asset Class | T18: ='Page Four - Portfolio Details'!Y80 -> 0 | AA18: Asset Class | AB18: ='Page Four - Portfolio Details'!AI80 -> 0 | AI18: Asset Class | AJ18: ='Page Four - Portfolio Details'!AS80 -> 0 | AQ18: Asset Class | AR18: ='Page Four - Portfolio Details'!BC80 -> 0 | AY18: Asset Class | AZ18: ='Page Four - Portfolio Details'!BM80 -> 0 | BG18: Asset Class | BH18: ='Page Four - Portfolio Details'!BW80 -> 0 | BO18: Asset Class | BP18: ='Page Four - Portfolio Details'!CG80 -> 0 | BW18: Asset Class | BX18: ='Page Four - Portfolio Details'!CQ80 -> 0
C19: Availability | K19: Availability | S19: Availability | AA19: Availability | AI19: Availability | AQ19: Availability | AY19: Availability | BG19: Availability | BO19: Availability | BW19: Availability
C20: Investment Objective | D20: ='Page Four - Portfolio Details'!E85 -> 0 | K20: Investment Objective | L20: ='Page Four - Portfolio Details'!O85 -> 0 | S20: Investment Objective | T20: ='Page Four - Portfolio Details'!Y85 -> 0 | AA20: Investment Objective | AB20: ='Page Four - Portfolio Details'!AI85 -> 0 | AI20: Investment Objective | AJ20: ='Page Four - Portfolio Details'!AS85 -> 0 | AQ20: Investment Objective | AR20: ='Page Four - Portfolio Details'!BC85 -> 0 | AY20: Investment Objective | AZ20: ='Page Four - Portfolio Details'!BM85 -> 0 | BG20: Investment Objective | BH20: ='Page Four - Portfolio Details'!BW85 -> 0 | BO20: Investment Objective | BP20: ='Page Four - Portfolio Details'!CG85 -> 0 | BW20: Investment Objective | BX20: ='Page Four - Portfolio Details'!CQ85 -> 0
C21: Benchmark | D21: ='Page Four - Portfolio Details'!E86 -> 0 | K21: Benchmark | L21: ='Page Four - Portfolio Details'!O86 -> 0 | S21: Benchmark | T21: ='Page Four - Portfolio Details'!Y86 -> 0 | AA21: Benchmark | AB21: ='Page Four - Portfolio Details'!AI86 -> 0 | AI21: Benchmark | AJ21: ='Page Four - Portfolio Details'!AS86 -> 0 | AQ21: Benchmark | AR21: ='Page Four - Portfolio Details'!BC86 -> 0 | AY21: Benchmark | AZ21: ='Page Four - Portfolio Details'!BM86 -> 0 | BG21: Benchmark | BH21: ='Page Four - Portfolio Details'!BW86 -> 0 | BO21: Benchmark | BP21: ='Page Four - Portfolio Details'!CG86 -> 0 | BW21: Benchmark | BX21: ='Page Four - Portfolio Details'!CQ86 -> 0
C22: Minimum investment horizon | D22: ='Page Four - Portfolio Details'!E89 -> 0 | K22: Minimum investment horizon | L22: ='Page Four - Portfolio Details'!O89 -> 0 | S22: Minimum investment horizon | T22: ='Page Four - Portfolio Details'!Y89 -> 0 | AA22: Minimum investment horizon | AB22: ='Page Four - Portfolio Details'!AI89 -> 0 | AI22: Minimum investment horizon | AJ22: ='Page Four - Portfolio Details'!AS89 -> 0 | AQ22: Minimum investment horizon | AR22: ='Page Four - Portfolio Details'!BC89 -> 0 | AY22: Minimum investment horizon | AZ22: ='Page Four - Portfolio Details'!BM89 -> 0 | BG22: Minimum investment horizon | BH22: ='Page Four - Portfolio Details'!BW89 -> 0 | BO22: Minimum investment horizon | BP22: ='Page Four - Portfolio Details'!CG89 -> 0 | BW22: Minimum investment horizon | BX22: ='Page Four - Portfolio Details'!CQ89 -> 0
C23: Minimum investment amount | K23: Minimum investment amount | S23: Minimum investment amount | AA23: Minimum investment amount | AI23: Minimum investment amount | AQ23: Minimum investment amount | AY23: Minimum investment amount | BG23: Minimum investment amount | BO23: Minimum investment amount | BW23: Minimum investment amount
C24: Underlying assets | K24: Underlying assets | S24: Underlying assets | AA24: Underlying assets | AI24: Underlying assets | AQ24: Underlying assets | AY24: Underlying assets | BG24: Underlying assets | BO24: Underlying assets | BW24: Underlying assets
C25: Target growth/defensive exposure | K25: Target growth/defensive exposure | S25: Target growth/defensive exposure | AA25: Target growth/defensive exposure | AI25: Target growth/defensive exposure | AQ25: Target growth/defensive exposure | AY25: Target growth/defensive exposure | BG25: Target growth/defensive exposure | BO25: Target growth/defensive exposure | BW25: Target growth/defensive exposure
C26: Indicative asset allocation ranges | D26: Refer to asset class table below | K26: Indicative asset allocation ranges | L26: Refer to asset class table below | S26: Indicative asset allocation ranges | T26: Refer to asset class table below | AA26: Indicative asset allocation ranges | AB26: Refer to asset class table below | AI26: Indicative asset allocation ranges | AJ26: Refer to asset class table below | AQ26: Indicative asset allocation ranges | AR26: Refer to asset class table below | AY26: Indicative asset allocation ranges | AZ26: Refer to asset class table below | BG26: Indicative asset allocation ranges | BH26: Refer to asset class table below | BO26: Indicative asset allocation ranges | BP26: Refer to asset class table below | BW26: Indicative asset allocation ranges | BX26: Refer to asset class table below
C27: Portfolio income | D27: ='Page Four - Portfolio Details'!E110 -> 0 | K27: Portfolio income | L27: ='Page Four - Portfolio Details'!O110 -> 0 | S27: Portfolio income | T27: ='Page Four - Portfolio Details'!Y110 -> 0 | AA27: Portfolio income | AB27: ='Page Four - Portfolio Details'!AI110 -> 0 | AI27: Portfolio income | AJ27: ='Page Four - Portfolio Details'!AS110 -> 0 | AQ27: Portfolio income | AR27: ='Page Four - Portfolio Details'!BC110 -> 0 | AY27: Portfolio income | AZ27: ='Page Four - Portfolio Details'!BM110 -> 0 | BG27: Portfolio income | BH27: ='Page Four - Portfolio Details'!BW110 -> 0 | BO27: Portfolio income | BP27: ='Page Four - Portfolio Details'!CG110 -> 0 | BW27: Portfolio income | BX27: ='Page Four - Portfolio Details'!CQ110 -> 0
C28: Risk Band and Label | D28: ='Page Four - Portfolio Details'!E84 -> 0 | K28: Risk Band and Label | L28: ='Page Four - Portfolio Details'!O84 -> 0 | S28: Risk Band and Label | T28: ='Page Four - Portfolio Details'!Y84 -> 0 | AA28: Risk Band and Label | AB28: ='Page Four - Portfolio Details'!AI84 -> 0 | AI28: Risk Band and Label | AJ28: ='Page Four - Portfolio Details'!AS84 -> 0 | AQ28: Risk Band and Label | AR28: ='Page Four - Portfolio Details'!BC84 -> 0 | AY28: Risk Band and Label | AZ28: ='Page Four - Portfolio Details'!BM84 -> 0 | BG28: Risk Band and Label | BH28: ='Page Four - Portfolio Details'!BW84 -> 0 | BO28: Risk Band and Label | BP28: ='Page Four - Portfolio Details'!CG84 -> 0 | BW28: Risk Band and Label | BX28: ='Page Four - Portfolio Details'!CQ84 -> 0
C30: Asset class | D30: Min (%) | E30: Max (%) | K30: Asset class | L30: Min (%) | M30: Max (%) | S30: Asset class | T30: Min (%) | U30: Max (%) | AA30: Asset class | AB30: Min (%) | AC30: Max (%) | AI30: Asset class | AJ30: Min (%) | AK30: Max (%) | AQ30: Asset class | AR30: Min (%) | AS30: Max (%) | AY30: Asset class | AZ30: Min (%) | BA30: Max (%) | BG30: Asset class | BH30: Min (%) | BI30: Max (%) | BO30: Asset class | BP30: Min (%) | BQ30: Max (%) | BW30: Asset class | BX30: Min (%) | BY30: Max (%)
C31: Growth assets | K31: Growth assets | S31: Growth assets | AA31: Growth assets | AI31: Growth assets | AQ31: Growth assets | AY31: Growth assets | BG31: Growth assets | BO31: Growth assets | BW31: Growth assets
C32: Australian Equities | D32: ='Page Four - Portfolio Details'!D51 -> 0 | E32: ='Page Four - Portfolio Details'!F51 -> 0.85 | K32: Australian Equities | L32: ='Page Four - Portfolio Details'!N51 -> 0 | M32: ='Page Four - Portfolio Details'!P51 -> 0.2 | S32: Australian Equities | T32: ='Page Four - Portfolio Details'!X51 -> 0 | U32: ='Page Four - Portfolio Details'!Z51 -> 0 | AA32: Australian Equities | AB32: ='Page Four - Portfolio Details'!AH51 -> 0 | AC32: ='Page Four - Portfolio Details'!AJ51 -> 0 | AI32: Australian Equities | AJ32: ='Page Four - Portfolio Details'!AR51 -> 0 | AK32: ='Page Four - Portfolio Details'!AT51 -> 0 | AQ32: Australian Equities | AR32: ='Page Four - Portfolio Details'!BB51 -> 0 | AS32: ='Page Four - Portfolio Details'!BD51 -> 0 | AY32: Australian Equities | AZ32: ='Page Four - Portfolio Details'!BL51 -> 0 | BA32: ='Page Four - Portfolio Details'!BN51 -> 0 | BG32: Australian Equities | BH32: ='Page Four - Portfolio Details'!BV51 -> 0 | BI32: ='Page Four - Portfolio Details'!BX51 -> 0 | BO32: Australian Equities | BP32: ='Page Four - Portfolio Details'!CF51 -> 0 | BQ32: ='Page Four - Portfolio Details'!CH51 -> 0 | BW32: Australian Equities | BX32: ='Page Four - Portfolio Details'!CP51 -> 0 | BY32: ='Page Four - Portfolio Details'!CR51 -> 0
C33: International Equities | D33: ='Page Four - Portfolio Details'!D52 -> 0 | E33: ='Page Four - Portfolio Details'!F52 -> 0.85 | K33: International Equities | L33: ='Page Four - Portfolio Details'!N52 -> 0 | M33: ='Page Four - Portfolio Details'!P52 -> 0.2 | S33: International Equities | T33: ='Page Four - Portfolio Details'!X52 -> 0 | U33: ='Page Four - Portfolio Details'!Z52 -> 0 | AA33: International Equities | AB33: ='Page Four - Portfolio Details'!AH52 -> 0 | AC33: ='Page Four - Portfolio Details'!AJ52 -> 0 | AI33: International Equities | AJ33: ='Page Four - Portfolio Details'!AR52 -> 0 | AK33: ='Page Four - Portfolio Details'!AT52 -> 0 | AQ33: International Equities | AR33: ='Page Four - Portfolio Details'!BB52 -> 0 | AS33: ='Page Four - Portfolio Details'!BD52 -> 0 | AY33: International Equities | AZ33: ='Page Four - Portfolio Details'!BL52 -> 0 | BA33: ='Page Four - Portfolio Details'!BN52 -> 0 | BG33: International Equities | BH33: ='Page Four - Portfolio Details'!BV52 -> 0 | BI33: ='Page Four - Portfolio Details'!BX52 -> 0 | BO33: International Equities | BP33: ='Page Four - Portfolio Details'!CF52 -> 0 | BQ33: ='Page Four - Portfolio Details'!CH52 -> 0 | BW33: International Equities | BX33: ='Page Four - Portfolio Details'!CP52 -> 0 | BY33: ='Page Four - Portfolio Details'!CR52 -> 0
C34: Listed property/infrastructure | D34: ='Page Four - Portfolio Details'!D53 -> 0 | E34: ='Page Four - Portfolio Details'!F53 -> 0.35 | K34: Listed property/infrastructure | L34: ='Page Four - Portfolio Details'!N53 -> 0 | M34: ='Page Four - Portfolio Details'!P53 -> 0.2 | S34: Listed property/infrastructure | T34: ='Page Four - Portfolio Details'!X53 -> 0 | U34: ='Page Four - Portfolio Details'!Z53 -> 0 | AA34: Listed property/infrastructure | AB34: ='Page Four - Portfolio Details'!AH53 -> 0 | AC34: ='Page Four - Portfolio Details'!AJ53 -> 0 | AI34: Listed property/infrastructure | AJ34: ='Page Four - Portfolio Details'!AR53 -> 0 | AK34: ='Page Four - Portfolio Details'!AT53 -> 0 | AQ34: Listed property/infrastructure | AR34: ='Page Four - Portfolio Details'!BB53 -> 0 | AS34: ='Page Four - Portfolio Details'!BD53 -> 0 | AY34: Listed property/infrastructure | AZ34: ='Page Four - Portfolio Details'!BL53 -> 0 | BA34: ='Page Four - Portfolio Details'!BN53 -> 0 | BG34: Listed property/infrastructure | BH34: ='Page Four - Portfolio Details'!BV53 -> 0 | BI34: ='Page Four - Portfolio Details'!BX53 -> 0 | BO34: Listed property/infrastructure | BP34: ='Page Four - Portfolio Details'!CF53 -> 0 | BQ34: ='Page Four - Portfolio Details'!CH53 -> 0 | BW34: Listed property/infrastructure | BX34: ='Page Four - Portfolio Details'!CP53 -> 0 | BY34: ='Page Four - Portfolio Details'!CR53 -> 0
E35: ='Page Four - Portfolio Details'!F54 -> 0 | M35: ='Page Four - Portfolio Details'!P54 -> 0 | U35: ='Page Four - Portfolio Details'!Z54 -> 0 | AC35: ='Page Four - Portfolio Details'!AJ54 -> 0 | AK35: ='Page Four - Portfolio Details'!AT54 -> 0 | AS35: ='Page Four - Portfolio Details'!BD54 -> 0 | BA35: ='Page Four - Portfolio Details'!BN54 -> 0 | BI35: ='Page Four - Portfolio Details'!BX54 -> 0 | BQ35: ='Page Four - Portfolio Details'!CH54 -> 0 | BY35: ='Page Four - Portfolio Details'!CR54 -> 0
C36: Alternatives | D36: ='Page Four - Portfolio Details'!D55 -> 0 | E36: ='Page Four - Portfolio Details'!F55 -> 0.2 | K36: Alternatives | L36: ='Page Four - Portfolio Details'!N55 -> 0 | M36: ='Page Four - Portfolio Details'!P55 -> 0.2 | S36: Alternatives | T36: ='Page Four - Portfolio Details'!X55 -> 0 | U36: ='Page Four - Portfolio Details'!Z55 -> 0 | AA36: Alternatives | AB36: ='Page Four - Portfolio Details'!AH55 -> 0 | AC36: ='Page Four - Portfolio Details'!AJ55 -> 0 | AI36: Alternatives | AJ36: ='Page Four - Portfolio Details'!AR55 -> 0 | AK36: ='Page Four - Portfolio Details'!AT55 -> 0 | AQ36: Alternatives | AR36: ='Page Four - Portfolio Details'!BB55 -> 0 | AS36: ='Page Four - Portfolio Details'!BD55 -> 0 | AY36: Alternatives | AZ36: ='Page Four - Portfolio Details'!BL55 -> 0 | BA36: ='Page Four - Portfolio Details'!BN55 -> 0 | BG36: Alternatives | BH36: ='Page Four - Portfolio Details'!BV55 -> 0 | BI36: ='Page Four - Portfolio Details'!BX55 -> 0 | BO36: Alternatives | BP36: ='Page Four - Portfolio Details'!CF55 -> 0 | BQ36: ='Page Four - Portfolio Details'!CH55 -> 0 | BW36: Alternatives | BX36: ='Page Four - Portfolio Details'!CP55 -> 0 | BY36: ='Page Four - Portfolio Details'!CR55 -> 0
C37: Defensive assets | K37: Defensive assets | S37: Defensive assets | AA37: Defensive assets | AI37: Defensive assets | AQ37: Defensive assets | AY37: Defensive assets | BG37: Defensive assets | BO37: Defensive assets | BW37: Defensive assets
C38: Australian Fixed Interest | D38: ='Page Four - Portfolio Details'!D57 -> 0 | E38: ='Page Four - Portfolio Details'!F57 -> 0.19 | K38: Australian Fixed Interest | L38: ='Page Four - Portfolio Details'!N57 -> 0 | M38: ='Page Four - Portfolio Details'!P57 -> 0.98 | S38: Australian Fixed Interest | T38: ='Page Four - Portfolio Details'!X57 -> 0 | U38: ='Page Four - Portfolio Details'!Z57 -> 0 | AA38: Australian Fixed Interest | AB38: ='Page Four - Portfolio Details'!AH57 -> 0 | AC38: ='Page Four - Portfolio Details'!AJ57 -> 0 | AI38: Australian Fixed Interest | AJ38: ='Page Four - Portfolio Details'!AR57 -> 0 | AK38: ='Page Four - Portfolio Details'!AT57 -> 0 | AQ38: Australian Fixed Interest | AR38: ='Page Four - Portfolio Details'!BB57 -> 0 | AS38: ='Page Four - Portfolio Details'!BD57 -> 0 | AY38: Australian Fixed Interest | AZ38: ='Page Four - Portfolio Details'!BL57 -> 0 | BA38: ='Page Four - Portfolio Details'!BN57 -> 0 | BG38: Australian Fixed Interest | BH38: ='Page Four - Portfolio Details'!BV57 -> 0 | BI38: ='Page Four - Portfolio Details'!BX57 -> 0 | BO38: Australian Fixed Interest | BP38: ='Page Four - Portfolio Details'!CF57 -> 0 | BQ38: ='Page Four - Portfolio Details'!CH57 -> 0 | BW38: Australian Fixed Interest | BX38: ='Page Four - Portfolio Details'!CP57 -> 0 | BY38: ='Page Four - Portfolio Details'!CR57 -> 0
C39: International Fixed Interest | D39: ='Page Four - Portfolio Details'!D58 -> 0 | E39: ='Page Four - Portfolio Details'!F58 -> 0.19 | K39: International Fixed Interest | L39: ='Page Four - Portfolio Details'!N58 -> 0 | M39: ='Page Four - Portfolio Details'!P58 -> 0.98 | S39: International Fixed Interest | T39: ='Page Four - Portfolio Details'!X58 -> 0 | U39: ='Page Four - Portfolio Details'!Z58 -> 0 | AA39: International Fixed Interest | AB39: ='Page Four - Portfolio Details'!AH58 -> 0 | AC39: ='Page Four - Portfolio Details'!AJ58 -> 0 | AI39: International Fixed Interest | AJ39: ='Page Four - Portfolio Details'!AR58 -> 0 | AK39: ='Page Four - Portfolio Details'!AT58 -> 0 | AQ39: International Fixed Interest | AR39: ='Page Four - Portfolio Details'!BB58 -> 0 | AS39: ='Page Four - Portfolio Details'!BD58 -> 0 | AY39: International Fixed Interest | AZ39: ='Page Four - Portfolio Details'!BL58 -> 0 | BA39: ='Page Four - Portfolio Details'!BN58 -> 0 | BG39: International Fixed Interest | BH39: ='Page Four - Portfolio Details'!BV58 -> 0 | BI39: ='Page Four - Portfolio Details'!BX58 -> 0 | BO39: International Fixed Interest | BP39: ='Page Four - Portfolio Details'!CF58 -> 0 | BQ39: ='Page Four - Portfolio Details'!CH58 -> 0 | BW39: International Fixed Interest | BX39: ='Page Four - Portfolio Details'!CP58 -> 0 | BY39: ='Page Four - Portfolio Details'!CR58 -> 0
C40: Cash | D40: ='Page Four - Portfolio Details'!D59 -> 0.01 | E40: ='Page Four - Portfolio Details'!F59 -> 0.2 | K40: Cash | L40: ='Page Four - Portfolio Details'!N59 -> 0.01 | M40: ='Page Four - Portfolio Details'!P59 -> 1 | S40: Cash | T40: ='Page Four - Portfolio Details'!X59 -> 0 | U40: ='Page Four - Portfolio Details'!Z59 -> 0 | AA40: Cash | AB40: ='Page Four - Portfolio Details'!AH59 -> 0 | AC40: ='Page Four - Portfolio Details'!AJ59 -> 0 | AI40: Cash | AJ40: ='Page Four - Portfolio Details'!AR59 -> 0 | AK40: ='Page Four - Portfolio Details'!AT59 -> 0 | AQ40: Cash | AR40: ='Page Four - Portfolio Details'!BB59 -> 0 | AS40: ='Page Four - Portfolio Details'!BD59 -> 0 | AY40: Cash | AZ40: ='Page Four - Portfolio Details'!BL59 -> 0 | BA40: ='Page Four - Portfolio Details'!BN59 -> 0 | BG40: Cash | BH40: ='Page Four - Portfolio Details'!BV59 -> 0 | BI40: ='Page Four - Portfolio Details'!BX59 -> 0 | BO40: Cash | BP40: ='Page Four - Portfolio Details'!CF59 -> 0 | BQ40: ='Page Four - Portfolio Details'!CH59 -> 0 | BW40: Cash | BX40: ='Page Four - Portfolio Details'!CP59 -> 0 | BY40: ='Page Four - Portfolio Details'!CR59 -> 0
